Workbook
Name Cst_Médio_Lingote: Dados!$Q$2
Name CstMedKgFund: Dados!$N$4
Name CstOleoKgALuminio: Dados!$I$8
Name CustoOleoFornada: Dados!$I$7
Name Dias_Uteis: Dados!$Q$5
Name OleoKGAluminio: Dados!$I$4
Name Produto: Tabela2[Cód Placa - Descrição]
Name Produto: Tabela2[Cód Placa - Descrição]
Name Profissional: Tabela1[Nome]
Name Profissional: Tabela1[Nome]

Sheet Dados
A1: CUSTO MÉDIO | F1: CONSUMO OLEO / KG DE ALUMINIO | K1: Custo Médio Alumínio Fundido | P1: Tipo | Q1: Valor
A2: Descrição | B2: Qtde Total Compra | C2: Valor Total | D2: Custo Médio | F2: Total Aluminio | I2: =CmpLingote[[#Totals],[Qtde Aluminio]]+CmpSucata[[#Totals],[Qtde Aluminio]] -> 73689.1 | K2: Compras Total | N2: =Tabela8[[#Totals],[Valor Total]] -> 1039745.6 | P2: Lingote | Q2: =(VLOOKUP(TODAY(),CmpLingote[],3,TRUE))*1.1 -> 17.6
A3: Lingote | B3: =CmpLingote[[#Totals],[Qtde Aluminio]] -> 20524.8 | C3: =CmpLingote[[#Totals],[Total]] -> 400378.85 | D3: =Tabela8[[#This Row],[Valor Total]]/(Tabela8[[#This Row],[Qtde Total Compra]]*0.9) -> 21.67453 | F3: Total Oleo | I3: =CompraOleo[[#Totals],[QTDE OLEO]] -> 34101 | K3: Peso Aluminio Util | N3: =Tabela8[[#This Row],[Qtde Total Compra]]*0.9+B4*0.65 -> 53029.115 | P3: Sucata | Q3: =(VLOOKUP(TODAY(),CmpSucata[],3,TRUE))*1.3 -> 15.6
A4: Sucata | B4: =CmpSucata[[#Totals],[Qtde Aluminio]] -> 53164.3 | C4: =CmpSucata[[#Totals],[Total]] -> 542763.24 | D4: =Tabela8[[#This Row],[Valor Total]]/(Tabela8[[#This Row],[Qtde Total Compra]]*0.7) -> 14.584525 | F4: Cada Litro de Oleo Funde (KG Alum.) | I4: =I2/I3*1.1 -> 2.376998 | K4: Custo Médio/Kg Fundido | N4: =N2/N3 -> 19.60707 | P4: Mistura | Q4: =GEOMEAN(Q2:Q3) -> 16.569852
A5: Oleo | B5: =CompraOleo[[#Totals],[QTDE OLEO]] -> 34101 | C5: =CompraOleo[[#Totals],[Total]] -> 85252.5 | D5: =Tabela8[[#This Row],[Valor Total]]/(Tabela8[[#This Row],[Qtde Total Compra]]*0.95) -> 2.6315789 | F5: Capacidade do Fornada KG | I5: 180 | P5: Dias Uteis | Q5: 22
A6: Insumos | C6: =CompraInsumos[[#Totals],[Total]] -> 11351 | F6: Qtde Oléo/Fornada | I6: =I5/I4 -> 75.725767 | K6: Custo Lingote | N6: =CmpLingote[[#Totals],[Total]]/(CmpLingote[[#Totals],[Qtde Aluminio]]*0.9) -> 21.67453
A7: TOTAL | C7: =SUBTOTAL(109,Tabela8[Valor Total]) -> 1039745.6 | F7: Custo Oleo/Fornada | I7: =I6*D5 -> 199.27833 | K7: Custo Sucata | N7: =CmpSucata[[#Totals],[Total]]/(CmpSucata[[#Totals],[Qtde Aluminio]]*0.65) -> 15.706411
F8: Custo Oleo / Kg Fundido | I8: =I7/I5 -> 1.1071019
A11: COMPRAS LINGOTE | F11: COMPRAS SUCATA | K11: COMPRAS OLEO | P11: COMPRAS INSUMOS | S11: Custo Machos Kg
A12: Data | B12: Qtde Aluminio | C12: Custo/Kg Alumínio | D12: Total | F12: Data | G12: Qtde Aluminio | H12: Custo/Kg Alumínio | I12: Total | K12: Data | L12: QTDE OLEO | M12: CUSTO / L | N12: Total | P12: Data | Q12: Total | S12: Data | T12: Total
A13: 45688 | B13: 6675.3 | C13: 16 | D13: 192328.4 | F13: 45838 | G13: 20717.5 | H13: 10 | I13: 206393.59 | K13: 45658 | L13: 1 | M13: 2.5 | N13: =CompraOleo[[#This Row],[CUSTO / L]]*CompraOleo[[#This Row],[QTDE OLEO]] -> 2.5 | P13: 45838 | Q13: 3417.5 | S13: 45658 | T13: 1.5
A14: 45930 | B14: 3804.5 | C14: 16 | D14: 56786.15 | F14: 46295 | G14: 15683.8 | H14: 10 | I14: 155365.15 | K14: 45838 | L14: 11900 | M14: 2.5 | N14: =CompraOleo[[#This Row],[CUSTO / L]]*CompraOleo[[#This Row],[QTDE OLEO]] -> 29750 | P14: 45930 | Q14: 3042.5 | S14: 45748 | T14: 1.5
A15: 45991 | B15: 1035 | C15: 14.7 | D15: =CmpLingote[[#This Row],[Custo/Kg Alumínio]]*CmpLingote[[#This Row],[Qtde Aluminio]] -> 15214.5 | F15: 45961 | G15: 3486 | H15: 10 | I15: =CmpSucata[[#This Row],[Custo/Kg Alumínio]]*CmpSucata[[#This Row],[Qtde Aluminio]] -> 34860 | K15: 45930 | L15: 7000 | M15: 2.5 | N15: =CompraOleo[[#This Row],[CUSTO / L]]*CompraOleo[[#This Row],[QTDE OLEO]] -> 17500 | P15: 45961 | Q15: 1305 | S15: 45778 | T15: 1.5
A16: 46022 | B16: 1003 | C16: 14.7 | D16: =CmpLingote[[#This Row],[Custo/Kg Alumínio]]*CmpLingote[[#This Row],[Qtde Aluminio]] -> 14744.1 | F16: 45991 | G16: 3558 | H16: 10 | I16: =CmpSucata[[#This Row],[Qtde Aluminio]]*CmpSucata[[#This Row],[Custo/Kg Alumínio]] -> 35580 | K16: 45961 | L16: 2000 | M16: 2.5 | N16: =CompraOleo[[#This Row],[CUSTO / L]]*CompraOleo[[#This Row],[QTDE OLEO]] -> 5000 | P16: 45991 | Q16: 386 | S16: 45809 | T16: 1.7
A17: 46053 | B17: 1001 | C17: 14.7 | D17: =CmpLingote[[#This Row],[Custo/Kg Alumínio]]*CmpLingote[[#This Row],[Qtde Aluminio]] -> 14714.7 | F17: 46022 | G17: 887 | H17: 10 | I17: =CmpSucata[[#This Row],[Custo/Kg Alumínio]]*CmpSucata[[#This Row],[Qtde Aluminio]] -> 8870 | K17: 45991 | L17: 2000 | M17: 2.5 | N17: =CompraOleo[[#This Row],[CUSTO / L]]*CompraOleo[[#This Row],[QTDE OLEO]] -> 5000 | P17: 46022 | Q17: 305
A18: 46063 | B18: 1000 | C18: 15 | D18: =CmpLingote[[#This Row],[Custo/Kg Alumínio]]*CmpLingote[[#This Row],[Qtde Aluminio]] -> 15000 | F18: 46053 | G18: 2357.5 | H18: 12 | I18: =CmpSucata[[#This Row],[Custo/Kg Alumínio]]*CmpSucata[[#This Row],[Qtde Aluminio]] -> 28290 | K18: 46022 | L18: 1000 | M18: 2.5 | N18: =CompraOleo[[#This Row],[CUSTO / L]]*CompraOleo[[#This Row],[QTDE OLEO]] -> 2500 | P18: 46053 | Q18: =500+295 -> 795
A19: 46083 | B19: 1004 | C19: 15 | D19: =CmpLingote[[#This Row],[Custo/Kg Alumínio]]*CmpLingote[[#This Row],[Qtde Aluminio]] -> 15060 | F19: 46066 | G19: =600+474+427 -> 1501 | H19: 11 | I19: =CmpSucata[[#This Row],[Custo/Kg Alumínio]]*CmpSucata[[#This Row],[Qtde Aluminio]] -> 16511 | K19: 46053 | L19: 1000 | M19: 2.5 | N19: =CompraOleo[[#This Row],[CUSTO / L]]*CompraOleo[[#This Row],[QTDE OLEO]] -> 2500 | P19: 46081 | Q19: 500
A20: 46098 | B20: 1000 | C20: 15 | D20: =CmpLingote[[#This Row],[Custo/Kg Alumínio]]*CmpLingote[[#This Row],[Qtde Aluminio]] -> 15000 | F20: 46085 | G20: 606 | H20: 10 | I20: =CmpSucata[[#This Row],[Custo/Kg Alumínio]]*CmpSucata[[#This Row],[Qtde Aluminio]] -> 6060 | K20: 46056 | L20: 1000 | M20: 2.5 | N20: =CompraOleo[[#This Row],[CUSTO / L]]*CompraOleo[[#This Row],[QTDE OLEO]] -> 2500 | P20: 46112 | Q20: 500
A21: 46106 | B21: 1001 | C21: 15 | D21: =CmpLingote[[#This Row],[Custo/Kg Alumínio]]*CmpLingote[[#This Row],[Qtde Aluminio]] -> 15015 | F21: 46090 | G21: 547 | H21: 10 | I21: =CmpSucata[[#This Row],[Custo/Kg Alumínio]]*CmpSucata[[#This Row],[Qtde Aluminio]] -> 5470 | K21: 46076 | L21: 1000 | M21: 2.5 | N21: =CompraOleo[[#This Row],[CUSTO / L]]*CompraOleo[[#This Row],[QTDE OLEO]] -> 2500 | P21: 46142 | Q21: 600
A22: 46133 | B22: 1000 | C22: 15 | D22: =CmpLingote[[#This Row],[Custo/Kg Alumínio]]*CmpLingote[[#This Row],[Qtde Aluminio]] -> 15000 | F22: 46092 | G22: 816.5 | H22: 12 | I22: =CmpSucata[[#This Row],[Custo/Kg Alumínio]]*CmpSucata[[#This Row],[Qtde Aluminio]] -> 9798 | K22: 46085 | L22: 1000 | M22: 2.5 | N22: =CompraOleo[[#This Row],[CUSTO / L]]*CompraOleo[[#This Row],[QTDE OLEO]] -> 2500 | P22: 46172 | Q22: 500
A23: 46141 | B23: 1000 | C23: 15.5 | D23: =CmpLingote[[#This Row],[Custo/Kg Alumínio]]*CmpLingote[[#This Row],[Qtde Aluminio]] -> 15500 | F23: 46099 | G23: 96.5 | H23: 7 | I23: =CmpSucata[[#This Row],[Custo/Kg Alumínio]]*CmpSucata[[#This Row],[Qtde Aluminio]] -> 675.5 | K23: 46094 | L23: 1000 | M23: 2.5 | N23: =CompraOleo[[#This Row],[CUSTO / L]]*CompraOleo[[#This Row],[QTDE OLEO]] -> 2500
A24: 46161 | B24: 1001 | C24: 16 | D24: =CmpLingote[[#This Row],[Custo/Kg Alumínio]]*CmpLingote[[#This Row],[Qtde Aluminio]] -> 16016 | F24: 46122 | G24: 1607 | H24: 12 | I24: =CmpSucata[[#This Row],[Custo/Kg Alumínio]]*CmpSucata[[#This Row],[Qtde Aluminio]] -> 19284 | K24: 46106 | L24: 1000 | M24: 2.5 | N24: =CompraOleo[[#This Row],[CUSTO / L]]*CompraOleo[[#This Row],[QTDE OLEO]] -> 2500
D25: =CmpLingote[[#This Row],[Custo/Kg Alumínio]]*CmpLingote[[#This Row],[Qtde Aluminio]] -> 0 | F25: 46149 | G25: 710 | H25: 12 | I25: =CmpSucata[[#This Row],[Custo/Kg Alumínio]]*CmpSucata[[#This Row],[Qtde Aluminio]] -> 8520 | K25: 46114 | L25: 1000 | M25: 2.5 | N25: =CompraOleo[[#This Row],[CUSTO / L]]*CompraOleo[[#This Row],[QTDE OLEO]] -> 2500
D26: =CmpLingote[[#This Row],[Custo/Kg Alumínio]]*CmpLingote[[#This Row],[Qtde Aluminio]] -> 0 | F26: 46161 | G26: 590.5 | H26: 12 | I26: =CmpSucata[[#This Row],[Custo/Kg Alumínio]]*CmpSucata[[#This Row],[Qtde Aluminio]] -> 7086 | K26: 46122 | L26: 800 | M26: 2.5 | N26: =CompraOleo[[#This Row],[CUSTO / L]]*CompraOleo[[#This Row],[QTDE OLEO]] -> 2000 | T26: =SUBTOTAL(101,Tabela461213[Total]) -> 1.55
D27: =CmpLingote[[#This Row],[Custo/Kg Alumínio]]*CmpLingote[[#This Row],[Qtde Aluminio]] -> 0 | K27: 46133 | L27: 800 | M27: 2.5 | N27: =CompraOleo[[#This Row],[CUSTO / L]]*CompraOleo[[#This Row],[QTDE OLEO]] -> 2000 | Q27: =SUBTOTAL(109,CompraInsumos[Total]) -> 11351
D28: =CmpLingote[[#This Row],[Custo/Kg Alumínio]]*CmpLingote[[#This Row],[Qtde Aluminio]] -> 0 | K28: 46149 | L28: 800 | M28: 2.5 | N28: =CompraOleo[[#This Row],[CUSTO / L]]*CompraOleo[[#This Row],[QTDE OLEO]] -> 2000
K29: 46160 | L29: 800 | M29: 2.5 | N29: =CompraOleo[[#This Row],[CUSTO / L]]*CompraOleo[[#This Row],[QTDE OLEO]] -> 2000
B33: =SUBTOTAL(109,CmpLingote[Qtde Aluminio]) -> 20524.8 | D33: =SUBTOTAL(109,CmpLingote[Total]) -> 400378.85 | G33: =SUBTOTAL(109,CmpSucata[Qtde Aluminio]) -> 53164.3 | I33: =SUBTOTAL(109,CmpSucata[Total]) -> 542763.24 | L33: =SUBTOTAL(109,CompraOleo[QTDE OLEO]) -> 34101 | M33: =SUBTOTAL(101,CompraOleo[CUSTO / L]) -> 2.5 | N33: =SUBTOTAL(109,CompraOleo[Total]) -> 85252.5

Sheet Profissionais
A1: Nome | B1: Função | C1: Salário | D1: Cartão | E1: Custo/h
A2: Marcelo Santos | B2: Moldador | C2: 2968 | D2: 500 | E2: =(Tabela1[[#This Row],[Salário]]*1.45+Tabela1[[#This Row],[Cartão]])/180*1.05 -> 28.021 | J2: Moldador | K2: 30.26
A3: Daniel Garcia | B3: Moldador | C3: 2968 | D3: 500 | E3: =(Tabela1[[#This Row],[Salário]]*1.45+Tabela1[[#This Row],[Cartão]])/180*1.05 -> 28.021 | J3: Moldador | K3: 30.26
A4: Claudio Henrique | B4: Ajudante | C4: 2236.6 | D4: 280 | E4: =(Tabela1[[#This Row],[Salário]]*1.45+Tabela1[[#This Row],[Cartão]])/180*1.05 -> 20.551242 | J4: Ajudante | K4: 23
A5: Anderson | B5: Ajudante | C5: 2236.6 | D5: 280 | E5: =(Tabela1[[#This Row],[Salário]]*1.45+Tabela1[[#This Row],[Cartão]])/180*1.05 -> 20.551242 | J5: Ajudante | K5: 23
A6: Renan Gabriel | B6: Ajudante | C6: 2236.6 | D6: 280 | E6: =(Tabela1[[#This Row],[Salário]]*1.45+Tabela1[[#This Row],[Cartão]])/180*1.05 -> 20.551242 | J6: Rebarbador | K6: 23
A7: Victor Hugo | B7: Ajudante | C7: 2236.6 | D7: 280 | E7: =(Tabela1[[#This Row],[Salário]]*1.45+Tabela1[[#This Row],[Cartão]])/180*1.05 -> 20.551242
A8: William | B8: Forno | C8: 2968 | D8: 500 | E8: =(Tabela1[[#This Row],[Salário]]*1.45+Tabela1[[#This Row],[Cartão]])/180*1.05 -> 28.021 | J8: Acabamento | K8: 46
A9: João Paulo | B9: Ajudante | C9: 2236.6 | D9: 280 | E9: =(Tabela1[[#This Row],[Salário]]*1.45+Tabela1[[#This Row],[Cartão]])/180*1.05 -> 20.551242
A10: Marco W | B10: Ajudante | C10: 2236.6 | D10: 280 | E10: =(Tabela1[[#This Row],[Salário]]*1.45+Tabela1[[#This Row],[Cartão]])/180*1.05 -> 20.551242
A11: Marlon | B11: Ajudante | C11: 2236.6 | D11: 280 | E11: =(Tabela1[[#This Row],[Salário]]*1.45+Tabela1[[#This Row],[Cartão]])/180*1.05 -> 20.551242

Sheet Produtos
A1: Cód Placa - Descrição | B1: Qdt Peça Placa | C1: Peso Pç | D1: Peso Total Galho | E1: Retorno | F1: Peso Caixa Areia | G1: Qde macho / CX | H1: Peso Macho | I1: Caixa Usada | J1: Cód Cx Macho | K1: Cód Placa | L1: Tipo de Material | M1: Prço/Kg | N1: Cliente | O1: Usinagem Pintura Outros
A2: 276003 Flange Distribuidor De Ar / REGULADOR 26002 - Fundido | B2: 2 | D2: 0 | E2: =((Tabela2[[#This Row],[Peso Total Galho]]-(Tabela2[[#This Row],[Peso Pç]]*Tabela2[[#This Row],[Qdt Peça Placa]]))*0.9) -> 0 | L2: Sucata | M2: =VLOOKUP(Tabela2[[#This Row],[Tipo de Material]],Dados!$P$2:$Q$4,2,FALSE) -> 15.6 | N2: Jumil | O2: 3
A3: 2766811 POLIA FUNDIDO | B3: 1 | C3: 1.885 | D3: 3.335 | E3: =((Tabela2[[#This Row],[Peso Total Galho]]-(Tabela2[[#This Row],[Peso Pç]]*Tabela2[[#This Row],[Qdt Peça Placa]]))*0.9) -> 1.305 | L3: Sucata | M3: =VLOOKUP(Tabela2[[#This Row],[Tipo de Material]],Dados!$P$2:$Q$4,2,FALSE) -> 15.6 | N3: Jumil | O3: 4
A4: Corpo Visor Agua / Luz Fundido | B4: 2 | C4: 0.444 | D4: 1.452 | E4: =((Tabela2[[#This Row],[Peso Total Galho]]-(Tabela2[[#This Row],[Peso Pç]]*Tabela2[[#This Row],[Qdt Peça Placa]]))*0.9) -> 0.5076 | L4: Sucata | M4: =VLOOKUP(Tabela2[[#This Row],[Tipo de Material]],Dados!$P$2:$Q$4,2,FALSE) -> 15.6 | N4: Senun | O4: 5
A5: PROTEC TITAN 150 ES | B5: 1 | C5: 1.2 | D5: 1.85 | E5: =((Tabela2[[#This Row],[Peso Total Galho]]-(Tabela2[[#This Row],[Peso Pç]]*Tabela2[[#This Row],[Qdt Peça Placa]]))*0.9) -> 0.585 | L5: Lingote | M5: =VLOOKUP(Tabela2[[#This Row],[Tipo de Material]],Dados!$P$2:$Q$4,2,FALSE) -> 17.6 | N5: Protec
A6: 0429005 TAMPA DO DISTRIBUIDOR (0432527P) | B6: 1 | C6: 2.99 | D6: 5.29 | E6: =((Tabela2[[#This Row],[Peso Total Galho]]-(Tabela2[[#This Row],[Peso Pç]]*Tabela2[[#This Row],[Qdt Peça Placa]]))*0.9) -> 2.07 | G6: 1 | H6: 2 | J6: 400411 | L6: Sucata | M6: =VLOOKUP(Tabela2[[#This Row],[Tipo de Material]],Dados!$P$2:$Q$4,2,FALSE) -> 15.6 | N6: Jumil | O6: 1
A7: 0429011 ARO | B7: 1 | C7: 1 | D7: 1.8 | E7: =((Tabela2[[#This Row],[Peso Total Galho]]-(Tabela2[[#This Row],[Peso Pç]]*Tabela2[[#This Row],[Qdt Peça Placa]]))*0.9) -> 0.72 | L7: Sucata | M7: =VLOOKUP(Tabela2[[#This Row],[Tipo de Material]],Dados!$P$2:$Q$4,2,FALSE) -> 15.6 | N7: Jumil | O7: 4
A8: 0429013 BICA DUPLA (0432155P) | B8: 4 | C8: 0.185 | D8: 1.308 | E8: =((Tabela2[[#This Row],[Peso Total Galho]]-(Tabela2[[#This Row],[Peso Pç]]*Tabela2[[#This Row],[Qdt Peça Placa]]))*0.9) -> 0.5112 | G8: 4 | H8: 0.175 | J8: 400420 | L8: Sucata | M8: =VLOOKUP(Tabela2[[#This Row],[Tipo de Material]],Dados!$P$2:$Q$4,2,FALSE) -> 15.6 | N8: Jumil | O8: 1
A9: 0460277 TAMPA DO DISTRIBUIDOR (0460276P) | B9: 1 | C9: 1.8 | D9: 2 | E9: =((Tabela2[[#This Row],[Peso Total Galho]]-(Tabela2[[#This Row],[Peso Pç]]*Tabela2[[#This Row],[Qdt Peça Placa]]))*0.9) -> 0.18 | G9: 1 | H9: 2.03 | J9: 400421 | L9: Sucata | M9: =VLOOKUP(Tabela2[[#This Row],[Tipo de Material]],Dados!$P$2:$Q$4,2,FALSE) -> 15.6 | N9: Jumil | O9: 15
A10: 2760002 Regulador (3225354P) Fundido | B10: 4 | C10: 0.218 | D10: 1.544 | E10: =((Tabela2[[#This Row],[Peso Total Galho]]-(Tabela2[[#This Row],[Peso Pç]]*Tabela2[[#This Row],[Qdt Peça Placa]]))*0.9) -> 0.6048 | L10: Sucata | M10: =VLOOKUP(Tabela2[[#This Row],[Tipo de Material]],Dados!$P$2:$Q$4,2,FALSE) -> 15.6 | N10: Jumil | O10: 3
A11: 2760173 Base Do Condutor Da Semente (2749842P) Fundido | B11: 2 | C11: 1.15 | D11: 4.06 | E11: =((Tabela2[[#This Row],[Peso Total Galho]]-(Tabela2[[#This Row],[Peso Pç]]*Tabela2[[#This Row],[Qdt Peça Placa]]))*0.9) -> 1.584 | L11: Sucata | M11: =VLOOKUP(Tabela2[[#This Row],[Tipo de Material]],Dados!$P$2:$Q$4,2,FALSE) -> 15.6 | N11: Jumil | O11: 8
A12: 2760174 Condutor Inclinado (2749843P) Fundido | B12: 2 | C12: 0.737 | D12: 2.608 | E12: =((Tabela2[[#This Row],[Peso Total Galho]]-(Tabela2[[#This Row],[Peso Pç]]*Tabela2[[#This Row],[Qdt Peça Placa]]))*0.9) -> 1.0206 | G12: 2 | H12: 0.49 | J12: 400418/01 | L12: Sucata | M12: =VLOOKUP(Tabela2[[#This Row],[Tipo de Material]],Dados!$P$2:$Q$4,2,FALSE) -> 15.6 | N12: Jumil | O12: 1
A13: 2760211 Tapo Deposito Unico De Sementes (2749147P) Fundido | D13: 0 | E13: =((Tabela2[[#This Row],[Peso Total Galho]]-(Tabela2[[#This Row],[Peso Pç]]*Tabela2[[#This Row],[Qdt Peça Placa]]))*0.9) -> 0 | L13: Sucata | M13: =VLOOKUP(Tabela2[[#This Row],[Tipo de Material]],Dados!$P$2:$Q$4,2,FALSE) -> 15.6 | N13: Jumil | O13: 8
A14: 2760315 Base do Depósito (2729990P) - FUNDIDO | B14: 4 | C14: 0.784 | D14: 5.548 | E14: =((Tabela2[[#This Row],[Peso Total Galho]]-(Tabela2[[#This Row],[Peso Pç]]*Tabela2[[#This Row],[Qdt Peça Placa]]))*0.9) -> 2.1708 | G14: 12 | H14: 2.662 | J14: 400403 | L14: Sucata | M14: =VLOOKUP(Tabela2[[#This Row],[Tipo de Material]],Dados!$P$2:$Q$4,2,FALSE) -> 15.6 | N14: Jumil | O14: 8
A15: 2766824 Distribuidor de Ar 12s - FUNDIDO | B15: 1 | C15: 2.47 | D15: 1.8 | E15: =((Tabela2[[#This Row],[Peso Total Galho]]-(Tabela2[[#This Row],[Peso Pç]]*Tabela2[[#This Row],[Qdt Peça Placa]]))*0.9) -> -0.603 | G15: 1 | H15: 3.006 | J15: 400417 | L15: Sucata | M15: =VLOOKUP(Tabela2[[#This Row],[Tipo de Material]],Dados!$P$2:$Q$4,2,FALSE) -> 15.6 | N15: Jumil | O15: 4
A16: 9990066 - Marcação luva 3,5x7 / 4x7 / 5x4 / Bacia - Fundido | B16: 3 | C16: 0.412 | D16: 3.036 | E16: =((Tabela2[[#This Row],[Peso Total Galho]]-(Tabela2[[#This Row],[Peso Pç]]*Tabela2[[#This Row],[Qdt Peça Placa]]))*0.9) -> 1.62 | L16: Lingote | M16: =VLOOKUP(Tabela2[[#This Row],[Tipo de Material]],Dados!$P$2:$Q$4,2,FALSE) -> 17.6 | N16: Oscar | O16: 4
A17: 9990066 - Varão 1 / 2 / 3 / 4 - Fundido | B17: 4 | C17: 0.412 | D17: 4.048 | E17: =((Tabela2[[#This Row],[Peso Total Galho]]-(Tabela2[[#This Row],[Peso Pç]]*Tabela2[[#This Row],[Qdt Peça Placa]]))*0.9) -> 2.16 | L17: Lingote | M17: =VLOOKUP(Tabela2[[#This Row],[Tipo de Material]],Dados!$P$2:$Q$4,2,FALSE) -> 17.6 | N17: Oscar | O17: 4
A18: Acoplador 2750340 - FUNDIDO | B18: 3 | C18: 0.884 | D18: 4.692 | E18: =((Tabela2[[#This Row],[Peso Total Galho]]-(Tabela2[[#This Row],[Peso Pç]]*Tabela2[[#This Row],[Qdt Peça Placa]]))*0.9) -> 1.836 | G18: 9 | H18: 1.401 | J18: 400401 | L18: Sucata | M18: =VLOOKUP(Tabela2[[#This Row],[Tipo de Material]],Dados!$P$2:$Q$4,2,FALSE) -> 15.6 | N18: Jumil | O18: 10
A19: ACOPLADOR DO PRATO - DANILO | B19: 1 | C19: 1.1 | D19: 1.6 | E19: =((Tabela2[[#This Row],[Peso Total Galho]]-(Tabela2[[#This Row],[Peso Pç]]*Tabela2[[#This Row],[Qdt Peça Placa]]))*0.9) -> 0.45 | L19: Lingote | M19: =VLOOKUP(Tabela2[[#This Row],[Tipo de Material]],Dados!$P$2:$Q$4,2,FALSE) -> 17.6 | N19: Danilo
A20: ADAPTADOR 0429051 | B20: 22 | C20: 0.024 | D20: 1.65 | E20: =((Tabela2[[#This Row],[Peso Total Galho]]-(Tabela2[[#This Row],[Peso Pç]]*Tabela2[[#This Row],[Qdt Peça Placa]]))*0.9) -> 1.0098 | L20: Sucata | M20: =VLOOKUP(Tabela2[[#This Row],[Tipo de Material]],Dados!$P$2:$Q$4,2,FALSE) -> 15.6 | N20: Jumil | O20: 1
A21: ALÇA TRASEIRA TITAN DIR. ( PROTEC ) | B21: 2 | C21: 0.6 | D21: 2.2 | E21: =((Tabela2[[#This Row],[Peso Total Galho]]-(Tabela2[[#This Row],[Peso Pç]]*Tabela2[[#This Row],[Qdt Peça Placa]]))*0.9) -> 0.9 | L21: Lingote | M21: =VLOOKUP(Tabela2[[#This Row],[Tipo de Material]],Dados!$P$2:$Q$4,2,FALSE) -> 17.6 | N21: Protec
A22: ALÇA TRASEIRA TITAN ESQ. ( PROTEC ) | B22: 2 | C22: 0.6 | D22: 2.2 | E22: =((Tabela2[[#This Row],[Peso Total Galho]]-(Tabela2[[#This Row],[Peso Pç]]*Tabela2[[#This Row],[Qdt Peça Placa]]))*0.9) -> 0.9 | L22: Lingote | M22: =VLOOKUP(Tabela2[[#This Row],[Tipo de Material]],Dados!$P$2:$Q$4,2,FALSE) -> 17.6 | N22: Protec
A23: ANEL 300mm - TRATOMAG | B23: 1 | C23: 19.2 | D23: 20.6 | E23: =((Tabela2[[#This Row],[Peso Total Galho]]-(Tabela2[[#This Row],[Peso Pç]]*Tabela2[[#This Row],[Qdt Peça Placa]]))*0.9) -> 1.26 | L23: Lingote | M23: =VLOOKUP(Tabela2[[#This Row],[Tipo de Material]],Dados!$P$2:$Q$4,2,FALSE) -> 17.6 | N23: TRATOMAG
A24: BASE DE ACENTAMENTO DO DEPOSITO - FUNDIDO | B24: 4 | C24: 0.774 | D24: 5.472 | E24: =((Tabela2[[#This Row],[Peso Total Galho]]-(Tabela2[[#This Row],[Peso Pç]]*Tabela2[[#This Row],[Qdt Peça Placa]]))*0.9) -> 2.1384 | L24: Sucata | M24: =VLOOKUP(Tabela2[[#This Row],[Tipo de Material]],Dados!$P$2:$Q$4,2,FALSE) -> 15.6 | N24: Jumil | O24: 4
A25: Base Depósito Semente 2760317 (2749444P) - FUNDIDO | B25: 6 | C25: 0.78 | D25: 8.28 | E25: =((Tabela2[[#This Row],[Peso Total Galho]]-(Tabela2[[#This Row],[Peso Pç]]*Tabela2[[#This Row],[Qdt Peça Placa]]))*0.9) -> 3.24 | G25: 1 | H25: 4.982 | J25: 400402 | L25: Sucata | M25: =VLOOKUP(Tabela2[[#This Row],[Tipo de Material]],Dados!$P$2:$Q$4,2,FALSE) -> 15.6 | N25: Jumil | O25: 10
A26: Base do Deposito 2761086 Fundido | B26: 4 | C26: 0.795 | D26: 5.628 | E26: =((Tabela2[[#This Row],[Peso Total Galho]]-(Tabela2[[#This Row],[Peso Pç]]*Tabela2[[#This Row],[Qdt Peça Placa]]))*0.9) -> 2.2032 | G26: 4 | H26: 1.115 | J26: 400403 | L26: Sucata | M26: =VLOOKUP(Tabela2[[#This Row],[Tipo de Material]],Dados!$P$2:$Q$4,2,FALSE) -> 15.6 | N26: Jumil | O26: 5
A27: BIELA M42 | B27: 10 | C27: 0.16 | D27: 2.5 | E27: =((Tabela2[[#This Row],[Peso Total Galho]]-(Tabela2[[#This Row],[Peso Pç]]*Tabela2[[#This Row],[Qdt Peça Placa]]))*0.9) -> 0.81 | L27: Lingote | M27: =VLOOKUP(Tabela2[[#This Row],[Tipo de Material]],Dados!$P$2:$Q$4,2,FALSE) -> 17.6 | N27: MGA
A28: BLOCO FUNDIDO - MGA | B28: 3 | C28: 2.5 | D28: 8.4 | E28: =((Tabela2[[#This Row],[Peso Total Galho]]-(Tabela2[[#This Row],[Peso Pç]]*Tabela2[[#This Row],[Qdt Peça Placa]]))*0.9) -> 0.81 | L28: Lingote | M28: =VLOOKUP(Tabela2[[#This Row],[Tipo de Material]],Dados!$P$2:$Q$4,2,FALSE) -> 17.6 | N28: MGA
A29: Bocal de Saida 0429034 Fundido | B29: 1 | C29: 1.95 | D29: 2.4 | E29: =((Tabela2[[#This Row],[Peso Total Galho]]-(Tabela2[[#This Row],[Peso Pç]]*Tabela2[[#This Row],[Qdt Peça Placa]]))*0.9) -> 0.405 | G29: 1 | L29: Sucata | M29: =VLOOKUP(Tabela2[[#This Row],[Tipo de Material]],Dados!$P$2:$Q$4,2,FALSE) -> 15.6 | N29: Jumil | O29: 1
A30: Bocal de Saida 2761392 / 0429008 Fundido | B30: 1 | C30: 1.95 | D30: 3.45 | E30: =((Tabela2[[#This Row],[Peso Total Galho]]-(Tabela2[[#This Row],[Peso Pç]]*Tabela2[[#This Row],[Qdt Peça Placa]]))*0.9) -> 1.35 | L30: Sucata | M30: =VLOOKUP(Tabela2[[#This Row],[Tipo de Material]],Dados!$P$2:$Q$4,2,FALSE) -> 15.6 | N30: Jumil | O30: 1
A31: BRACINHO ARTICULADOR | B31: 4 | C31: 0.5 | D31: 3.2 | E31: =((Tabela2[[#This Row],[Peso Total Galho]]-(Tabela2[[#This Row],[Peso Pç]]*Tabela2[[#This Row],[Qdt Peça Placa]]))*0.9) -> 1.08 | L31: Lingote | M31: =VLOOKUP(Tabela2[[#This Row],[Tipo de Material]],Dados!$P$2:$Q$4,2,FALSE) -> 17.6 | N31: Marcelo
A32: CABEÇOTE DUPLO - DANILO | B32: 1 | C32: 20 | D32: 22.3 | E32: =((Tabela2[[#This Row],[Peso Total Galho]]-(Tabela2[[#This Row],[Peso Pç]]*Tabela2[[#This Row],[Qdt Peça Placa]]))*0.9) -> 2.07 | L32: Mistura | M32: =VLOOKUP(Tabela2[[#This Row],[Tipo de Material]],Dados!$P$2:$Q$4,2,FALSE) -> 16.569852 | N32: Danilo
A33: Cachimbo Fundido 33 (-) Fundido | B33: 12 | C33: 0.262 | D33: 5.57 | E33: =((Tabela2[[#This Row],[Peso Total Galho]]-(Tabela2[[#This Row],[Peso Pç]]*Tabela2[[#This Row],[Qdt Peça Placa]]))*0.9) -> 2.1834 | L33: Lingote | M33: =VLOOKUP(Tabela2[[#This Row],[Tipo de Material]],Dados!$P$2:$Q$4,2,FALSE) -> 17.6 | N33: Marcelo | O33: 5
A34: Cachimbo Fundido 34,5 (+) Fundido | B34: 12 | C34: 0.262 | D34: 5.568 | E34: =((Tabela2[[#This Row],[Peso Total Galho]]-(Tabela2[[#This Row],[Peso Pç]]*Tabela2[[#This Row],[Qdt Peça Placa]]))*0.9) -> 2.1816 | L34: Lingote | M34: =VLOOKUP(Tabela2[[#This Row],[Tipo de Material]],Dados!$P$2:$Q$4,2,FALSE) -> 17.6 | N34: Marcelo | O34: 1
A35: CAIXA DA TAMPA 40 Kg - DANILO | B35: 1 | C35: 40 | D35: 40.3 | E35: =((Tabela2[[#This Row],[Peso Total Galho]]-(Tabela2[[#This Row],[Peso Pç]]*Tabela2[[#This Row],[Qdt Peça Placa]]))*0.9) -> 0.27 | L35: Mistura | M35: =VLOOKUP(Tabela2[[#This Row],[Tipo de Material]],Dados!$P$2:$Q$4,2,FALSE) -> 16.569852 | N35: Danilo
A36: CAIXA TUDO DESCO EXATA | B36: 2 | C36: 1.9 | D36: 4.7 | E36: =((Tabela2[[#This Row],[Peso Total Galho]]-(Tabela2[[#This Row],[Peso Pç]]*Tabela2[[#This Row],[Qdt Peça Placa]]))*0.9) -> 0.81 | L36: Lingote | M36: =VLOOKUP(Tabela2[[#This Row],[Tipo de Material]],Dados!$P$2:$Q$4,2,FALSE) -> 17.6 | N36: Marcelo
A37: Caracol HX55 - Fundido | B37: 1 | C37: 3.1 | D37: 3.8 | E37: =((Tabela2[[#This Row],[Peso Total Galho]]-(Tabela2[[#This Row],[Peso Pç]]*Tabela2[[#This Row],[Qdt Peça Placa]]))*0.9) -> 0.63 | G37: 2 | H37: 1.25 | J37: 400301 | L37: Lingote | M37: =VLOOKUP(Tabela2[[#This Row],[Tipo de Material]],Dados!$P$2:$Q$4,2,FALSE) -> 17.6 | N37: Oscar | O37: 20
A38: Caracol S300 John Deere 3520 - Fundido | B38: 1 | C38: 2 | D38: 2.4 | E38: =((Tabela2[[#This Row],[Peso Total Galho]]-(Tabela2[[#This Row],[Peso Pç]]*Tabela2[[#This Row],[Qdt Peça Placa]]))*0.9) -> 0.36 | G38: 2 | H38: 1.175 | J38: 400302 | L38: Lingote | M38: =VLOOKUP(Tabela2[[#This Row],[Tipo de Material]],Dados!$P$2:$Q$4,2,FALSE) -> 17.6 | N38: Oscar | O38: 20
A39: CARCAÇA T-924 | B39: 4 | C39: 0.425 | D39: 2.4 | E39: =((Tabela2[[#This Row],[Peso Total Galho]]-(Tabela2[[#This Row],[Peso Pç]]*Tabela2[[#This Row],[Qdt Peça Placa]]))*0.9) -> 0.63 | L39: Lingote | M39: =VLOOKUP(Tabela2[[#This Row],[Tipo de Material]],Dados!$P$2:$Q$4,2,FALSE) -> 17.6 | N39: TPA/TEMPLA
A40: CARCAÇA T-925 | B40: 4 | C40: 0.575 | D40: 3.4 | E40: =((Tabela2[[#This Row],[Peso Total Galho]]-(Tabela2[[#This Row],[Peso Pç]]*Tabela2[[#This Row],[Qdt Peça Placa]]))*0.9) -> 0.99 | L40: Lingote | M40: =VLOOKUP(Tabela2[[#This Row],[Tipo de Material]],Dados!$P$2:$Q$4,2,FALSE) -> 17.6 | N40: TPA/TEMPLA
A41: Centro da Banda (3224429P) - Fundido | B41: 1 | C41: 1.69 | D41: 2.99 | E41: =((Tabela2[[#This Row],[Peso Total Galho]]-(Tabela2[[#This Row],[Peso Pç]]*Tabela2[[#This Row],[Qdt Peça Placa]]))*0.9) -> 1.17 | L41: Sucata | M41: =VLOOKUP(Tabela2[[#This Row],[Tipo de Material]],Dados!$P$2:$Q$4,2,FALSE) -> 15.6 | N41: Jumil | O41: 8
A42: Chapa Churrasqueira 1 Fogareiro - Fundido | B42: 1 | C42: 1.402 | D42: 1.95 | E42: =((Tabela2[[#This Row],[Peso Total Galho]]-(Tabela2[[#This Row],[Peso Pç]]*Tabela2[[#This Row],[Qdt Peça Placa]]))*0.9) -> 0.4932 | L42: Sucata | M42: =VLOOKUP(Tabela2[[#This Row],[Tipo de Material]],Dados!$P$2:$Q$4,2,FALSE) -> 15.6 | N42: Senun | O42: 6
A43: Chapa Churrasqueira 2 Fogareiros Fundido | B43: 1 | C43: 3.142 | D43: 5.559 | E43: =((Tabela2[[#This Row],[Peso Total Galho]]-(Tabela2[[#This Row],[Peso Pç]]*Tabela2[[#This Row],[Qdt Peça Placa]]))*0.9) -> 2.1753 | L43: Sucata | M43: =VLOOKUP(Tabela2[[#This Row],[Tipo de Material]],Dados!$P$2:$Q$4,2,FALSE) -> 15.6 | N43: Senun | O43: 6.5
A44: Condutor Reto 2760209 - fundido | B44: 6 | C44: 0.4 | D44: 3.6 | E44: =((Tabela2[[#This Row],[Peso Total Galho]]-(Tabela2[[#This Row],[Peso Pç]]*Tabela2[[#This Row],[Qdt Peça Placa]]))*0.9) -> 1.08 | G44: 6 | H44: 0.89 | J44: 0400413/01 | L44: Sucata | M44: =VLOOKUP(Tabela2[[#This Row],[Tipo de Material]],Dados!$P$2:$Q$4,2,FALSE) -> 15.6 | N44: Jumil | O44: 2
A45: Corpo Case Kurokawa - Fundido | B45: 1 | C45: 1.62 | D45: 2.5 | E45: =((Tabela2[[#This Row],[Peso Total Galho]]-(Tabela2[[#This Row],[Peso Pç]]*Tabela2[[#This Row],[Qdt Peça Placa]]))*0.9) -> 0.792 | L45: Lingote | M45: =VLOOKUP(Tabela2[[#This Row],[Tipo de Material]],Dados!$P$2:$Q$4,2,FALSE) -> 17.6 | N45: Jumil | O45: 80
A46: Corpo do Distribuidor 0429006 (0427384P) - FUNDIDO | B46: 1 | C46: 2.93 | D46: 5.18 | E46: =((Tabela2[[#This Row],[Peso Total Galho]]-(Tabela2[[#This Row],[Peso Pç]]*Tabela2[[#This Row],[Qdt Peça Placa]]))*0.9) -> 2.025 | G46: 3 | H46: 0.23 | J46: 0400410/01 | L46: Sucata | M46: =VLOOKUP(Tabela2[[#This Row],[Tipo de Material]],Dados!$P$2:$Q$4,2,FALSE) -> 15.6 | N46: Jumil | O46: 1
A47: CORPO DO VISOR | B47: 2 | C47: 0.435 | D47: 1.5 | E47: =((Tabela2[[#This Row],[Peso Total Galho]]-(Tabela2[[#This Row],[Peso Pç]]*Tabela2[[#This Row],[Qdt Peça Placa]]))*0.9) -> 0.567 | L47: Lingote | M47: =VLOOKUP(Tabela2[[#This Row],[Tipo de Material]],Dados!$P$2:$Q$4,2,FALSE) -> 17.6 | N47: Senun
A48: DISCO DO ACOPLADOR - 0,266KG | B48: 3 | C48: 0.266 | D48: 1.3 | E48: =((Tabela2[[#This Row],[Peso Total Galho]]-(Tabela2[[#This Row],[Peso Pç]]*Tabela2[[#This Row],[Qdt Peça Placa]]))*0.9) -> 0.4518 | L48: Lingote | M48: =VLOOKUP(Tabela2[[#This Row],[Tipo de Material]],Dados!$P$2:$Q$4,2,FALSE) -> 17.6 | N48: Danilo
A49: Distribuidor de Ar 14S (3225353P) - FUNDIDO | B49: 1 | C49: 3.65 | D49: 6.46 | E49: =((Tabela2[[#This Row],[Peso Total Galho]]-(Tabela2[[#This Row],[Peso Pç]]*Tabela2[[#This Row],[Qdt Peça Placa]]))*0.9) -> 2.529 | G49: 1 | H49: 2.742 | J49: 400412 | L49: Sucata | M49: =VLOOKUP(Tabela2[[#This Row],[Tipo de Material]],Dados!$P$2:$Q$4,2,FALSE) -> 15.6 | N49: Jumil | O49: 15
A50: Distribuidor de Ar 8s 2761098 (3241145P) - FUNDIDO | B50: 1 | C50: 1.77 | D50: 3.13 | E50: =((Tabela2[[#This Row],[Peso Total Galho]]-(Tabela2[[#This Row],[Peso Pç]]*Tabela2[[#This Row],[Qdt Peça Placa]]))*0.9) -> 1.224 | G50: 1 | H50: 2.657 | J50: 400405 | L50: Sucata | M50: =VLOOKUP(Tabela2[[#This Row],[Tipo de Material]],Dados!$P$2:$Q$4,2,FALSE) -> 15.6 | N50: Jumil | O50: 10
A51: DIVISOR - Fundido | B51: 6 | C51: 0.166 | D51: 1.392 | E51: =((Tabela2[[#This Row],[Peso Total Galho]]-(Tabela2[[#This Row],[Peso Pç]]*Tabela2[[#This Row],[Qdt Peça Placa]]))*0.9) -> 0.3564 | L51: Lingote | M51: =VLOOKUP(Tabela2[[#This Row],[Tipo de Material]],Dados!$P$2:$Q$4,2,FALSE) -> 17.6 | N51: Marcelo | O51: 10
A52: Dobradiça (Mallascar) - Fundido | B52: 6 | C52: 0.387 | D52: 4.11 | E52: =((Tabela2[[#This Row],[Peso Total Galho]]-(Tabela2[[#This Row],[Peso Pç]]*Tabela2[[#This Row],[Qdt Peça Placa]]))*0.9) -> 1.6092 | L52: Lingote | M52: =VLOOKUP(Tabela2[[#This Row],[Tipo de Material]],Dados!$P$2:$Q$4,2,FALSE) -> 17.6 | N52: Marcelo | O52: 5
A53: Ejetor de Amendoim 0429053 - Fundido | B53: 8 | C53: 0.061 | D53: 1 | E53: =((Tabela2[[#This Row],[Peso Total Galho]]-(Tabela2[[#This Row],[Peso Pç]]*Tabela2[[#This Row],[Qdt Peça Placa]]))*0.9) -> 0.4608 | L53: Sucata | M53: =VLOOKUP(Tabela2[[#This Row],[Tipo de Material]],Dados!$P$2:$Q$4,2,FALSE) -> 15.6 | N53: Jumil | O53: 4
A54: ESTRADO PARA HUNTER 10 | B54: 1 | C54: 4.96 | D54: 5.312 | E54: =((Tabela2[[#This Row],[Peso Total Galho]]-(Tabela2[[#This Row],[Peso Pç]]*Tabela2[[#This Row],[Qdt Peça Placa]]))*0.9) -> 0.3168 | L54: Sucata | M54: =VLOOKUP(Tabela2[[#This Row],[Tipo de Material]],Dados!$P$2:$Q$4,2,FALSE) -> 15.6 | N54: Jumil | O54: 1
A55: ESTRADO PARA HUNTER 20 | B55: 1 | C55: 11.8 | D55: 13 | E55: =((Tabela2[[#This Row],[Peso Total Galho]]-(Tabela2[[#This Row],[Peso Pç]]*Tabela2[[#This Row],[Qdt Peça Placa]]))*0.9) -> 1.08 | L55: Sucata | M55: =VLOOKUP(Tabela2[[#This Row],[Tipo de Material]],Dados!$P$2:$Q$4,2,FALSE) -> 15.6 | N55: Jumil | O55: 1
A56: FLANGE DA TAMPA 0021/002 - DANILO | B56: 1 | C56: 3.1 | D56: 3.5 | E56: =((Tabela2[[#This Row],[Peso Total Galho]]-(Tabela2[[#This Row],[Peso Pç]]*Tabela2[[#This Row],[Qdt Peça Placa]]))*0.9) -> 0.36 | L56: Lingote | M56: =VLOOKUP(Tabela2[[#This Row],[Tipo de Material]],Dados!$P$2:$Q$4,2,FALSE) -> 17.6 | N56: Danilo
A57: FLANGE FIX. 39.01.04.004 - ( 0,800 ) | B57: 1 | C57: 0.8 | D57: 1.35 | E57: =((Tabela2[[#This Row],[Peso Total Galho]]-(Tabela2[[#This Row],[Peso Pç]]*Tabela2[[#This Row],[Qdt Peça Placa]]))*0.9) -> 0.495 | L57: Mistura | M57: =VLOOKUP(Tabela2[[#This Row],[Tipo de Material]],Dados!$P$2:$Q$4,2,FALSE) -> 16.569852 | N57: Danilo
A58: FLANGE FIXAÇÃO - 0,266 | B58: 1 | C58: 0.266 | D58: 1.2 | E58: =((Tabela2[[#This Row],[Peso Total Galho]]-(Tabela2[[#This Row],[Peso Pç]]*Tabela2[[#This Row],[Qdt Peça Placa]]))*0.9) -> 0.8406 | L58: Mistura | M58: =VLOOKUP(Tabela2[[#This Row],[Tipo de Material]],Dados!$P$2:$Q$4,2,FALSE) -> 16.569852 | N58: Danilo
A59: Flange Menor Fundido | B59: 4 | C59: 0.241 | D59: 1.708 | E59: =((Tabela2[[#This Row],[Peso Total Galho]]-(Tabela2[[#This Row],[Peso Pç]]*Tabela2[[#This Row],[Qdt Peça Placa]]))*0.9) -> 0.6696 | L59: Lingote | M59: =VLOOKUP(Tabela2[[#This Row],[Tipo de Material]],Dados!$P$2:$Q$4,2,FALSE) -> 17.6 | N59: Senun | O59: 4
A60: Fogareiro Churrasqueira 2 Fog Fundido | B60: 2 | C60: 1.014 | D60: 3.59 | E60: =((Tabela2[[#This Row],[Peso Total Galho]]-(Tabela2[[#This Row],[Peso Pç]]*Tabela2[[#This Row],[Qdt Peça Placa]]))*0.9) -> 1.4058 | L60: Sucata | M60: =VLOOKUP(Tabela2[[#This Row],[Tipo de Material]],Dados!$P$2:$Q$4,2,FALSE) -> 15.6 | N60: Senun | O60: 6
A61: Frente Caixa de Correio Fit | B61: 3 | C61: 0.533 | D61: 2.499 | E61: =((Tabela2[[#This Row],[Peso Total Galho]]-(Tabela2[[#This Row],[Peso Pç]]*Tabela2[[#This Row],[Qdt Peça Placa]]))*0.9) -> 0.81 | L61: Sucata | M61: =VLOOKUP(Tabela2[[#This Row],[Tipo de Material]],Dados!$P$2:$Q$4,2,FALSE) -> 15.6 | N61: Senun | O61: 5
A62: Frente Caixa de Correio Infinity | B62: 1 | C62: 1.98 | D62: 3.08 | E62: =((Tabela2[[#This Row],[Peso Total Galho]]-(Tabela2[[#This Row],[Peso Pç]]*Tabela2[[#This Row],[Qdt Peça Placa]]))*0.9) -> 0.99 | L62: Sucata | M62: =VLOOKUP(Tabela2[[#This Row],[Tipo de Material]],Dados!$P$2:$Q$4,2,FALSE) -> 15.6 | N62: Senun | O62: 5
A63: Frente Caixa de Correio Master | B63: 1 | C63: 1.5 | D63: 2.5 | E63: =((Tabela2[[#This Row],[Peso Total Galho]]-(Tabela2[[#This Row],[Peso Pç]]*Tabela2[[#This Row],[Qdt Peça Placa]]))*0.9) -> 0.9 | L63: Sucata | M63: =VLOOKUP(Tabela2[[#This Row],[Tipo de Material]],Dados!$P$2:$Q$4,2,FALSE) -> 15.6 | N63: Senun | O63: 5
A64: Frente Caixa de Correio Personnalite | B64: 1 | C64: 1.64 | D64: 2.37 | E64: =((Tabela2[[#This Row],[Peso Total Galho]]-(Tabela2[[#This Row],[Peso Pç]]*Tabela2[[#This Row],[Qdt Peça Placa]]))*0.9) -> 0.657 | L64: Sucata | M64: =VLOOKUP(Tabela2[[#This Row],[Tipo de Material]],Dados!$P$2:$Q$4,2,FALSE) -> 15.6 | N64: Senun | O64: 5
A65: Frente Caixa de Correio Quadrada | B65: 2 | C65: 1.02 | D65: 3.224 | E65: =((Tabela2[[#This Row],[Peso Total Galho]]-(Tabela2[[#This Row],[Peso Pç]]*Tabela2[[#This Row],[Qdt Peça Placa]]))*0.9) -> 1.0656 | L65: Sucata | M65: =VLOOKUP(Tabela2[[#This Row],[Tipo de Material]],Dados!$P$2:$Q$4,2,FALSE) -> 15.6 | N65: Senun | O65: 5
A66: Frente Caixa de Correio Senun | B66: 1 | C66: 1.45 | D66: 2.6 | E66: =((Tabela2[[#This Row],[Peso Total Galho]]-(Tabela2[[#This Row],[Peso Pç]]*Tabela2[[#This Row],[Qdt Peça Placa]]))*0.9) -> 1.035 | L66: Sucata | M66: =VLOOKUP(Tabela2[[#This Row],[Tipo de Material]],Dados!$P$2:$Q$4,2,FALSE) -> 15.6 | N66: Senun | O66: 5
A67: Frente Caixa de Correio Soft / Slim | B67: 2 | C67: 0.65 | D67: 2 | E67: =((Tabela2[[#This Row],[Peso Total Galho]]-(Tabela2[[#This Row],[Peso Pç]]*Tabela2[[#This Row],[Qdt Peça Placa]]))*0.9) -> 0.63 | L67: Sucata | M67: =VLOOKUP(Tabela2[[#This Row],[Tipo de Material]],Dados!$P$2:$Q$4,2,FALSE) -> 15.6 | N67: Senun | O67: 5
A68: HANTER 10 | B68: 1 | C68: 4.96 | D68: 5.312 | E68: =((Tabela2[[#This Row],[Peso Total Galho]]-(Tabela2[[#This Row],[Peso Pç]]*Tabela2[[#This Row],[Qdt Peça Placa]]))*0.9) -> 0.3168 | L68: Lingote | M68: =VLOOKUP(Tabela2[[#This Row],[Tipo de Material]],Dados!$P$2:$Q$4,2,FALSE) -> 17.6 | N68: Jumil | O68: 1
A69: HANTER 20 | B69: 1 | C69: 11.8 | D69: 13 | E69: =((Tabela2[[#This Row],[Peso Total Galho]]-(Tabela2[[#This Row],[Peso Pç]]*Tabela2[[#This Row],[Qdt Peça Placa]]))*0.9) -> 1.08 | L69: Lingote | M69: =VLOOKUP(Tabela2[[#This Row],[Tipo de Material]],Dados!$P$2:$Q$4,2,FALSE) -> 17.6 | N69: Jumil | O69: 1
A70: Lateral Churrasqueira 1 Fogareiro - Fundido | B70: 4 | C70: 0.26 | D70: 1.84 | E70: =((Tabela2[[#This Row],[Peso Total Galho]]-(Tabela2[[#This Row],[Peso Pç]]*Tabela2[[#This Row],[Qdt Peça Placa]]))*0.9) -> 0.72 | L70: Sucata | M70: =VLOOKUP(Tabela2[[#This Row],[Tipo de Material]],Dados!$P$2:$Q$4,2,FALSE) -> 15.6 | N70: Senun | O70: 0
... A72: Mallascar Biela Fundido | B72: 6 | C72: 0.335 | D72: 3.558 | E72: =((Tabela2[[#This Row],[Peso Total Galho]]-(Tabela2[[#This Row],[Peso Pç]]*Tabela2[[#This Row],[Qdt Peça Placa]]))*0.9) -> 1.3932 | L72: Lingote | M72: =VLOOKUP(Tabela2[[#This Row],[Tipo de Material]],Dados!$P$2:$Q$4,2,FALSE) -> 17.6 | N72: Marcelo | O72: 5
A73: MANCAL FPP 1,500 | B73: 4 | C73: 1.5 | D73: 6.4 | E73: =((Tabela2[[#This Row],[Peso Total Galho]]-(Tabela2[[#This Row],[Peso Pç]]*Tabela2[[#This Row],[Qdt Peça Placa]]))*0.9) -> 0.36 | L73: Lingote | M73: =VLOOKUP(Tabela2[[#This Row],[Tipo de Material]],Dados!$P$2:$Q$4,2,FALSE) -> 17.6 | N73: Danilo
A74: MANCAL TRAVA DO PANO | B74: 4 | C74: 1 | D74: 4.5 | E74: =((Tabela2[[#This Row],[Peso Total Galho]]-(Tabela2[[#This Row],[Peso Pç]]*Tabela2[[#This Row],[Qdt Peça Placa]]))*0.9) -> 0.45 | L74: Lingote | M74: =VLOOKUP(Tabela2[[#This Row],[Tipo de Material]],Dados!$P$2:$Q$4,2,FALSE) -> 17.6 | N74: Danilo
A75: MODELO SOLTO - 09071 | B75: 1 | C75: 11.925 | D75: 12.925 | E75: =((Tabela2[[#This Row],[Peso Total Galho]]-(Tabela2[[#This Row],[Peso Pç]]*Tabela2[[#This Row],[Qdt Peça Placa]]))*0.9) -> 0.9 | L75: Lingote | M75: =VLOOKUP(Tabela2[[#This Row],[Tipo de Material]],Dados!$P$2:$Q$4,2,FALSE) -> 17.6 | N75: Oscar
A76: MODELO SOLTO - 09593 | B76: 1 | C76: 16.2 | D76: 17.3 | E76: =((Tabela2[[#This Row],[Peso Total Galho]]-(Tabela2[[#This Row],[Peso Pç]]*Tabela2[[#This Row],[Qdt Peça Placa]]))*0.9) -> 0.99 | L76: Lingote | M76: =VLOOKUP(Tabela2[[#This Row],[Tipo de Material]],Dados!$P$2:$Q$4,2,FALSE) -> 17.6 | N76: Oscar
A77: MODELO SOLTO - 07494 | B77: 1 | C77: 35.15 | D77: 38.15 | E77: =((Tabela2[[#This Row],[Peso Total Galho]]-(Tabela2[[#This Row],[Peso Pç]]*Tabela2[[#This Row],[Qdt Peça Placa]]))*0.9) -> 2.7 | L77: Lingote | M77: =VLOOKUP(Tabela2[[#This Row],[Tipo de Material]],Dados!$P$2:$Q$4,2,FALSE) -> 17.6 | N77: Oscar
A78: MODELO SOLTO - 07519 | B78: 5 | C78: 9.54 | D78: 10.34 | E78: =((Tabela2[[#This Row],[Peso Total Galho]]-(Tabela2[[#This Row],[Peso Pç]]*Tabela2[[#This Row],[Qdt Peça Placa]]))*0.9) -> -33.624 | L78: Lingote | M78: =VLOOKUP(Tabela2[[#This Row],[Tipo de Material]],Dados!$P$2:$Q$4,2,FALSE) -> 17.6 | N78: Oscar
A79: MODELO SOLTO - 07661 | B79: 2 | C79: 19.65 | D79: 21.15 | E79: =((Tabela2[[#This Row],[Peso Total Galho]]-(Tabela2[[#This Row],[Peso Pç]]*Tabela2[[#This Row],[Qdt Peça Placa]]))*0.9) -> -16.335 | L79: Lingote | M79: =VLOOKUP(Tabela2[[#This Row],[Tipo de Material]],Dados!$P$2:$Q$4,2,FALSE) -> 17.6 | N79: Oscar
A80: MODELO SOLTO - 07921 | B80: 1 | C80: 5.82 | D80: 6.72 | E80: =((Tabela2[[#This Row],[Peso Total Galho]]-(Tabela2[[#This Row],[Peso Pç]]*Tabela2[[#This Row],[Qdt Peça Placa]]))*0.9) -> 0.81 | L80: Lingote | M80: =VLOOKUP(Tabela2[[#This Row],[Tipo de Material]],Dados!$P$2:$Q$4,2,FALSE) -> 17.6 | N80: Oscar
A81: MODELO SOLTO - 07921 | B81: 1 | C81: 8.347 | D81: 9.06 | E81: =((Tabela2[[#This Row],[Peso Total Galho]]-(Tabela2[[#This Row],[Peso Pç]]*Tabela2[[#This Row],[Qdt Peça Placa]]))*0.9) -> 0.6417 | L81: Lingote | M81: =VLOOKUP(Tabela2[[#This Row],[Tipo de Material]],Dados!$P$2:$Q$4,2,FALSE) -> 17.6 | N81: Oscar
A82: MODELO SOLTO - 07928 | B82: 1 | C82: 6.433 | D82: 7.133 | E82: =((Tabela2[[#This Row],[Peso Total Galho]]-(Tabela2[[#This Row],[Peso Pç]]*Tabela2[[#This Row],[Qdt Peça Placa]]))*0.9) -> 0.63 | L82: Lingote | M82: =VLOOKUP(Tabela2[[#This Row],[Tipo de Material]],Dados!$P$2:$Q$4,2,FALSE) -> 17.6 | N82: Oscar
A83: MODELO SOLTO - 07941 | B83: 1 | C83: 49.4 | D83: 51.7 | E83: =((Tabela2[[#This Row],[Peso Total Galho]]-(Tabela2[[#This Row],[Peso Pç]]*Tabela2[[#This Row],[Qdt Peça Placa]]))*0.9) -> 2.07 | L83: Lingote | M83: =VLOOKUP(Tabela2[[#This Row],[Tipo de Material]],Dados!$P$2:$Q$4,2,FALSE) -> 17.6 | N83: Oscar
A84: MODELO SOLTO - 07986 | B84: 1 | C84: 25.7 | D84: 27.27 | E84: =((Tabela2[[#This Row],[Peso Total Galho]]-(Tabela2[[#This Row],[Peso Pç]]*Tabela2[[#This Row],[Qdt Peça Placa]]))*0.9) -> 1.413 | L84: Lingote | M84: =VLOOKUP(Tabela2[[#This Row],[Tipo de Material]],Dados!$P$2:$Q$4,2,FALSE) -> 17.6 | N84: Oscar
... A102: MODELO SOLTO - 09936 | B102: 1 | C102: 19.4 | D102: 22 | E102: =((Tabela2[[#This Row],[Peso Total Galho]]-(Tabela2[[#This Row],[Peso Pç]]*Tabela2[[#This Row],[Qdt Peça Placa]]))*0.9) -> 2.34 | L102: Lingote | M102: =VLOOKUP(Tabela2[[#This Row],[Tipo de Material]],Dados!$P$2:$Q$4,2,FALSE) -> 17.6 | N102: Oscar
A103: MODELO SOLTO - OSCAR | B103: 1 | C103: 29.4 | D103: 31.1 | E103: =((Tabela2[[#This Row],[Peso Total Galho]]-(Tabela2[[#This Row],[Peso Pç]]*Tabela2[[#This Row],[Qdt Peça Placa]]))*0.9) -> 1.53 | L103: Lingote | M103: =VLOOKUP(Tabela2[[#This Row],[Tipo de Material]],Dados!$P$2:$Q$4,2,FALSE) -> 17.6 | N103: Oscar | O103: 4
A104: MODELO SOLTO -07661 | B104: 1 | C104: 39.9 | D104: 43.1 | E104: =((Tabela2[[#This Row],[Peso Total Galho]]-(Tabela2[[#This Row],[Peso Pç]]*Tabela2[[#This Row],[Qdt Peça Placa]]))*0.9) -> 2.88 | L104: Lingote | M104: =VLOOKUP(Tabela2[[#This Row],[Tipo de Material]],Dados!$P$2:$Q$4,2,FALSE) -> 17.6 | N104: Oscar
A105: MODELO SOLTO DANILO - 07053 | B105: 1 | C105: 1.1 | D105: 1.25 | E105: =((Tabela2[[#This Row],[Peso Total Galho]]-(Tabela2[[#This Row],[Peso Pç]]*Tabela2[[#This Row],[Qdt Peça Placa]]))*0.9) -> 0.135 | L105: Lingote | M105: =VLOOKUP(Tabela2[[#This Row],[Tipo de Material]],Dados!$P$2:$Q$4,2,FALSE) -> 17.6 | N105: Danilo
A106: MODELO SOLTO OSCAR - 06111 | B106: 1 | C106: 9.68 | D106: 10.68 | E106: =((Tabela2[[#This Row],[Peso Total Galho]]-(Tabela2[[#This Row],[Peso Pç]]*Tabela2[[#This Row],[Qdt Peça Placa]]))*0.9) -> 0.9 | L106: Lingote | M106: =VLOOKUP(Tabela2[[#This Row],[Tipo de Material]],Dados!$P$2:$Q$4,2,FALSE) -> 17.6 | N106: Oscar
A107: MODELO SOLTO OSCAR - 06231 | B107: 1 | C107: 3.521 | D107: 3.957 | E107: =((Tabela2[[#This Row],[Peso Total Galho]]-(Tabela2[[#This Row],[Peso Pç]]*Tabela2[[#This Row],[Qdt Peça Placa]]))*0.9) -> 0.3924 | L107: Lingote | M107: =VLOOKUP(Tabela2[[#This Row],[Tipo de Material]],Dados!$P$2:$Q$4,2,FALSE) -> 17.6 | N107: Oscar
A108: MODELO SOLTO OSCAR - 06244 | B108: 2 | C108: 2.392 | D108: 2.858 | E108: =((Tabela2[[#This Row],[Peso Total Galho]]-(Tabela2[[#This Row],[Peso Pç]]*Tabela2[[#This Row],[Qdt Peça Placa]]))*0.9) -> -1.7334 | L108: Lingote | M108: =VLOOKUP(Tabela2[[#This Row],[Tipo de Material]],Dados!$P$2:$Q$4,2,FALSE) -> 17.6 | N108: Oscar
A109: MODELO SOLTO OSCAR - 06364 | B109: 1 | C109: 3.7 | D109: 4.2 | E109: =((Tabela2[[#This Row],[Peso Total Galho]]-(Tabela2[[#This Row],[Peso Pç]]*Tabela2[[#This Row],[Qdt Peça Placa]]))*0.9) -> 0.45 | L109: Lingote | M109: =VLOOKUP(Tabela2[[#This Row],[Tipo de Material]],Dados!$P$2:$Q$4,2,FALSE) -> 17.6 | N109: Oscar
A110: MODELO SOLTO OSCAR - 06477 | B110: 1 | C110: 9 | D110: 10.1 | E110: =((Tabela2[[#This Row],[Peso Total Galho]]-(Tabela2[[#This Row],[Peso Pç]]*Tabela2[[#This Row],[Qdt Peça Placa]]))*0.9) -> 0.99 | L110: Lingote | M110: =VLOOKUP(Tabela2[[#This Row],[Tipo de Material]],Dados!$P$2:$Q$4,2,FALSE) -> 17.6 | N110: Oscar
A111: MODELO SOLTO OSCAR - 06489 | B111: 1 | C111: 14.74 | D111: 16.214 | E111: =((Tabela2[[#This Row],[Peso Total Galho]]-(Tabela2[[#This Row],[Peso Pç]]*Tabela2[[#This Row],[Qdt Peça Placa]]))*0.9) -> 1.3266 | L111: Lingote | M111: =VLOOKUP(Tabela2[[#This Row],[Tipo de Material]],Dados!$P$2:$Q$4,2,FALSE) -> 17.6 | N111: Oscar
A112: MODELO SOLTO OSCAR - 06627 | B112: 1 | C112: 13.75 | D112: 14.55 | E112: =((Tabela2[[#This Row],[Peso Total Galho]]-(Tabela2[[#This Row],[Peso Pç]]*Tabela2[[#This Row],[Qdt Peça Placa]]))*0.9) -> 0.72 | L112: Lingote | M112: =VLOOKUP(Tabela2[[#This Row],[Tipo de Material]],Dados!$P$2:$Q$4,2,FALSE) -> 17.6 | N112: Oscar
A113: MODELO SOLTO OSCAR - 06743 | B113: 1 | C113: 12.92 | D113: 13.76 | E113: =((Tabela2[[#This Row],[Peso Total Galho]]-(Tabela2[[#This Row],[Peso Pç]]*Tabela2[[#This Row],[Qdt Peça Placa]]))*0.9) -> 0.756 | L113: Lingote | M113: =VLOOKUP(Tabela2[[#This Row],[Tipo de Material]],Dados!$P$2:$Q$4,2,FALSE) -> 17.6 | N113: Oscar
A114: MODELO SOLTO OSCAR - 06743 | B114: 1 | C114: 20.5 | D114: 20.96 | E114: =((Tabela2[[#This Row],[Peso Total Galho]]-(Tabela2[[#This Row],[Peso Pç]]*Tabela2[[#This Row],[Qdt Peça Placa]]))*0.9) -> 0.414 | L114: Lingote | M114: =VLOOKUP(Tabela2[[#This Row],[Tipo de Material]],Dados!$P$2:$Q$4,2,FALSE) -> 17.6 | N114: Oscar
A115: MODELO SOLTO OSCAR - 06806 | B115: 1 | C115: 3.13 | D115: 3.75 | E115: =((Tabela2[[#This Row],[Peso Total Galho]]-(Tabela2[[#This Row],[Peso Pç]]*Tabela2[[#This Row],[Qdt Peça Placa]]))*0.9) -> 0.558 | L115: Lingote | M115: =VLOOKUP(Tabela2[[#This Row],[Tipo de Material]],Dados!$P$2:$Q$4,2,FALSE) -> 17.6 | N115: Oscar
... A127: MODELOS OLTO - 09105 | B127: 1 | C127: 5.3 | D127: 5.84 | E127: =((Tabela2[[#This Row],[Peso Total Galho]]-(Tabela2[[#This Row],[Peso Pç]]*Tabela2[[#This Row],[Qdt Peça Placa]]))*0.9) -> 0.486 | L127: Lingote | M127: =VLOOKUP(Tabela2[[#This Row],[Tipo de Material]],Dados!$P$2:$Q$4,2,FALSE) -> 17.6 | N127: Oscar
A128: Numero 0 Fundido | C128: 0.147 | D128: 0 | E128: =((Tabela2[[#This Row],[Peso Total Galho]]-(Tabela2[[#This Row],[Peso Pç]]*Tabela2[[#This Row],[Qdt Peça Placa]]))*0.9) -> 0 | L128: Sucata | M128: =VLOOKUP(Tabela2[[#This Row],[Tipo de Material]],Dados!$P$2:$Q$4,2,FALSE) -> 15.6 | N128: Senun | O128: 4
A129: Numero 1 Fundido | C129: 0.077 | D129: 0 | E129: =((Tabela2[[#This Row],[Peso Total Galho]]-(Tabela2[[#This Row],[Peso Pç]]*Tabela2[[#This Row],[Qdt Peça Placa]]))*0.9) -> 0 | L129: Sucata | M129: =VLOOKUP(Tabela2[[#This Row],[Tipo de Material]],Dados!$P$2:$Q$4,2,FALSE) -> 15.6 | N129: Senun | O129: 4
...

Sheet Produção
A1: Data | B1: Produto | C1: O.P. | D1: Moldador | E1: Ajudante | F1: Qtde Cx Produzida | G1: Tempo | H1: Perda Pçs | I1: Custo / Kg Util | J1: Custo / Pç | K1: Cx/H | L1: Previsto | M1: Realizado | N1: % Perda | O1: Tempo / Cx | P1: Cx Perdida | Q1: Aluminio Util | R1: Aluminio Bruto | S1: Retorno Aluminio | T1: Qtde Oleo | U1: Custo M.O. / H | V1: Custo / Cx Moldada | W1: Custo M.O. Total | X1: Custo Aluminio | Y1: Custo Machos | Z1: Custo Oleo | AA1: Custo Total | AB1: Custo da Perda | AC1: Qdt Peça Placa | AD1: Peso Util/Pç | AE1: Peso Total Galho | AF1: Canal Retorno | AG1: Peso Caixa Areia | AH1: Qde macho / CX | AI1: Peso Macho | AJ1: Custo/Kg | AK1: Cliente | AL1: Custo Usinagem | AM1: Valor Mínimo Venda | AN1: Tabela 1 | AO1: Tabela 2 | AP1: Tabela 3
A2: 45691 | B2: PROTEC TITAN 150 DIR | C2: 5169 | D2: Daniel Garcia | E2: Victor Hugo | F2: 30 | G2: 0.12291667 | H2: 1 | I2: =IFERROR(Tabela3[[#This Row],[Custo Total]]/Tabela3[[#This Row],[Aluminio Util]],0) -> 27.591322 | J2: =Tabela3[[#This Row],[Custo Total]]/Tabela3[[#This Row],[Realizado]] -> 35.868719 | K2: =IFERROR(Tabela3[[#This Row],[Qtde Cx Produzida]]/Tabela3[[#This Row],[Tempo]]/24,0) -> 10.169492 | L2: =Tabela3[[#This Row],[Qtde Cx Produzida]]*Tabela3[[#This Row],[Qdt Peça Placa]] -> 30 | M2: =Tabela3[[#This Row],[Previsto]]-Tabela3[[#This Row],[Perda Pçs]] -> 29 | N2: =IFERROR(Tabela3[[#This Row],[Perda Pçs]]/Tabela3[[#This Row],[Previsto]],0) -> 0.033333333 | O2: =IFERROR(IF(Tabela3[[#This Row],[Qtde Cx Produzida]] <> 0, Tabela3[[#This Row],[Tempo]] / Tabela3[[#This Row],[Qtde Cx Produzida]], 0),0) -> 0.0040972222 | P2: =IFERROR(Tabela3[[#This Row],[Perda Pçs]]/Tabela3[[#This Row],[Qdt Peça Placa]],0) -> 1 | Q2: =IFERROR(Tabela3[[#This Row],[Realizado]]*Tabela3[[#This Row],[Peso Util/Pç]],0) -> 37.7 | R2: =IFERROR(Tabela3[[#This Row],[Peso Total Galho]]*Tabela3[[#This Row],[Qtde Cx Produzida]]*1.055,0) -> 64.8825 | S2: =(Tabela3[[#This Row],[Aluminio Bruto]]-Tabela3[[#This Row],[Aluminio Util]])*0.9 -> 24.46425 | T2: =Tabela3[[#This Row],[Aluminio Bruto]]/OleoKGAluminio -> 27.295984 | U2: =IFERROR((VLOOKUP(Tabela3[[#This Row],[Moldador]],Tabela1[],5,)+(VLOOKUP(Tabela3[[#This Row],[Ajudante]],Tabela1[],5,))*3.5),0) -> 99.950346 | V2: =IFERROR(Tabela3[[#This Row],[Custo M.O. / H]]/((Tabela3[[#This Row],[Realizado]]/Tabela3[[#This Row],[Qdt Peça Placa]])/Tabela3[[#This Row],[Tempo]]/24),) -> 10.167363 | W2: =Tabela3[[#This Row],[Custo / Cx Moldada]]*Tabela3[[#This Row],[Qtde Cx Produzida]] -> 305.02088 | X2: =Tabela3[[#This Row],[Aluminio Util]]*Tabela3[[#This Row],[Custo/Kg]] -> 663.52 | Y2: =IFERROR(VLOOKUP(Tabela3[[#This Row],[Data]],Tabela461213[],2,1)*(Tabela3[[#This Row],[Qtde Cx Produzida]]*Tabela3[[#This Row],[Qde macho / CX]]*Tabela3[[#This Row],[Peso Macho]]),) -> 0 | Z2: =IFERROR(Tabela3[[#This Row],[Qtde Oleo]]*(VLOOKUP(Tabela3[[#This Row],[Data]],CompraOleo[],3,TRUE))*1.05,0) -> 71.651958 | AA2: =(Tabela3[[#This Row],[Custo Oleo]]+Tabela3[[#This Row],[Custo Aluminio]]+Tabela3[[#This Row],[Custo M.O. Total]]+Tabela3[[#This Row],[Custo Machos]]) -> 1040.1928 | AB2: =Tabela3[[#This Row],[Custo Total]]*Tabela3[[#This Row],[% Perda]] -> 34.673095 | AC2: =IFERROR(VLOOKUP(Tabela3[[#This Row],[Produto]],Tabela2[],2,0),0) -> 1 | AD2: =IFERROR(VLOOKUP(Tabela3[[#This Row],[Produto]],Tabela2[],3,0),0) -> 1.3 | AE2: =IFERROR(VLOOKUP(Tabela3[[#This Row],[Produto]],Tabela2[],4,0),0) -> 2.05 | AF2: =IFERROR(VLOOKUP(Tabela3[[#This Row],[Produto]],Tabela2[],5,0),0) -> 0.675 | AG2: =IFERROR(VLOOKUP(Tabela3[[#This Row],[Produto]],Tabela2[],6,0),0) -> 0 | AH2: =IFERROR(VLOOKUP(Tabela3[[#This Row],[Produto]],Tabela2[],7,0),0) -> 0 | AI2: =IFERROR(VLOOKUP(Tabela3[[#This Row],[Produto]],Tabela2[],8,0),0) -> 0 | AJ2: =IFERROR(VLOOKUP(Tabela3[[#This Row],[Produto]],Tabela2[],13,0),0) -> 17.6 | AK2: =IFERROR(VLOOKUP(Tabela3[[#This Row],[Produto]],Tabela2[],14,0),0) -> Protec | AL2: =IFERROR(VLOOKUP(Tabela3[[#This Row],[Produto]],Tabela2[],15,0),0) -> 0 | AM2: =(Tabela3[[#This Row],[Custo Usinagem]]+Tabela3[[#This Row],[Custo / Pç]])*1.2 -> 43.042462 | AN2: =Tabela3[[#This Row],[Valor Mínimo Venda]]*1.15 -> 49.498832 | AO2: =Tabela3[[#This Row],[Tabela 1]]*1.08 -> 53.458738 | AP2: =Tabela3[[#This Row],[Tabela 2]]*1.15 -> 61.477549
A3: 45691 | B3: PROTEC TITAN 150 DIR | C3: 5169 | D3: Marcelo Santos | E3: Claudio Henrique | F3: 30 | G3: 0.125 | H3: 2 | I3: =IFERROR(Tabela3[[#This Row],[Custo Total]]/Tabela3[[#This Row],[Aluminio Util]],0) -> 28.394531 | J3: =Tabela3[[#This Row],[Custo Total]]/Tabela3[[#This Row],[Realizado]] -> 36.91289 | K3: =IFERROR(Tabela3[[#This Row],[Qtde Cx Produzida]]/Tabela3[[#This Row],[Tempo]]/24,0) -> 10 | L3: =Tabela3[[#This Row],[Qtde Cx Produzida]]*Tabela3[[#This Row],[Qdt Peça Placa]] -> 30 | M3: =Tabela3[[#This Row],[Previsto]]-Tabela3[[#This Row],[Perda Pçs]] -> 28 | N3: =IFERROR(Tabela3[[#This Row],[Perda Pçs]]/Tabela3[[#This Row],[Previsto]],0) -> 0.066666667 | O3: =IFERROR(IF(Tabela3[[#This Row],[Qtde Cx Produzida]] <> 0, Tabela3[[#This Row],[Tempo]] / Tabela3[[#This Row],[Qtde Cx Produzida]], 0),0) -> 0.0041666667 | P3: =IFERROR(Tabela3[[#This Row],[Perda Pçs]]/Tabela3[[#This Row],[Qdt Peça Placa]],0) -> 2 | Q3: =IFERROR(Tabela3[[#This Row],[Realizado]]*Tabela3[[#This Row],[Peso Util/Pç]],0) -> 36.4 | R3: =IFERROR(Tabela3[[#This Row],[Peso Total Galho]]*Tabela3[[#This Row],[Qtde Cx Produzida]]*1.055,0) -> 64.8825 | S3: =(Tabela3[[#This Row],[Aluminio Bruto]]-Tabela3[[#This Row],[Aluminio Util]])*0.9 -> 25.63425 | T3: =Tabela3[[#This Row],[Aluminio Bruto]]/OleoKGAluminio -> 27.295984 | U3: =IFERROR((VLOOKUP(Tabela3[[#This Row],[Moldador]],Tabela1[],5,)+(VLOOKUP(Tabela3[[#This Row],[Ajudante]],Tabela1[],5,))*3.5),0) -> 99.950346 | V3: =IFERROR(Tabela3[[#This Row],[Custo M.O. / H]]/((Tabela3[[#This Row],[Realizado]]/Tabela3[[#This Row],[Qdt Peça Placa]])/Tabela3[[#This Row],[Tempo]]/24),) -> 10.708966 | W3: =Tabela3[[#This Row],[Custo / Cx Moldada]]*Tabela3[[#This Row],[Qtde Cx Produzida]] -> 321.26897 | X3: =Tabela3[[#This Row],[Aluminio Util]]*Tabela3[[#This Row],[Custo/Kg]] -> 640.64 | Y3: =IFERROR(VLOOKUP(Tabela3[[#This Row],[Data]],Tabela461213[],2,1)*(Tabela3[[#This Row],[Qtde Cx Produzida]]*Tabela3[[#This Row],[Qde macho / CX]]*Tabela3[[#This Row],[Peso Macho]]),) -> 0 | Z3: =IFERROR(Tabela3[[#This Row],[Qtde Oleo]]*(VLOOKUP(Tabela3[[#This Row],[Data]],CompraOleo[],3,TRUE))*1.05,0) -> 71.651958 | AA3: =(Tabela3[[#This Row],[Custo Oleo]]+Tabela3[[#This Row],[Custo Aluminio]]+Tabela3[[#This Row],[Custo M.O. Total]]+Tabela3[[#This Row],[Custo Machos]]) -> 1033.5609 | AB3: =Tabela3[[#This Row],[Custo Total]]*Tabela3[[#This Row],[% Perda]] -> 68.904062 | AC3: =IFERROR(VLOOKUP(Tabela3[[#This Row],[Produto]],Tabela2[],2,0),0) -> 1 | AD3: =IFERROR(VLOOKUP(Tabela3[[#This Row],[Produto]],Tabela2[],3,0),0) -> 1.3 | AE3: =IFERROR(VLOOKUP(Tabela3[[#This Row],[Produto]],Tabela2[],4,0),0) -> 2.05 | AF3: =IFERROR(VLOOKUP(Tabela3[[#This Row],[Produto]],Tabela2[],5,0),0) -> 0.675 | AG3: =IFERROR(VLOOKUP(Tabela3[[#This Row],[Produto]],Tabela2[],6,0),0) -> 0 | AH3: =IFERROR(VLOOKUP(Tabela3[[#This Row],[Produto]],Tabela2[],7,0),0) -> 0 | AI3: =IFERROR(VLOOKUP(Tabela3[[#This Row],[Produto]],Tabela2[],8,0),0) -> 0 | AJ3: =IFERROR(VLOOKUP(Tabela3[[#This Row],[Produto]],Tabela2[],13,0),0) -> 17.6 | AK3: =IFERROR(VLOOKUP(Tabela3[[#This Row],[Produto]],Tabela2[],14,0),0) -> Protec | AL3: =IFERROR(VLOOKUP(Tabela3[[#This Row],[Produto]],Tabela2[],15,0),0) -> 0 | AM3: =(Tabela3[[#This Row],[Custo Usinagem]]+Tabela3[[#This Row],[Custo / Pç]])*1.2 -> 44.295468 | AN3: =Tabela3[[#This Row],[Valor Mínimo Venda]]*1.15 -> 50.939789 | AO3: =Tabela3[[#This Row],[Tabela 1]]*1.08 -> 55.014972 | AP3: =Tabela3[[#This Row],[Tabela 2]]*1.15 -> 63.267217
A4: 45691 | B4: Prot Câm Dome C Acopl - SENUN METAL | C4: 5309 | D4: Daniel Garcia | E4: Victor Hugo | F4: 40 | G4: 0.17847222 | H4: 10 | I4: =IFERROR(Tabela3[[#This Row],[Custo Total]]/Tabela3[[#This Row],[Aluminio Util]],0) -> 23.475382 | J4: =Tabela3[[#This Row],[Custo Total]]/Tabela3[[#This Row],[Realizado]] -> 7.0895653 | K4: =IFERROR(Tabela3[[#This Row],[Qtde Cx Produzida]]/Tabela3[[#This Row],[Tempo]]/24,0) -> 9.3385214 | L4: =Tabela3[[#This Row],[Qtde Cx Produzida]]*Tabela3[[#This Row],[Qdt Peça Placa]] -> 240 | M4: =Tabela3[[#This Row],[Previsto]]-Tabela3[[#This Row],[Perda Pçs]] -> 230 | N4: =IFERROR(Tabela3[[#This Row],[Perda Pçs]]/Tabela3[[#This Row],[Previsto]],0) -> 0.041666667 | O4: =IFERROR(IF(Tabela3[[#This Row],[Qtde Cx Produzida]] <> 0, Tabela3[[#This Row],[Tempo]] / Tabela3[[#This Row],[Qtde Cx Produzida]], 0),0) -> 0.0044618056 | P4: =IFERROR(Tabela3[[#This Row],[Perda Pçs]]/Tabela3[[#This Row],[Qdt Peça Placa]],0) -> 1.6666667 | Q4: =IFERROR(Tabela3[[#This Row],[Realizado]]*Tabela3[[#This Row],[Peso Util/Pç]],0) -> 69.46 | R4: =IFERROR(Tabela3[[#This Row],[Peso Total Galho]]*Tabela3[[#This Row],[Qtde Cx Produzida]]*1.055,0) -> 90.8144 | S4: =(Tabela3[[#This Row],[Aluminio Bruto]]-Tabela3[[#This Row],[Aluminio Util]])*0.9 -> 19.21896 | T4: =Tabela3[[#This Row],[Aluminio Bruto]]/OleoKGAluminio -> 38.205501 | U4: =IFERROR((VLOOKUP(Tabela3[[#This Row],[Moldador]],Tabela1[],5,)+(VLOOKUP(Tabela3[[#This Row],[Ajudante]],Tabela1[],5,))*3.5),0) -> 99.950346 | V4: =IFERROR(Tabela3[[#This Row],[Custo M.O. / H]]/((Tabela3[[#This Row],[Realizado]]/Tabela3[[#This Row],[Qdt Peça Placa]])/Tabela3[[#This Row],[Tempo]]/24),) -> 11.168365 | W4: =Tabela3[[#This Row],[Custo / Cx Moldada]]*Tabela3[[#This Row],[Qtde Cx Produzida]] -> 446.73459 | X4: =Tabela3[[#This Row],[Aluminio Util]]*Tabela3[[#This Row],[Custo/Kg]] -> 1083.576 | Y4: =IFERROR(VLOOKUP(Tabela3[[#This Row],[Data]],Tabela461213[],2,1)*(Tabela3[[#This Row],[Qtde Cx Produzida]]*Tabela3[[#This Row],[Qde macho / CX]]*Tabela3[[#This Row],[Peso Macho]]),) -> 0 | Z4: =IFERROR(Tabela3[[#This Row],[Qtde Oleo]]*(VLOOKUP(Tabela3[[#This Row],[Data]],CompraOleo[],3,TRUE))*1.05,0) -> 100.28944 | AA4: =(Tabela3[[#This Row],[Custo Oleo]]+Tabela3[[#This Row],[Custo Aluminio]]+Tabela3[[#This Row],[Custo M.O. Total]]+Tabela3[[#This Row],[Custo Machos]]) -> 1630.6 | AB4: =Tabela3[[#This Row],[Custo Total]]*Tabela3[[#This Row],[% Perda]] -> 67.941668 | AC4: =IFERROR(VLOOKUP(Tabela3[[#This Row],[Produto]],Tabela2[],2,0),0) -> 6 | AD4: =IFERROR(VLOOKUP(Tabela3[[#This Row],[Produto]],Tabela2[],3,0),0) -> 0.302 | AE4: =IFERROR(VLOOKUP(Tabela3[[#This Row],[Produto]],Tabela2[],4,0),0) -> 2.152 | AF4: =IFERROR(VLOOKUP(Tabela3[[#This Row],[Produto]],Tabela2[],5,0),0) -> 0.306 | AG4: =IFERROR(VLOOKUP(Tabela3[[#This Row],[Produto]],Tabela2[],6,0),0) -> 0 | AH4: =IFERROR(VLOOKUP(Tabela3[[#This Row],[Produto]],Tabela2[],7,0),0) -> 0 | AI4: =IFERROR(VLOOKUP(Tabela3[[#This Row],[Produto]],Tabela2[],8,0),0) -> 0 | AJ4: =IFERROR(VLOOKUP(Tabela3[[#This Row],[Produto]],Tabela2[],13,0),0) -> 15.6 | AK4: =IFERROR(VLOOKUP(Tabela3[[#This Row],[Produto]],Tabela2[],14,0),0) -> Senun | AL4: =IFERROR(VLOOKUP(Tabela3[[#This Row],[Produto]],Tabela2[],15,0),0) -> 4 | AM4: =(Tabela3[[#This Row],[Custo Usinagem]]+Tabela3[[#This Row],[Custo / Pç]])*1.2 -> 13.307478 | AN4: =Tabela3[[#This Row],[Valor Mínimo Venda]]*1.15 -> 15.3036 | AO4: =Tabela3[[#This Row],[Tabela 1]]*1.08 -> 16.527888 | AP4: =Tabela3[[#This Row],[Tabela 2]]*1.15 -> 19.007071
A5: 45691 | B5: Distribuidor de Ar 8s 2761098 (3241145P) - FUNDIDO | C5: 5223 | D5: Marcelo Santos | E5: Claudio Henrique | F5: 20 | G5: 0.098611111 | H5: 1 | I5: =IFERROR(Tabela3[[#This Row],[Custo Total]]/Tabela3[[#This Row],[Aluminio Util]],0) -> 27.542987 | J5: =Tabela3[[#This Row],[Custo Total]]/Tabela3[[#This Row],[Realizado]] -> 48.751087 | K5: =IFERROR(Tabela3[[#This Row],[Qtde Cx Produzida]]/Tabela3[[#This Row],[Tempo]]/24,0) -> 8.4507042 | L5: =Tabela3[[#This Row],[Qtde Cx Produzida]]*Tabela3[[#This Row],[Qdt Peça Placa]] -> 20 | M5: =Tabela3[[#This Row],[Previsto]]-Tabela3[[#This Row],[Perda Pçs]] -> 19 | N5: =IFERROR(Tabela3[[#This Row],[Perda Pçs]]/Tabela3[[#This Row],[Previsto]],0) -> 0.05 | O5: =IFERROR(IF(Tabela3[[#This Row],[Qtde Cx Produzida]] <> 0, Tabela3[[#This Row],[Tempo]] / Tabela3[[#This Row],[Qtde Cx Produzida]], 0),0) -> 0.0049305556 | P5: =IFERROR(Tabela3[[#This Row],[Perda Pçs]]/Tabela3[[#This Row],[Qdt Peça Placa]],0) -> 1 | Q5: =IFERROR(Tabela3[[#This Row],[Realizado]]*Tabela3[[#This Row],[Peso Util/Pç]],0) -> 33.63 | R5: =IFERROR(Tabela3[[#This Row],[Peso Total Galho]]*Tabela3[[#This Row],[Qtde Cx Produzida]]*1.055,0) -> 66.043 | S5: =(Tabela3[[#This Row],[Aluminio Bruto]]-Tabela3[[#This Row],[Aluminio Util]])*0.9 -> 29.1717 | T5: =Tabela3[[#This Row],[Aluminio Bruto]]/OleoKGAluminio -> 27.784205 | U5: =IFERROR((VLOOKUP(Tabela3[[#This Row],[Moldador]],Tabela1[],5,)+(VLOOKUP(Tabela3[[#This Row],[Ajudante]],Tabela1[],5,))*3.5),0) -> 99.950346 | V5: =IFERROR(Tabela3[[#This Row],[Custo M.O. / H]]/((Tabela3[[#This Row],[Realizado]]/Tabela3[[#This Row],[Qdt Peça Placa]])/Tabela3[[#This Row],[Tempo]]/24),) -> 12.449955 | W5: =Tabela3[[#This Row],[Custo / Cx Moldada]]*Tabela3[[#This Row],[Qtde Cx Produzida]] -> 248.99911 | X5: =Tabela3[[#This Row],[Aluminio Util]]*Tabela3[[#This Row],[Custo/Kg]] -> 524.628 | Y5: =IFERROR(VLOOKUP(Tabela3[[#This Row],[Data]],Tabela461213[],2,1)*(Tabela3[[#This Row],[Qtde Cx Produzida]]*Tabela3[[#This Row],[Qde macho / CX]]*Tabela3[[#This Row],[Peso Macho]]),) -> 79.71 | Z5: =IFERROR(Tabela3[[#This Row],[Qtde Oleo]]*(VLOOKUP(Tabela3[[#This Row],[Data]],CompraOleo[],3,TRUE))*1.05,0) -> 72.933537 | AA5: =(Tabela3[[#This Row],[Custo Oleo]]+Tabela3[[#This Row],[Custo Aluminio]]+Tabela3[[#This Row],[Custo M.O. Total]]+Tabela3[[#This Row],[Custo Machos]]) -> 926.27064 | AB5: =Tabela3[[#This Row],[Custo Total]]*Tabela3[[#This Row],[% Perda]] -> 46.313532 | AC5: =IFERROR(VLOOKUP(Tabela3[[#This Row],[Produto]],Tabela2[],2,0),0) -> 1 | AD5: =IFERROR(VLOOKUP(Tabela3[[#This Row],[Produto]],Tabela2[],3,0),0) -> 1.77 | AE5: =IFERROR(VLOOKUP(Tabela3[[#This Row],[Produto]],Tabela2[],4,0),0) -> 3.13 | AF5: =IFERROR(VLOOKUP(Tabela3[[#This Row],[Produto]],Tabela2[],5,0),0) -> 1.224 | AG5: =IFERROR(VLOOKUP(Tabela3[[#This Row],[Produto]],Tabela2[],6,0),0) -> 0 | AH5: =IFERROR(VLOOKUP(Tabela3[[#This Row],[Produto]],Tabela2[],7,0),0) -> 1 | AI5: =IFERROR(VLOOKUP(Tabela3[[#This Row],[Produto]],Tabela2[],8,0),0) -> 2.657 | AJ5: =IFERROR(VLOOKUP(Tabela3[[#This Row],[Produto]],Tabela2[],13,0),0) -> 15.6 | AK5: =IFERROR(VLOOKUP(Tabela3[[#This Row],[Produto]],Tabela2[],14,0),0) -> Jumil | AL5: =IFERROR(VLOOKUP(Tabela3[[#This Row],[Produto]],Tabela2[],15,0),0) -> 10 | AM5: =(Tabela3[[#This Row],[Custo Usinagem]]+Tabela3[[#This Row],[Custo / Pç]])*1.2 -> 70.501304 | AN5: =Tabela3[[#This Row],[Valor Mínimo Venda]]*1.15 -> 81.076499 | AO5: =Tabela3[[#This Row],[Tabela 1]]*1.08 -> 87.562619 | AP5: =Tabela3[[#This Row],[Tabela 2]]*1.15 -> 100.69701
A6: 45692 | B6: Centro da Banda (3224429P) - Fundido | C6: 5295 | D6: Daniel Garcia | E6: Victor Hugo | F6: 10 | G6: 0.034027778 | H6: 0 | I6: =IFERROR(Tabela3[[#This Row],[Custo Total]]/Tabela3[[#This Row],[Aluminio Util]],0) -> 22.49123 | J6: =Tabela3[[#This Row],[Custo Total]]/Tabela3[[#This Row],[Realizado]] -> 38.010178 | K6: =IFERROR(Tabela3[[#This Row],[Qtde Cx Produzida]]/Tabela3[[#This Row],[Tempo]]/24,0) -> 12.244898 | L6: =Tabela3[[#This Row],[Qtde Cx Produzida]]*Tabela3[[#This Row],[Qdt Peça Placa]] -> 10 | M6: =Tabela3[[#This Row],[Previsto]]-Tabela3[[#This Row],[Perda Pçs]] -> 10 | N6: =IFERROR(Tabela3[[#This Row],[Perda Pçs]]/Tabela3[[#This Row],[Previsto]],0) -> 0 | O6: =IFERROR(IF(Tabela3[[#This Row],[Qtde Cx Produzida]] <> 0, Tabela3[[#This Row],[Tempo]] / Tabela3[[#This Row],[Qtde Cx Produzida]], 0),0) -> 0.0034027778 | P6: =IFERROR(Tabela3[[#This Row],[Perda Pçs]]/Tabela3[[#This Row],[Qdt Peça Placa]],0) -> 0 | Q6: =IFERROR(Tabela3[[#This Row],[Realizado]]*Tabela3[[#This Row],[Peso Util/Pç]],0) -> 16.9 | R6: =IFERROR(Tabela3[[#This Row],[Peso Total Galho]]*Tabela3[[#This Row],[Qtde Cx Produzida]]*1.055,0) -> 31.5445 | S6: =(Tabela3[[#This Row],[Aluminio Bruto]]-Tabela3[[#This Row],[Aluminio Util]])*0.9 -> 13.18005 | T6: =Tabela3[[#This Row],[Aluminio Bruto]]/OleoKGAluminio -> 13.27073 | U6: =IFERROR((VLOOKUP(Tabela3[[#This Row],[Moldador]],Tabela1[],5,)+(VLOOKUP(Tabela3[[#This Row],[Ajudante]],Tabela1[],5,))*3.5),0) -> 99.950346 | V6: =IFERROR(Tabela3[[#This Row],[Custo M.O. / H]]/((Tabela3[[#This Row],[Realizado]]/Tabela3[[#This Row],[Qdt Peça Placa]])/Tabela3[[#This Row],[Tempo]]/24),) -> 8.1626116 | W6: =Tabela3[[#This Row],[Custo / Cx Moldada]]*Tabela3[[#This Row],[Qtde Cx Produzida]] -> 81.626116 | X6: =Tabela3[[#This Row],[Aluminio Util]]*Tabela3[[#This Row],[Custo/Kg]] -> 263.64 | Y6: =IFERROR(VLOOKUP(Tabela3[[#This Row],[Data]],Tabela461213[],2,1)*(Tabela3[[#This Row],[Qtde Cx Produzida]]*Tabela3[[#This Row],[Qde macho / CX]]*Tabela3[[#This Row],[Peso Macho]]),) -> 0 | Z6: =IFERROR(Tabela3[[#This Row],[Qtde Oleo]]*(VLOOKUP(Tabela3[[#This Row],[Data]],CompraOleo[],3,TRUE))*1.05,0) -> 34.835667 | AA6: =(Tabela3[[#This Row],[Custo Oleo]]+Tabela3[[#This Row],[Custo Aluminio]]+Tabela3[[#This Row],[Custo M.O. Total]]+Tabela3[[#This Row],[Custo Machos]]) -> 380.10178 | AB6: =Tabela3[[#This Row],[Custo Total]]*Tabela3[[#This Row],[% Perda]] -> 0 | AC6: =IFERROR(VLOOKUP(Tabela3[[#This Row],[Produto]],Tabela2[],2,0),0) -> 1 | AD6: =IFERROR(VLOOKUP(Tabela3[[#This Row],[Produto]],Tabela2[],3,0),0) -> 1.69 | AE6: =IFERROR(VLOOKUP(Tabela3[[#This Row],[Produto]],Tabela2[],4,0),0) -> 2.99 | AF6: =IFERROR(VLOOKUP(Tabela3[[#This Row],[Produto]],Tabela2[],5,0),0) -> 1.17 | AG6: =IFERROR(VLOOKUP(Tabela3[[#This Row],[Produto]],Tabela2[],6,0),0) -> 0 | AH6: =IFERROR(VLOOKUP(Tabela3[[#This Row],[Produto]],Tabela2[],7,0),0) -> 0 | AI6: =IFERROR(VLOOKUP(Tabela3[[#This Row],[Produto]],Tabela2[],8,0),0) -> 0 | AJ6: =IFERROR(VLOOKUP(Tabela3[[#This Row],[Produto]],Tabela2[],13,0),0) -> 15.6 | AK6: =IFERROR(VLOOKUP(Tabela3[[#This Row],[Produto]],Tabela2[],14,0),0) -> Jumil | AL6: =IFERROR(VLOOKUP(Tabela3[[#This Row],[Produto]],Tabela2[],15,0),0) -> 8 | AM6: =(Tabela3[[#This Row],[Custo Usinagem]]+Tabela3[[#This Row],[Custo / Pç]])*1.2 -> 55.212214 | AN6: =Tabela3[[#This Row],[Valor Mínimo Venda]]*1.15 -> 63.494046 | AO6: =Tabela3[[#This Row],[Tabela 1]]*1.08 -> 68.57357 | AP6: =Tabela3[[#This Row],[Tabela 2]]*1.15 -> 78.859605
A7: 45692 | B7: PROTEC TITAN 2000 ES | C7: 5173 | D7: Daniel Garcia | E7: Victor Hugo | F7: 55 | G7: 0.22777778 | H7: 4 | I7: =IFERROR(Tabela3[[#This Row],[Custo Total]]/Tabela3[[#This Row],[Aluminio Util]],0) -> 25.880499 | J7: =Tabela3[[#This Row],[Custo Total]]/Tabela3[[#This Row],[Realizado]] -> 22.541915 | K7: =IFERROR(Tabela3[[#This Row],[Qtde Cx Produzida]]/Tabela3[[#This Row],[Tempo]]/24,0) -> 10.060976 | L7: =Tabela3[[#This Row],[Qtde Cx Produzida]]*Tabela3[[#This Row],[Qdt Peça Placa]] -> 110 | M7: =Tabela3[[#This Row],[Previsto]]-Tabela3[[#This Row],[Perda Pçs]] -> 106 | N7: =IFERROR(Tabela3[[#This Row],[Perda Pçs]]/Tabela3[[#This Row],[Previsto]],0) -> 0.036363636 | O7: =IFERROR(IF(Tabela3[[#This Row],[Qtde Cx Produzida]] <> 0, Tabela3[[#This Row],[Tempo]] / Tabela3[[#This Row],[Qtde Cx Produzida]], 0),0) -> 0.0041414141 | P7: =IFERROR(Tabela3[[#This Row],[Perda Pçs]]/Tabela3[[#This Row],[Qdt Peça Placa]],0) -> 2 | Q7: =IFERROR(Tabela3[[#This Row],[Realizado]]*Tabela3[[#This Row],[Peso Util/Pç]],0) -> 92.326 | R7: =IFERROR(Tabela3[[#This Row],[Peso Total Galho]]*Tabela3[[#This Row],[Qtde Cx Produzida]]*1.055,0) -> 178.83305 | S7: =(Tabela3[[#This Row],[Aluminio Bruto]]-Tabela3[[#This Row],[Aluminio Util]])*0.9 -> 77.856345 | T7: =Tabela3[[#This Row],[Aluminio Bruto]]/OleoKGAluminio -> 75.234833 | U7: =IFERROR((VLOOKUP(Tabela3[[#This Row],[Moldador]],Tabela1[],5,)+(VLOOKUP(Tabela3[[#This Row],[Ajudante]],Tabela1[],5,))*3.5),0) -> 99.950346 | V7: =IFERROR(Tabela3[[#This Row],[Custo M.O. / H]]/((Tabela3[[#This Row],[Realizado]]/Tabela3[[#This Row],[Qdt Peça Placa]])/Tabela3[[#This Row],[Tempo]]/24),) -> 10.309344 | W7: =Tabela3[[#This Row],[Custo / Cx Moldada]]*Tabela3[[#This Row],[Qtde Cx Produzida]] -> 567.01391 | X7: =Tabela3[[#This Row],[Aluminio Util]]*Tabela3[[#This Row],[Custo/Kg]] -> 1624.9376 | Y7: =IFERROR(VLOOKUP(Tabela3[[#This Row],[Data]],Tabela461213[],2,1)*(Tabela3[[#This Row],[Qtde Cx Produzida]]*Tabela3[[#This Row],[Qde macho / CX]]*Tabela3[[#This Row],[Peso Macho]]),) -> 0 | Z7: =IFERROR(Tabela3[[#This Row],[Qtde Oleo]]*(VLOOKUP(Tabela3[[#This Row],[Data]],CompraOleo[],3,TRUE))*1.05,0) -> 197.49144 | AA7: =(Tabela3[[#This Row],[Custo Oleo]]+Tabela3[[#This Row],[Custo Aluminio]]+Tabela3[[#This Row],[Custo M.O. Total]]+Tabela3[[#This Row],[Custo Machos]]) -> 2389.4429 | AB7: =Tabela3[[#This Row],[Custo Total]]*Tabela3[[#This Row],[% Perda]] -> 86.888834 | AC7: =IFERROR(VLOOKUP(Tabela3[[#This Row],[Produto]],Tabela2[],2,0),0) -> 2 | AD7: =IFERROR(VLOOKUP(Tabela3[[#This Row],[Produto]],Tabela2[],3,0),0) -> 0.871 | AE7: =IFERROR(VLOOKUP(Tabela3[[#This Row],[Produto]],Tabela2[],4,0),0) -> 3.082 | AF7: =IFERROR(VLOOKUP(Tabela3[[#This Row],[Produto]],Tabela2[],5,0),0) -> 1.206 | AG7: =IFERROR(VLOOKUP(Tabela3[[#This Row],[Produto]],Tabela2[],6,0),0) -> 0 | AH7: =IFERROR(VLOOKUP(Tabela3[[#This Row],[Produto]],Tabela2[],7,0),0) -> 0 | AI7: =IFERROR(VLOOKUP(Tabela3[[#This Row],[Produto]],Tabela2[],8,0),0) -> 0 | AJ7: =IFERROR(VLOOKUP(Tabela3[[#This Row],[Produto]],Tabela2[],13,0),0) -> 17.6 | AK7: =IFERROR(VLOOKUP(Tabela3[[#This Row],[Produto]],Tabela2[],14,0),0) -> Protec | AL7: =IFERROR(VLOOKUP(Tabela3[[#This Row],[Produto]],Tabela2[],15,0),0) -> 0 | AM7: =(Tabela3[[#This Row],[Custo Usinagem]]+Tabela3[[#This Row],[Custo / Pç]])*1.2 -> 27.050298 | AN7: =Tabela3[[#This Row],[Valor Mínimo Venda]]*1.15 -> 31.107842 | AO7: =Tabela3[[#This Row],[Tabela 1]]*1.08 -> 33.59647 | AP7: =Tabela3[[#This Row],[Tabela 2]]*1.15 -> 38.63594
A8: 45692 | B8: Prot Câm Dome C Acopl - SENUN METAL | C8: 5309 | D8: Daniel Garcia | E8: Victor Hugo | F8: 25 | G8: 0.082638889 | H8: 0 | I8: =IFERROR(Tabela3[[#This Row],[Custo Total]]/Tabela3[[#This Row],[Aluminio Util]],0) -> 21.35973 | J8: =Tabela3[[#This Row],[Custo Total]]/Tabela3[[#This Row],[Realizado]] -> 6.4506383 | K8: =IFERROR(Tabela3[[#This Row],[Qtde Cx Produzida]]/Tabela3[[#This Row],[Tempo]]/24,0) -> 12.605042 | L8: =Tabela3[[#This Row],[Qtde Cx Produzida]]*Tabela3[[#This Row],[Qdt Peça Placa]] -> 150 | M8: =Tabela3[[#This Row],[Previsto]]-Tabela3[[#This Row],[Perda Pçs]] -> 150 | N8: =IFERROR(Tabela3[[#This Row],[Perda Pçs]]/Tabela3[[#This Row],[Previsto]],0) -> 0 | O8: =IFERROR(IF(Tabela3[[#This Row],[Qtde Cx Produzida]] <> 0, Tabela3[[#This Row],[Tempo]] / Tabela3[[#This Row],[Qtde Cx Produzida]], 0),0) -> 0.0033055556 | P8: =IFERROR(Tabela3[[#This Row],[Perda Pçs]]/Tabela3[[#This Row],[Qdt Peça Placa]],0) -> 0 | Q8: =IFERROR(Tabela3[[#This Row],[Realizado]]*Tabela3[[#This Row],[Peso Util/Pç]],0) -> 45.3 | R8: =IFERROR(Tabela3[[#This Row],[Peso Total Galho]]*Tabela3[[#This Row],[Qtde Cx Produzida]]*1.055,0) -> 56.759 | S8: =(Tabela3[[#This Row],[Aluminio Bruto]]-Tabela3[[#This Row],[Aluminio Util]])*0.9 -> 10.3131 | T8: =Tabela3[[#This Row],[Aluminio Bruto]]/OleoKGAluminio -> 23.878438 | U8: =IFERROR((VLOOKUP(Tabela3[[#This Row],[Moldador]],Tabela1[],5,)+(VLOOKUP(Tabela3[[#This Row],[Ajudante]],Tabela1[],5,))*3.5),0) -> 99.950346 | V8: =IFERROR(Tabela3[[#This Row],[Custo M.O. / H]]/((Tabela3[[#This Row],[Realizado]]/Tabela3[[#This Row],[Qdt Peça Placa]])/Tabela3[[#This Row],[Tempo]]/24),) -> 7.9293941 | W8: =Tabela3[[#This Row],[Custo / Cx Moldada]]*Tabela3[[#This Row],[Qtde Cx Produzida]] -> 198.23485 | X8: =Tabela3[[#This Row],[Aluminio Util]]*Tabela3[[#This Row],[Custo/Kg]] -> 706.68 | Y8: =IFERROR(VLOOKUP(Tabela3[[#This Row],[Data]],Tabela461213[],2,1)*(Tabela3[[#This Row],[Qtde Cx Produzida]]*Tabela3[[#This Row],[Qde macho / CX]]*Tabela3[[#This Row],[Peso Macho]]),) -> 0 | Z8: =IFERROR(Tabela3[[#This Row],[Qtde Oleo]]*(VLOOKUP(Tabela3[[#This Row],[Data]],CompraOleo[],3,TRUE))*1.05,0) -> 62.6809 | AA8: =(Tabela3[[#This Row],[Custo Oleo]]+Tabela3[[#This Row],[Custo Aluminio]]+Tabela3[[#This Row],[Custo M.O. Total]]+Tabela3[[#This Row],[Custo Machos]]) -> 967.59575 | AB8: =Tabela3[[#This Row],[Custo Total]]*Tabela3[[#This Row],[% Perda]] -> 0 | AC8: =IFERROR(VLOOKUP(Tabela3[[#This Row],[Produto]],Tabela2[],2,0),0) -> 6 | AD8: =IFERROR(VLOOKUP(Tabela3[[#This Row],[Produto]],Tabela2[],3,0),0) -> 0.302 | AE8: =IFERROR(VLOOKUP(Tabela3[[#This Row],[Produto]],Tabela2[],4,0),0) -> 2.152 | AF8: =IFERROR(VLOOKUP(Tabela3[[#This Row],[Produto]],Tabela2[],5,0),0) -> 0.306 | AG8: =IFERROR(VLOOKUP(Tabela3[[#This Row],[Produto]],Tabela2[],6,0),0) -> 0 | AH8: =IFERROR(VLOOKUP(Tabela3[[#This Row],[Produto]],Tabela2[],7,0),0) -> 0 | AI8: =IFERROR(VLOOKUP(Tabela3[[#This Row],[Produto]],Tabela2[],8,0),0) -> 0 | AJ8: =IFERROR(VLOOKUP(Tabela3[[#This Row],[Produto]],Tabela2[],13,0),0) -> 15.6 | AK8: =IFERROR(VLOOKUP(Tabela3[[#This Row],[Produto]],Tabela2[],14,0),0) -> Senun | AL8: =IFERROR(VLOOKUP(Tabela3[[#This Row],[Produto]],Tabela2[],15,0),0) -> 4 | AM8: =(Tabela3[[#This Row],[Custo Usinagem]]+Tabela3[[#This Row],[Custo / Pç]])*1.2 -> 12.540766 | AN8: =Tabela3[[#This Row],[Valor Mínimo Venda]]*1.15 -> 14.421881 | AO8: =Tabela3[[#This Row],[Tabela 1]]*1.08 -> 15.575631 | AP8: =Tabela3[[#This Row],[Tabela 2]]*1.15 -> 17.911976
A9: 45693 | B9: Prot Câm Dome C Acopl - SENUN METAL | C9: 5309 | D9: Daniel Garcia | E9: Victor Hugo | F9: 82 | G9: 0.36805556 | H9: 25 | I9: =IFERROR(Tabela3[[#This Row],[Custo Total]]/Tabela3[[#This Row],[Aluminio Util]],0) -> 23.653039 | J9: =Tabela3[[#This Row],[Custo Total]]/Tabela3[[#This Row],[Realizado]] -> 7.1432177 | K9: =IFERROR(Tabela3[[#This Row],[Qtde Cx Produzida]]/Tabela3[[#This Row],[Tempo]]/24,0) -> 9.2830189 | L9: =Tabela3[[#This Row],[Qtde Cx Produzida]]*Tabela3[[#This Row],[Qdt Peça Placa]] -> 492 | M9: =Tabela3[[#This Row],[Previsto]]-Tabela3[[#This Row],[Perda Pçs]] -> 467 | N9: =IFERROR(Tabela3[[#This Row],[Perda Pçs]]/Tabela3[[#This Row],[Previsto]],0) -> 0.050813008 | O9: =IFERROR(IF(Tabela3[[#This Row],[Qtde Cx Produzida]] <> 0, Tabela3[[#This Row],[Tempo]] / Tabela3[[#This Row],[Qtde Cx Produzida]], 0),0) -> 0.0044884824 | P9: =IFERROR(Tabela3[[#This Row],[Perda Pçs]]/Tabela3[[#This Row],[Qdt Peça Placa]],0) -> 4.1666667 | Q9: =IFERROR(Tabela3[[#This Row],[Realizado]]*Tabela3[[#This Row],[Peso Util/Pç]],0) -> 141.034 | R9: =IFERROR(Tabela3[[#This Row],[Peso Total Galho]]*Tabela3[[#This Row],[Qtde Cx Produzida]]*1.055,0) -> 186.16952 | S9: =(Tabela3[[#This Row],[Aluminio Bruto]]-Tabela3[[#This Row],[Aluminio Util]])*0.9 -> 40.621968 | T9: =Tabela3[[#This Row],[Aluminio Bruto]]/OleoKGAluminio -> 78.321276 | U9: =IFERROR((VLOOKUP(Tabela3[[#This Row],[Moldador]],Tabela1[],5,)+(VLOOKUP(Tabela3[[#This Row],[Ajudante]],Tabela1[],5,))*3.5),0) -> 99.950346 | V9: =IFERROR(Tabela3[[#This Row],[Custo M.O. / H]]/((Tabela3[[#This Row],[Realizado]]/Tabela3[[#This Row],[Qdt Peça Placa]])/Tabela3[[#This Row],[Tempo]]/24),) -> 11.343401 | W9: =Tabela3[[#This Row],[Custo / Cx Moldada]]*Tabela3[[#This Row],[Qtde Cx Produzida]] -> 930.15889 | X9: =Tabela3[[#This Row],[Aluminio Util]]*Tabela3[[#This Row],[Custo/Kg]] -> 2200.1304 | Y9: =IFERROR(VLOOKUP(Tabela3[[#This Row],[Data]],Tabela461213[],2,1)*(Tabela3[[#This Row],[Qtde Cx Produzida]]*Tabela3[[#This Row],[Qde macho / CX]]*Tabela3[[#This Row],[Peso Macho]]),) -> 0 | Z9: =IFERROR(Tabela3[[#This Row],[Qtde Oleo]]*(VLOOKUP(Tabela3[[#This Row],[Data]],CompraOleo[],3,TRUE))*1.05,0) -> 205.59335 | AA9: =(Tabela3[[#This Row],[Custo Oleo]]+Tabela3[[#This Row],[Custo Aluminio]]+Tabela3[[#This Row],[Custo M.O. Total]]+Tabela3[[#This Row],[Custo Machos]]) -> 3335.8826 | AB9: =Tabela3[[#This Row],[Custo Total]]*Tabela3[[#This Row],[% Perda]] -> 169.50623 | AC9: =IFERROR(VLOOKUP(Tabela3[[#This Row],[Produto]],Tabela2[],2,0),0) -> 6 | AD9: =IFERROR(VLOOKUP(Tabela3[[#This Row],[Produto]],Tabela2[],3,0),0) -> 0.302 | AE9: =IFERROR(VLOOKUP(Tabela3[[#This Row],[Produto]],Tabela2[],4,0),0) -> 2.152 | AF9: =IFERROR(VLOOKUP(Tabela3[[#This Row],[Produto]],Tabela2[],5,0),0) -> 0.306 | AG9: =IFERROR(VLOOKUP(Tabela3[[#This Row],[Produto]],Tabela2[],6,0),0) -> 0 | AH9: =IFERROR(VLOOKUP(Tabela3[[#This Row],[Produto]],Tabela2[],7,0),0) -> 0 | AI9: =IFERROR(VLOOKUP(Tabela3[[#This Row],[Produto]],Tabela2[],8,0),0) -> 0 | AJ9: =IFERROR(VLOOKUP(Tabela3[[#This Row],[Produto]],Tabela2[],13,0),0) -> 15.6 | AK9: =IFERROR(VLOOKUP(Tabela3[[#This Row],[Produto]],Tabela2[],14,0),0) -> Senun | AL9: =IFERROR(VLOOKUP(Tabela3[[#This Row],[Produto]],Tabela2[],15,0),0) -> 4 | AM9: =(Tabela3[[#This Row],[Custo Usinagem]]+Tabela3[[#This Row],[Custo / Pç]])*1.2 -> 13.371861 | AN9: =Tabela3[[#This Row],[Valor Mínimo Venda]]*1.15 -> 15.37764 | AO9: =Tabela3[[#This Row],[Tabela 1]]*1.08 -> 16.607852 | AP9: =Tabela3[[#This Row],[Tabela 2]]*1.15 -> 19.099029
A10: 45694 | B10: Prot Câm Dome C Acopl - SENUN METAL | C10: 5309 | D10: Daniel Garcia | E10: Victor Hugo | F10: 17 | G10: 0.073611111 | H10: 0 | I10: =IFERROR(Tabela3[[#This Row],[Custo Total]]/Tabela3[[#This Row],[Aluminio Util]],0) -> 22.716022 | J10: =Tabela3[[#This Row],[Custo Total]]/Tabela3[[#This Row],[Realizado]] -> 6.8602388 | K10: =IFERROR(Tabela3[[#This Row],[Qtde Cx Produzida]]/Tabela3[[#This Row],[Tempo]]/24,0) -> 9.6226415 | L10: =Tabela3[[#This Row],[Qtde Cx Produzida]]*Tabela3[[#This Row],[Qdt Peça Placa]] -> 102 | M10: =Tabela3[[#This Row],[Previsto]]-Tabela3[[#This Row],[Perda Pçs]] -> 102 | N10: =IFERROR(Tabela3[[#This Row],[Perda Pçs]]/Tabela3[[#This Row],[Previsto]],0) -> 0 | O10: =IFERROR(IF(Tabela3[[#This Row],[Qtde Cx Produzida]] <> 0, Tabela3[[#This Row],[Tempo]] / Tabela3[[#This Row],[Qtde Cx Produzida]], 0),0) -> 0.0043300654 | P10: =IFERROR(Tabela3[[#This Row],[Perda Pçs]]/Tabela3[[#This Row],[Qdt Peça Placa]],0) -> 0 | Q10: =IFERROR(Tabela3[[#This Row],[Realizado]]*Tabela3[[#This Row],[Peso Util/Pç]],0) -> 30.804 | R10: =IFERROR(Tabela3[[#This Row],[Peso Total Galho]]*Tabela3[[#This Row],[Qtde Cx Produzida]]*1.055,0) -> 38.59612 | S10: =(Tabela3[[#This Row],[Aluminio Bruto]]-Tabela3[[#This Row],[Aluminio Util]])*0.9 -> 7.012908 | T10: =Tabela3[[#This Row],[Aluminio Bruto]]/OleoKGAluminio -> 16.237338 | U10: =IFERROR((VLOOKUP(Tabela3[[#This Row],[Moldador]],Tabela1[],5,)+(VLOOKUP(Tabela3[[#This Row],[Ajudante]],Tabela1[],5,))*3.5),0) -> 99.950346 | V10: =IFERROR(Tabela3[[#This Row],[Custo M.O. / H]]/((Tabela3[[#This Row],[Realizado]]/Tabela3[[#This Row],[Qdt Peça Placa]])/Tabela3[[#This Row],[Tempo]]/24),) -> 10.386997 | W10: =Tabela3[[#This Row],[Custo / Cx Moldada]]*Tabela3[[#This Row],[Qtde Cx Produzida]] -> 176.57894 | X10: =Tabela3[[#This Row],[Aluminio Util]]*Tabela3[[#This Row],[Custo/Kg]] -> 480.5424 | Y10: =IFERROR(VLOOKUP(Tabela3[[#This Row],[Data]],Tabela461213[],2,1)*(Tabela3[[#This Row],[Qtde Cx Produzida]]*Tabela3[[#This Row],[Qde macho / CX]]*Tabela3[[#This Row],[Peso Macho]]),) -> 0 | Z10: =IFERROR(Tabela3[[#This Row],[Qtde Oleo]]*(VLOOKUP(Tabela3[[#This Row],[Data]],CompraOleo[],3,TRUE))*1.05,0) -> 42.623012 | AA10: =(Tabela3[[#This Row],[Custo Oleo]]+Tabela3[[#This Row],[Custo Aluminio]]+Tabela3[[#This Row],[Custo M.O. Total]]+Tabela3[[#This Row],[Custo Machos]]) -> 699.74436 | AB10: =Tabela3[[#This Row],[Custo Total]]*Tabela3[[#This Row],[% Perda]] -> 0 | AC10: =IFERROR(VLOOKUP(Tabela3[[#This Row],[Produto]],Tabela2[],2,0),0) -> 6 | AD10: =IFERROR(VLOOKUP(Tabela3[[#This Row],[Produto]],Tabela2[],3,0),0) -> 0.302 | AE10: =IFERROR(VLOOKUP(Tabela3[[#This Row],[Produto]],Tabela2[],4,0),0) -> 2.152 | AF10: =IFERROR(VLOOKUP(Tabela3[[#This Row],[Produto]],Tabela2[],5,0),0) -> 0.306 | AG10: =IFERROR(VLOOKUP(Tabela3[[#This Row],[Produto]],Tabela2[],6,0),0) -> 0 | AH10: =IFERROR(VLOOKUP(Tabela3[[#This Row],[Produto]],Tabela2[],7,0),0) -> 0 | AI10: =IFERROR(VLOOKUP(Tabela3[[#This Row],[Produto]],Tabela2[],8,0),0) -> 0 | AJ10: =IFERROR(VLOOKUP(Tabela3[[#This Row],[Produto]],Tabela2[],13,0),0) -> 15.6 | AK10: =IFERROR(VLOOKUP(Tabela3[[#This Row],[Produto]],Tabela2[],14,0),0) -> Senun | AL10: =IFERROR(VLOOKUP(Tabela3[[#This Row],[Produto]],Tabela2[],15,0),0) -> 4 | AM10: =(Tabela3[[#This Row],[Custo Usinagem]]+Tabela3[[#This Row],[Custo / Pç]])*1.2 -> 13.032287 | AN10: =Tabela3[[#This Row],[Valor Mínimo Venda]]*1.15 -> 14.98713 | AO10: =Tabela3[[#This Row],[Tabela 1]]*1.08 -> 16.1861 | AP10: =Tabela3[[#This Row],[Tabela 2]]*1.15 -> 18.614015
A11: 45694 | B11: Cachimbo Fundido 33 (-) Fundido | C11: 5443 | D11: Daniel Garcia | E11: Victor Hugo | F11: 26 | G11: 0.17430556 | H11: 107 | I11: =IFERROR(Tabela3[[#This Row],[Custo Total]]/Tabela3[[#This Row],[Aluminio Util]],0) -> 32.589622 | J11: =Tabela3[[#This Row],[Custo Total]]/Tabela3[[#This Row],[Realizado]] -> 8.5384809 | K11: =IFERROR(Tabela3[[#This Row],[Qtde Cx Produzida]]/Tabela3[[#This Row],[Tempo]]/24,0) -> 6.2151394 | L11: =Tabela3[[#This Row],[Qtde Cx Produzida]]*Tabela3[[#This Row],[Qdt Peça Placa]] -> 312 | M11: =Tabela3[[#This Row],[Previsto]]-Tabela3[[#This Row],[Perda Pçs]] -> 205 | N11: =IFERROR(Tabela3[[#This Row],[Perda Pçs]]/Tabela3[[#This Row],[Previsto]],0) -> 0.34294872 | O11: =IFERROR(IF(Tabela3[[#This Row],[Qtde Cx Produzida]] <> 0, Tabela3[[#This Row],[Tempo]] / Tabela3[[#This Row],[Qtde Cx Produzida]], 0),0) -> 0.0067040598 | P11: =IFERROR(Tabela3[[#This Row],[Perda Pçs]]/Tabela3[[#This Row],[Qdt Peça Placa]],0) -> 8.9166667 | Q11: =IFERROR(Tabela3[[#This Row],[Realizado]]*Tabela3[[#This Row],[Peso Util/Pç]],0) -> 53.71 | R11: =IFERROR(Tabela3[[#This Row],[Peso Total Galho]]*Tabela3[[#This Row],[Qtde Cx Produzida]]*1.055,0) -> 152.7851 | S11: =(Tabela3[[#This Row],[Aluminio Bruto]]-Tabela3[[#This Row],[Aluminio Util]])*0.9 -> 89.16759 | T11: =Tabela3[[#This Row],[Aluminio Bruto]]/OleoKGAluminio -> 64.276494 | U11: =IFERROR((VLOOKUP(Tabela3[[#This Row],[Moldador]],Tabela1[],5,)+(VLOOKUP(Tabela3[[#This Row],[Ajudante]],Tabela1[],5,))*3.5),0) -> 99.950346 | V11: =IFERROR(Tabela3[[#This Row],[Custo M.O. / H]]/((Tabela3[[#This Row],[Realizado]]/Tabela3[[#This Row],[Qdt Peça Placa]])/Tabela3[[#This Row],[Tempo]]/24),) -> 24.475646 | W11: =Tabela3[[#This Row],[Custo / Cx Moldada]]*Tabela3[[#This Row],[Qtde Cx Produzida]] -> 636.36679 | X11: =Tabela3[[#This Row],[Aluminio Util]]*Tabela3[[#This Row],[Custo/Kg]] -> 945.296 | Y11: =IFERROR(VLOOKUP(Tabela3[[#This Row],[Data]],Tabela461213[],2,1)*(Tabela3[[#This Row],[Qtde Cx Produzida]]*Tabela3[[#This Row],[Qde macho / CX]]*Tabela3[[#This Row],[Peso Macho]]),) -> 0 | Z11: =IFERROR(Tabela3[[#This Row],[Qtde Oleo]]*(VLOOKUP(Tabela3[[#This Row],[Data]],CompraOleo[],3,TRUE))*1.05,0) -> 168.7258 | AA11: =(Tabela3[[#This Row],[Custo Oleo]]+Tabela3[[#This Row],[Custo Aluminio]]+Tabela3[[#This Row],[Custo M.O. Total]]+Tabela3[[#This Row],[Custo Machos]]) -> 1750.3886 | AB11: =Tabela3[[#This Row],[Custo Total]]*Tabela3[[#This Row],[% Perda]] -> 600.29352 | AC11: =IFERROR(VLOOKUP(Tabela3[[#This Row],[Produto]],Tabela2[],2,0),0) -> 12 | AD11: =IFERROR(VLOOKUP(Tabela3[[#This Row],[Produto]],Tabela2[],3,0),0) -> 0.262 | AE11: =IFERROR(VLOOKUP(Tabela3[[#This Row],[Produto]],Tabela2[],4,0),0) -> 5.57 | AF11: =IFERROR(VLOOKUP(Tabela3[[#This Row],[Produto]],Tabela2[],5,0),0) -> 2.1834 | AG11: =IFERROR(VLOOKUP(Tabela3[[#This Row],[Produto]],Tabela2[],6,0),0) -> 0 | AH11: =IFERROR(VLOOKUP(Tabela3[[#This Row],[Produto]],Tabela2[],7,0),0) -> 0 | AI11: =IFERROR(VLOOKUP(Tabela3[[#This Row],[Produto]],Tabela2[],8,0),0) -> 0 | AJ11: =IFERROR(VLOOKUP(Tabela3[[#This Row],[Produto]],Tabela2[],13,0),0) -> 17.6 | AK11: =IFERROR(VLOOKUP(Tabela3[[#This Row],[Produto]],Tabela2[],14,0),0) -> Marcelo | AL11: =IFERROR(VLOOKUP(Tabela3[[#This Row],[Produto]],Tabela2[],15,0),0) -> 5 | AM11: =(Tabela3[[#This Row],[Custo Usinagem]]+Tabela3[[#This Row],[Custo / Pç]])*1.2 -> 16.246177 | AN11: =Tabela3[[#This Row],[Valor Mínimo Venda]]*1.15 -> 18.683104 | AO11: =Tabela3[[#This Row],[Tabela 1]]*1.08 -> 20.177752 | AP11: =Tabela3[[#This Row],[Tabela 2]]*1.15 -> 23.204415
A12: 45694 | B12: Prot. Interfone Ivr 1010 Fundido | C12: 5438 | D12: Daniel Garcia | E12: Victor Hugo | F12: 22 | G12: 0.098611111 | H12: 6 | I12: =IFERROR(Tabela3[[#This Row],[Custo Total]]/Tabela3[[#This Row],[Aluminio Util]],0) -> 28.315866 | J12: =Tabela3[[#This Row],[Custo Total]]/Tabela3[[#This Row],[Realizado]] -> 8.4947597 | K12: =IFERROR(Tabela3[[#This Row],[Qtde Cx Produzida]]/Tabela3[[#This Row],[Tempo]]/24,0) -> 9.2957746 | L12: =Tabela3[[#This Row],[Qtde Cx Produzida]]*Tabela3[[#This Row],[Qdt Peça Placa]] -> 88 | M12: =Tabela3[[#This Row],[Previsto]]-Tabela3[[#This Row],[Perda Pçs]] -> 82 | N12: =IFERROR(Tabela3[[#This Row],[Perda Pçs]]/Tabela3[[#This Row],[Previsto]],0) -> 0.068181818 | O12: =IFERROR(IF(Tabela3[[#This Row],[Qtde Cx Produzida]] <> 0, Tabela3[[#This Row],[Tempo]] / Tabela3[[#This Row],[Qtde Cx Produzida]], 0),0) -> 0.0044823232 | P12: =IFERROR(Tabela3[[#This Row],[Perda Pçs]]/Tabela3[[#This Row],[Qdt Peça Placa]],0) -> 1.5 | Q12: =IFERROR(Tabela3[[#This Row],[Realizado]]*Tabela3[[#This Row],[Peso Util/Pç]],0) -> 24.6 | R12: =IFERROR(Tabela3[[#This Row],[Peso Total Galho]]*Tabela3[[#This Row],[Qtde Cx Produzida]]*1.055,0) -> 53.383 | S12: =(Tabela3[[#This Row],[Aluminio Bruto]]-Tabela3[[#This Row],[Aluminio Util]])*0.9 -> 25.9047 | T12: =Tabela3[[#This Row],[Aluminio Bruto]]/OleoKGAluminio -> 22.458159 | U12: =IFERROR((VLOOKUP(Tabela3[[#This Row],[Moldador]],Tabela1[],5,)+(VLOOKUP(Tabela3[[#This Row],[Ajudante]],Tabela1[],5,))*3.5),0) -> 99.950346 | V12: =IFERROR(Tabela3[[#This Row],[Custo M.O. / H]]/((Tabela3[[#This Row],[Realizado]]/Tabela3[[#This Row],[Qdt Peça Placa]])/Tabela3[[#This Row],[Tempo]]/24),) -> 11.538983 | W12: =Tabela3[[#This Row],[Custo / Cx Moldada]]*Tabela3[[#This Row],[Qtde Cx Produzida]] -> 253.85763 | X12: =Tabela3[[#This Row],[Aluminio Util]]*Tabela3[[#This Row],[Custo/Kg]] -> 383.76 | Y12: =IFERROR(VLOOKUP(Tabela3[[#This Row],[Data]],Tabela461213[],2,1)*(Tabela3[[#This Row],[Qtde Cx Produzida]]*Tabela3[[#This Row],[Qde macho / CX]]*Tabela3[[#This Row],[Peso Macho]]),) -> 0 | Z12: =IFERROR(Tabela3[[#This Row],[Qtde Oleo]]*(VLOOKUP(Tabela3[[#This Row],[Data]],CompraOleo[],3,TRUE))*1.05,0) -> 58.952668 | AA12: =(Tabela3[[#This Row],[Custo Oleo]]+Tabela3[[#This Row],[Custo Aluminio]]+Tabela3[[#This Row],[Custo M.O. Total]]+Tabela3[[#This Row],[Custo Machos]]) -> 696.57029 | AB12: =Tabela3[[#This Row],[Custo Total]]*Tabela3[[#This Row],[% Perda]] -> 47.493429 | AC12: =IFERROR(VLOOKUP(Tabela3[[#This Row],[Produto]],Tabela2[],2,0),0) -> 4 | AD12: =IFERROR(VLOOKUP(Tabela3[[#This Row],[Produto]],Tabela2[],3,0),0) -> 0.3 | AE12: =IFERROR(VLOOKUP(Tabela3[[#This Row],[Produto]],Tabela2[],4,0),0) -> 2.3 | AF12: =IFERROR(VLOOKUP(Tabela3[[#This Row],[Produto]],Tabela2[],5,0),0) -> 0.99 | AG12: =IFERROR(VLOOKUP(Tabela3[[#This Row],[Produto]],Tabela2[],6,0),0) -> 0 | AH12: =IFERROR(VLOOKUP(Tabela3[[#This Row],[Produto]],Tabela2[],7,0),0) -> 0 | AI12: =IFERROR(VLOOKUP(Tabela3[[#This Row],[Produto]],Tabela2[],8,0),0) -> 0 | AJ12: =IFERROR(VLOOKUP(Tabela3[[#This Row],[Produto]],Tabela2[],13,0),0) -> 15.6 | AK12: =IFERROR(VLOOKUP(Tabela3[[#This Row],[Produto]],Tabela2[],14,0),0) -> Senun | AL12: =IFERROR(VLOOKUP(Tabela3[[#This Row],[Produto]],Tabela2[],15,0),0) -> 3.5 | AM12: =(Tabela3[[#This Row],[Custo Usinagem]]+Tabela3[[#This Row],[Custo / Pç]])*1.2 -> 14.393712 | AN12: =Tabela3[[#This Row],[Valor Mínimo Venda]]*1.15 -> 16.552768 | AO12: =Tabela3[[#This Row],[Tabela 1]]*1.08 -> 17.87699 | AP12: =Tabela3[[#This Row],[Tabela 2]]*1.15 -> 20.558538
A13: 45695 | B13: Prot. Interfone Ivr 1010 Fundido | C13: 5438 | D13: Daniel Garcia | E13: Victor Hugo | F13: 18 | G13: 0.11875 | H13: 5 | I13: =IFERROR(Tabela3[[#This Row],[Custo Total]]/Tabela3[[#This Row],[Aluminio Util]],0) -> 33.229382 | J13: =Tabela3[[#This Row],[Custo Total]]/Tabela3[[#This Row],[Realizado]] -> 9.9688147 | K13: =IFERROR(Tabela3[[#This Row],[Qtde Cx Produzida]]/Tabela3[[#This Row],[Tempo]]/24,0) -> 6.3157895 | L13: =Tabela3[[#This Row],[Qtde Cx Produzida]]*Tabela3[[#This Row],[Qdt Peça Placa]] -> 72 | M13: =Tabela3[[#This Row],[Previsto]]-Tabela3[[#This Row],[Perda Pçs]] -> 67 | N13: =IFERROR(Tabela3[[#This Row],[Perda Pçs]]/Tabela3[[#This Row],[Previsto]],0) -> 0.069444444 | O13: =IFERROR(IF(Tabela3[[#This Row],[Qtde Cx Produzida]] <> 0, Tabela3[[#This Row],[Tempo]] / Tabela3[[#This Row],[Qtde Cx Produzida]], 0),0) -> 0.0065972222 | P13: =IFERROR(Tabela3[[#This Row],[Perda Pçs]]/Tabela3[[#This Row],[Qdt Peça Placa]],0) -> 1.25 | Q13: =IFERROR(Tabela3[[#This Row],[Realizado]]*Tabela3[[#This Row],[Peso Util/Pç]],0) -> 20.1 | R13: =IFERROR(Tabela3[[#This Row],[Peso Total Galho]]*Tabela3[[#This Row],[Qtde Cx Produzida]]*1.055,0) -> 43.677 | S13: =(Tabela3[[#This Row],[Aluminio Bruto]]-Tabela3[[#This Row],[Aluminio Util]])*0.9 -> 21.2193 | T13: =Tabela3[[#This Row],[Aluminio Bruto]]/OleoKGAluminio -> 18.374857 | U13: =IFERROR((VLOOKUP(Tabela3[[#This Row],[Moldador]],Tabela1[],5,)+(VLOOKUP(Tabela3[[#This Row],[Ajudante]],Tabela1[],5,))*3.5),0) -> 99.950346 | V13: =IFERROR(Tabela3[[#This Row],[Custo M.O. / H]]/((Tabela3[[#This Row],[Realizado]]/Tabela3[[#This Row],[Qdt Peça Placa]])/Tabela3[[#This Row],[Tempo]]/24),) -> 17.006477 | W13: =Tabela3[[#This Row],[Custo / Cx Moldada]]*Tabela3[[#This Row],[Qtde Cx Produzida]] -> 306.11658 | X13: =Tabela3[[#This Row],[Aluminio Util]]*Tabela3[[#This Row],[Custo/Kg]] -> 313.56 | Y13: =IFERROR(VLOOKUP(Tabela3[[#This Row],[Data]],Tabela461213[],2,1)*(Tabela3[[#This Row],[Qtde Cx Produzida]]*Tabela3[[#This Row],[Qde macho / CX]]*Tabela3[[#This Row],[Peso Macho]]),) -> 0 | Z13: =IFERROR(Tabela3[[#This Row],[Qtde Oleo]]*(VLOOKUP(Tabela3[[#This Row],[Data]],CompraOleo[],3,TRUE))*1.05,0) -> 48.234001 | AA13: =(Tabela3[[#This Row],[Custo Oleo]]+Tabela3[[#This Row],[Custo Aluminio]]+Tabela3[[#This Row],[Custo M.O. Total]]+Tabela3[[#This Row],[Custo Machos]]) -> 667.91058 | AB13: =Tabela3[[#This Row],[Custo Total]]*Tabela3[[#This Row],[% Perda]] -> 46.382679 | AC13: =IFERROR(VLOOKUP(Tabela3[[#This Row],[Produto]],Tabela2[],2,0),0) -> 4 | AD13: =IFERROR(VLOOKUP(Tabela3[[#This Row],[Produto]],Tabela2[],3,0),0) -> 0.3 | AE13: =IFERROR(VLOOKUP(Tabela3[[#This Row],[Produto]],Tabela2[],4,0),0) -> 2.3 | AF13: =IFERROR(VLOOKUP(Tabela3[[#This Row],[Produto]],Tabela2[],5,0),0) -> 0.99 | AG13: =IFERROR(VLOOKUP(Tabela3[[#This Row],[Produto]],Tabela2[],6,0),0) -> 0 | AH13: =IFERROR(VLOOKUP(Tabela3[[#This Row],[Produto]],Tabela2[],7,0),0) -> 0 | AI13: =IFERROR(VLOOKUP(Tabela3[[#This Row],[Produto]],Tabela2[],8,0),0) -> 0 | AJ13: =IFERROR(VLOOKUP(Tabela3[[#This Row],[Produto]],Tabela2[],13,0),0) -> 15.6 | AK13: =IFERROR(VLOOKUP(Tabela3[[#This Row],[Produto]],Tabela2[],14,0),0) -> Senun | AL13: =IFERROR(VLOOKUP(Tabela3[[#This Row],[Produto]],Tabela2[],15,0),0) -> 3.5 | AM13: =(Tabela3[[#This Row],[Custo Usinagem]]+Tabela3[[#This Row],[Custo / Pç]])*1.2 -> 16.162578 | AN13: =Tabela3[[#This Row],[Valor Mínimo Venda]]*1.15 -> 18.586964 | AO13: =Tabela3[[#This Row],[Tabela 1]]*1.08 -> 20.073921 | AP13: =Tabela3[[#This Row],[Tabela 2]]*1.15 -> 23.08501
... A99: 45729 | B99: Centro da Banda (3224429P) - Fundido | C99: 5751 | D99: Daniel Garcia | E99: Victor Hugo | F99: 49 | G99: 0.19166667 | H99: 0 | I99: =IFERROR(Tabela3[[#This Row],[Custo Total]]/Tabela3[[#This Row],[Aluminio Util]],0) -> 23.213409 | J99: =Tabela3[[#This Row],[Custo Total]]/Tabela3[[#This Row],[Realizado]] -> 39.23066 | K99: =IFERROR(Tabela3[[#This Row],[Qtde Cx Produzida]]/Tabela3[[#This Row],[Tempo]]/24,0) -> 10.652174 | L99: =Tabela3[[#This Row],[Qtde Cx Produzida]]*Tabela3[[#This Row],[Qdt Peça Placa]] -> 49 | M99: =Tabela3[[#This Row],[Previsto]]-Tabela3[[#This Row],[Perda Pçs]] -> 49 | N99: =IFERROR(Tabela3[[#This Row],[Perda Pçs]]/Tabela3[[#This Row],[Previsto]],0) -> 0 | O99: =IFERROR(IF(Tabela3[[#This Row],[Qtde Cx Produzida]] <> 0, Tabela3[[#This Row],[Tempo]] / Tabela3[[#This Row],[Qtde Cx Produzida]], 0),0) -> 0.0039115646 | P99: =IFERROR(Tabela3[[#This Row],[Perda Pçs]]/Tabela3[[#This Row],[Qdt Peça Placa]],0) -> 0 | Q99: =IFERROR(Tabela3[[#This Row],[Realizado]]*Tabela3[[#This Row],[Peso Util/Pç]],0) -> 82.81 | R99: =IFERROR(Tabela3[[#This Row],[Peso Total Galho]]*Tabela3[[#This Row],[Qtde Cx Produzida]]*1.055,0) -> 154.56805 | S99: =(Tabela3[[#This Row],[Aluminio Bruto]]-Tabela3[[#This Row],[Aluminio Util]])*0.9 -> 64.582245 | T99: =Tabela3[[#This Row],[Aluminio Bruto]]/OleoKGAluminio -> 65.026579 | U99: =IFERROR((VLOOKUP(Tabela3[[#This Row],[Moldador]],Tabela1[],5,)+(VLOOKUP(Tabela3[[#This Row],[Ajudante]],Tabela1[],5,))*3.5),0) -> 99.950346 | V99: =IFERROR(Tabela3[[#This Row],[Custo M.O. / H]]/((Tabela3[[#This Row],[Realizado]]/Tabela3[[#This Row],[Qdt Peça Placa]])/Tabela3[[#This Row],[Tempo]]/24),) -> 9.3830937 | W99: =Tabela3[[#This Row],[Custo / Cx Moldada]]*Tabela3[[#This Row],[Qtde Cx Produzida]] -> 459.77159 | X99: =Tabela3[[#This Row],[Aluminio Util]]*Tabela3[[#This Row],[Custo/Kg]] -> 1291.836 | Y99: =IFERROR(VLOOKUP(Tabela3[[#This Row],[Data]],Tabela461213[],2,1)*(Tabela3[[#This Row],[Qtde Cx Produzida]]*Tabela3[[#This Row],[Qde macho / CX]]*Tabela3[[#This Row],[Peso Macho]]),) -> 0 | Z99: =IFERROR(Tabela3[[#This Row],[Qtde Oleo]]*(VLOOKUP(Tabela3[[#This Row],[Data]],CompraOleo[],3,TRUE))*1.05,0) -> 170.69477 | AA99: =(Tabela3[[#This Row],[Custo Oleo]]+Tabela3[[#This Row],[Custo Aluminio]]+Tabela3[[#This Row],[Custo M.O. Total]]+Tabela3[[#This Row],[Custo Machos]]) -> 1922.3024 | AB99: =Tabela3[[#This Row],[Custo Total]]*Tabela3[[#This Row],[% Perda]] -> 0 | AC99: =IFERROR(VLOOKUP(Tabela3[[#This Row],[Produto]],Tabela2[],2,0),0) -> 1 | AD99: =IFERROR(VLOOKUP(Tabela3[[#This Row],[Produto]],Tabela2[],3,0),0) -> 1.69 | AE99: =IFERROR(VLOOKUP(Tabela3[[#This Row],[Produto]],Tabela2[],4,0),0) -> 2.99 | AF99: =IFERROR(VLOOKUP(Tabela3[[#This Row],[Produto]],Tabela2[],5,0),0) -> 1.17 | AG99: =IFERROR(VLOOKUP(Tabela3[[#This Row],[Produto]],Tabela2[],6,0),0) -> 0 | AH99: =IFERROR(VLOOKUP(Tabela3[[#This Row],[Produto]],Tabela2[],7,0),0) -> 0 | AI99: =IFERROR(VLOOKUP(Tabela3[[#This Row],[Produto]],Tabela2[],8,0),0) -> 0 | AJ99: =IFERROR(VLOOKUP(Tabela3[[#This Row],[Produto]],Tabela2[],13,0),0) -> 15.6 | AK99: =IFERROR(VLOOKUP(Tabela3[[#This Row],[Produto]],Tabela2[],14,0),0) -> Jumil | AL99: =IFERROR(VLOOKUP(Tabela3[[#This Row],[Produto]],Tabela2[],15,0),0) -> 8 | AM99: =(Tabela3[[#This Row],[Custo Usinagem]]+Tabela3[[#This Row],[Custo / Pç]])*1.2 -> 56.676792 | AN99: =Tabela3[[#This Row],[Valor Mínimo Venda]]*1.15 -> 65.178311 | AO99: =Tabela3[[#This Row],[Tabela 1]]*1.08 -> 70.392576 | AP99: =Tabela3[[#This Row],[Tabela 2]]*1.15 -> 80.951463
A100: 45729 | B100: Ventilador Grande 45093000 Fundido | C100: 5891 | D100: Daniel Garcia | E100: Victor Hugo | F100: 16 | G100: 0.15972222 | I100: =IFERROR(Tabela3[[#This Row],[Custo Total]]/Tabela3[[#This Row],[Aluminio Util]],0) -> 29.128048 | J100: =Tabela3[[#This Row],[Custo Total]]/Tabela3[[#This Row],[Realizado]] -> 73.693962 | K100: =IFERROR(Tabela3[[#This Row],[Qtde Cx Produzida]]/Tabela3[[#This Row],[Tempo]]/24,0) -> 4.173913 | L100: =Tabela3[[#This Row],[Qtde Cx Produzida]]*Tabela3[[#This Row],[Qdt Peça Placa]] -> 16 | M100: =Tabela3[[#This Row],[Previsto]]-Tabela3[[#This Row],[Perda Pçs]] -> 16 | N100: =IFERROR(Tabela3[[#This Row],[Perda Pçs]]/Tabela3[[#This Row],[Previsto]],0) -> 0 | O100: =IFERROR(IF(Tabela3[[#This Row],[Qtde Cx Produzida]] <> 0, Tabela3[[#This Row],[Tempo]] / Tabela3[[#This Row],[Qtde Cx Produzida]], 0),0) -> 0.0099826389 | P100: =IFERROR(Tabela3[[#This Row],[Perda Pçs]]/Tabela3[[#This Row],[Qdt Peça Placa]],0) -> 0 | Q100: =IFERROR(Tabela3[[#This Row],[Realizado]]*Tabela3[[#This Row],[Peso Util/Pç]],0) -> 40.48 | R100: =IFERROR(Tabela3[[#This Row],[Peso Total Galho]]*Tabela3[[#This Row],[Qtde Cx Produzida]]*1.055,0) -> 75.6224 | S100: =(Tabela3[[#This Row],[Aluminio Bruto]]-Tabela3[[#This Row],[Aluminio Util]])*0.9 -> 31.62816 | T100: =Tabela3[[#This Row],[Aluminio Bruto]]/OleoKGAluminio -> 31.814246 | U100: =IFERROR((VLOOKUP(Tabela3[[#This Row],[Moldador]],Tabela1[],5,)+(VLOOKUP(Tabela3[[#This Row],[Ajudante]],Tabela1[],5,))*3.5),0) -> 99.950346 | V100: =IFERROR(Tabela3[[#This Row],[Custo M.O. / H]]/((Tabela3[[#This Row],[Realizado]]/Tabela3[[#This Row],[Qdt Peça Placa]])/Tabela3[[#This Row],[Tempo]]/24),) -> 23.946437 | W100: =Tabela3[[#This Row],[Custo / Cx Moldada]]*Tabela3[[#This Row],[Qtde Cx Produzida]] -> 383.14299 | X100: =Tabela3[[#This Row],[Aluminio Util]]*Tabela3[[#This Row],[Custo/Kg]] -> 712.448 | Y100: =IFERROR(VLOOKUP(Tabela3[[#This Row],[Data]],Tabela461213[],2,1)*(Tabela3[[#This Row],[Qtde Cx Produzida]]*Tabela3[[#This Row],[Qde macho / CX]]*Tabela3[[#This Row],[Peso Macho]]),) -> 0 | Z100: =IFERROR(Tabela3[[#This Row],[Qtde Oleo]]*(VLOOKUP(Tabela3[[#This Row],[Data]],CompraOleo[],3,TRUE))*1.05,0) -> 83.512395 | AA100: =(Tabela3[[#This Row],[Custo Oleo]]+Tabela3[[#This Row],[Custo Aluminio]]+Tabela3[[#This Row],[Custo M.O. Total]]+Tabela3[[#This Row],[Custo Machos]]) -> 1179.1034 | AB100: =Tabela3[[#This Row],[Custo Total]]*Tabela3[[#This Row],[% Perda]] -> 0 | AC100: =IFERROR(VLOOKUP(Tabela3[[#This Row],[Produto]],Tabela2[],2,0),0) -> 1 | AD100: =IFERROR(VLOOKUP(Tabela3[[#This Row],[Produto]],Tabela2[],3,0),0) -> 2.53 | AE100: =IFERROR(VLOOKUP(Tabela3[[#This Row],[Produto]],Tabela2[],4,0),0) -> 4.48 | AF100: =IFERROR(VLOOKUP(Tabela3[[#This Row],[Produto]],Tabela2[],5,0),0) -> 1.755 | AG100: =IFERROR(VLOOKUP(Tabela3[[#This Row],[Produto]],Tabela2[],6,0),0) -> 0 | AH100: =IFERROR(VLOOKUP(Tabela3[[#This Row],[Produto]],Tabela2[],7,0),0) -> 0 | AI100: =IFERROR(VLOOKUP(Tabela3[[#This Row],[Produto]],Tabela2[],8,0),0) -> 0 | AJ100: =IFERROR(VLOOKUP(Tabela3[[#This Row],[Produto]],Tabela2[],13,0),0) -> 17.6 | AK100: =IFERROR(VLOOKUP(Tabela3[[#This Row],[Produto]],Tabela2[],14,0),0) -> Bambozzi | AL100: =IFERROR(VLOOKUP(Tabela3[[#This Row],[Produto]],Tabela2[],15,0),0) -> 15 | AM100: =(Tabela3[[#This Row],[Custo Usinagem]]+Tabela3[[#This Row],[Custo / Pç]])*1.2 -> 106.43275 | AN100: =Tabela3[[#This Row],[Valor Mínimo Venda]]*1.15 -> 122.39767 | AO100: =Tabela3[[#This Row],[Tabela 1]]*1.08 -> 132.18948 | AP100: =Tabela3[[#This Row],[Tabela 2]]*1.15 -> 152.0179
A101: 45730 | B101: Ventilador Grande 45093000 Fundido | C101: 5891 | D101: Daniel Garcia | E101: Victor Hugo | F101: 67 | G101: 0.36041667 | H101: 1 | I101: =IFERROR(Tabela3[[#This Row],[Custo Total]]/Tabela3[[#This Row],[Aluminio Util]],0) -> 24.95045 | J101: =Tabela3[[#This Row],[Custo Total]]/Tabela3[[#This Row],[Realizado]] -> 63.124639 | K101: =IFERROR(Tabela3[[#This Row],[Qtde Cx Produzida]]/Tabela3[[#This Row],[Tempo]]/24,0) -> 7.7456647 | L101: =Tabela3[[#This Row],[Qtde Cx Produzida]]*Tabela3[[#This Row],[Qdt Peça Placa]] -> 67 | M101: =Tabela3[[#This Row],[Previsto]]-Tabela3[[#This Row],[Perda Pçs]] -> 66 | N101: =IFERROR(Tabela3[[#This Row],[Perda Pçs]]/Tabela3[[#This Row],[Previsto]],0) -> 0.014925373 | O101: =IFERROR(IF(Tabela3[[#This Row],[Qtde Cx Produzida]] <> 0, Tabela3[[#This Row],[Tempo]] / Tabela3[[#This Row],[Qtde Cx Produzida]], 0),0) -> 0.0053793532 | P101: =IFERROR(Tabela3[[#This Row],[Perda Pçs]]/Tabela3[[#This Row],[Qdt Peça Placa]],0) -> 1 | Q101: =IFERROR(Tabela3[[#This Row],[Realizado]]*Tabela3[[#This Row],[Peso Util/Pç]],0) -> 166.98 | R101: =IFERROR(Tabela3[[#This Row],[Peso Total Galho]]*Tabela3[[#This Row],[Qtde Cx Produzida]]*1.055,0) -> 316.6688 | S101: =(Tabela3[[#This Row],[Aluminio Bruto]]-Tabela3[[#This Row],[Aluminio Util]])*0.9 -> 134.71992 | T101: =Tabela3[[#This Row],[Aluminio Bruto]]/OleoKGAluminio -> 133.22215 | U101: =IFERROR((VLOOKUP(Tabela3[[#This Row],[Moldador]],Tabela1[],5,)+(VLOOKUP(Tabela3[[#This Row],[Ajudante]],Tabela1[],5,))*3.5),0) -> 99.950346 | V101: =IFERROR(Tabela3[[#This Row],[Custo M.O. / H]]/((Tabela3[[#This Row],[Realizado]]/Tabela3[[#This Row],[Qdt Peça Placa]])/Tabela3[[#This Row],[Tempo]]/24),) -> 13.099553 | W101: =Tabela3[[#This Row],[Custo / Cx Moldada]]*Tabela3[[#This Row],[Qtde Cx Produzida]] -> 877.67004 | X101: =Tabela3[[#This Row],[Aluminio Util]]*Tabela3[[#This Row],[Custo/Kg]] -> 2938.848 | Y101: =IFERROR(VLOOKUP(Tabela3[[#This Row],[Data]],Tabela461213[],2,1)*(Tabela3[[#This Row],[Qtde Cx Produzida]]*Tabela3[[#This Row],[Qde macho / CX]]*Tabela3[[#This Row],[Peso Macho]]),) -> 0 | Z101: =IFERROR(Tabela3[[#This Row],[Qtde Oleo]]*(VLOOKUP(Tabela3[[#This Row],[Data]],CompraOleo[],3,TRUE))*1.05,0) -> 349.70816 | AA101: =(Tabela3[[#This Row],[Custo Oleo]]+Tabela3[[#This Row],[Custo Aluminio]]+Tabela3[[#This Row],[Custo M.O. Total]]+Tabela3[[#This Row],[Custo Machos]]) -> 4166.2262 | AB101: =Tabela3[[#This Row],[Custo Total]]*Tabela3[[#This Row],[% Perda]] -> 62.182481 | AC101: =IFERROR(VLOOKUP(Tabela3[[#This Row],[Produto]],Tabela2[],2,0),0) -> 1 | AD101: =IFERROR(VLOOKUP(Tabela3[[#This Row],[Produto]],Tabela2[],3,0),0) -> 2.53 | AE101: =IFERROR(VLOOKUP(Tabela3[[#This Row],[Produto]],Tabela2[],4,0),0) -> 4.48 | AF101: =IFERROR(VLOOKUP(Tabela3[[#This Row],[Produto]],Tabela2[],5,0),0) -> 1.755 | AG101: =IFERROR(VLOOKUP(Tabela3[[#This Row],[Produto]],Tabela2[],6,0),0) -> 0 | AH101: =IFERROR(VLOOKUP(Tabela3[[#This Row],[Produto]],Tabela2[],7,0),0) -> 0 | AI101: =IFERROR(VLOOKUP(Tabela3[[#This Row],[Produto]],Tabela2[],8,0),0) -> 0 | AJ101: =IFERROR(VLOOKUP(Tabela3[[#This Row],[Produto]],Tabela2[],13,0),0) -> 17.6 | AK101: =IFERROR(VLOOKUP(Tabela3[[#This Row],[Produto]],Tabela2[],14,0),0) -> Bambozzi | AL101: =IFERROR(VLOOKUP(Tabela3[[#This Row],[Produto]],Tabela2[],15,0),0) -> 15 | AM101: =(Tabela3[[#This Row],[Custo Usinagem]]+Tabela3[[#This Row],[Custo / Pç]])*1.2 -> 93.749567 | AN101: =Tabela3[[#This Row],[Valor Mínimo Venda]]*1.15 -> 107.812 | AO101: =Tabela3[[#This Row],[Tabela 1]]*1.08 -> 116.43696 | AP101: =Tabela3[[#This Row],[Tabela 2]]*1.15 -> 133.90251
A102: 45730 | B102: Protetor de Campainha Intelbras - Fundido | C102: 5856 | D102: Marcelo Santos | E102: Claudio Henrique | F102: 34 | G102: 0.17777778 | H102: 0 | I102: =IFERROR(Tabela3[[#This Row],[Custo Total]]/Tabela3[[#This Row],[Aluminio Util]],0) -> 30.705948 | J102: =Tabela3[[#This Row],[Custo Total]]/Tabela3[[#This Row],[Realizado]] -> 3.8382435 | K102: =IFERROR(Tabela3[[#This Row],[Qtde Cx Produzida]]/Tabela3[[#This Row],[Tempo]]/24,0) -> 7.96875 | L102: =Tabela3[[#This Row],[Qtde Cx Produzida]]*Tabela3[[#This Row],[Qdt Peça Placa]] -> 272 | M102: =Tabela3[[#This Row],[Previsto]]-Tabela3[[#This Row],[Perda Pçs]] -> 272 | N102: =IFERROR(Tabela3[[#This Row],[Perda Pçs]]/Tabela3[[#This Row],[Previsto]],0) -> 0 | O102: =IFERROR(IF(Tabela3[[#This Row],[Qtde Cx Produzida]] <> 0, Tabela3[[#This Row],[Tempo]] / Tabela3[[#This Row],[Qtde Cx Produzida]], 0),0) -> 0.0052287582 | P102: =IFERROR(Tabela3[[#This Row],[Perda Pçs]]/Tabela3[[#This Row],[Qdt Peça Placa]],0) -> 0 | Q102: =IFERROR(Tabela3[[#This Row],[Realizado]]*Tabela3[[#This Row],[Peso Util/Pç]],0) -> 34 | R102: =IFERROR(Tabela3[[#This Row],[Peso Total Galho]]*Tabela3[[#This Row],[Qtde Cx Produzida]]*1.055,0) -> 78.914 | S102: =(Tabela3[[#This Row],[Aluminio Bruto]]-Tabela3[[#This Row],[Aluminio Util]])*0.9 -> 40.4226 | T102: =Tabela3[[#This Row],[Aluminio Bruto]]/OleoKGAluminio -> 33.199018 | U102: =IFERROR((VLOOKUP(Tabela3[[#This Row],[Moldador]],Tabela1[],5,)+(VLOOKUP(Tabela3[[#This Row],[Ajudante]],Tabela1[],5,))*3.5),0) -> 99.950346 | V102: =IFERROR(Tabela3[[#This Row],[Custo M.O. / H]]/((Tabela3[[#This Row],[Realizado]]/Tabela3[[#This Row],[Qdt Peça Placa]])/Tabela3[[#This Row],[Tempo]]/24),) -> 12.542788 | W102: =Tabela3[[#This Row],[Custo / Cx Moldada]]*Tabela3[[#This Row],[Qtde Cx Produzida]] -> 426.45481 | X102: =Tabela3[[#This Row],[Aluminio Util]]*Tabela3[[#This Row],[Custo/Kg]] -> 530.4 | Y102: =IFERROR(VLOOKUP(Tabela3[[#This Row],[Data]],Tabela461213[],2,1)*(Tabela3[[#This Row],[Qtde Cx Produzida]]*Tabela3[[#This Row],[Qde macho / CX]]*Tabela3[[#This Row],[Peso Macho]]),) -> 0 | Z102: =IFERROR(Tabela3[[#This Row],[Qtde Oleo]]*(VLOOKUP(Tabela3[[#This Row],[Data]],CompraOleo[],3,TRUE))*1.05,0) -> 87.147422 | AA102: =(Tabela3[[#This Row],[Custo Oleo]]+Tabela3[[#This Row],[Custo Aluminio]]+Tabela3[[#This Row],[Custo M.O. Total]]+Tabela3[[#This Row],[Custo Machos]]) -> 1044.0022 | AB102: =Tabela3[[#This Row],[Custo Total]]*Tabela3[[#This Row],[% Perda]] -> 0 | AC102: =IFERROR(VLOOKUP(Tabela3[[#This Row],[Produto]],Tabela2[],2,0),0) -> 8 | AD102: =IFERROR(VLOOKUP(Tabela3[[#This Row],[Produto]],Tabela2[],3,0),0) -> 0.125 | AE102: =IFERROR(VLOOKUP(Tabela3[[#This Row],[Produto]],Tabela2[],4,0),0) -> 2.2 | AF102: =IFERROR(VLOOKUP(Tabela3[[#This Row],[Produto]],Tabela2[],5,0),0) -> 1.08 | AG102: =IFERROR(VLOOKUP(Tabela3[[#This Row],[Produto]],Tabela2[],6,0),0) -> 0 | AH102: =IFERROR(VLOOKUP(Tabela3[[#This Row],[Produto]],Tabela2[],7,0),0) -> 0 | AI102: =IFERROR(VLOOKUP(Tabela3[[#This Row],[Produto]],Tabela2[],8,0),0) -> 0 | AJ102: =IFERROR(VLOOKUP(Tabela3[[#This Row],[Produto]],Tabela2[],13,0),0) -> 15.6 | AK102: =IFERROR(VLOOKUP(Tabela3[[#This Row],[Produto]],Tabela2[],14,0),0) -> Senun | AL102: =IFERROR(VLOOKUP(Tabela3[[#This Row],[Produto]],Tabela2[],15,0),0) -> 7 | AM102: =(Tabela3[[#This Row],[Custo Usinagem]]+Tabela3[[#This Row],[Custo / Pç]])*1.2 -> 13.005892 | AN102: =Tabela3[[#This Row],[Valor Mínimo Venda]]*1.15 -> 14.956776 | AO102: =Tabela3[[#This Row],[Tabela 1]]*1.08 -> 16.153318 | AP102: =Tabela3[[#This Row],[Tabela 2]]*1.15 -> 18.576316
A103: 45730 | B103: Polia 305J16 (2726161P) Fundido | C103: 5928 | D103: Marcelo Santos | E103: Claudio Henrique | F103: 20 | G103: 0.098611111 | H103: 0 | I103: =IFERROR(Tabela3[[#This Row],[Custo Total]]/Tabela3[[#This Row],[Aluminio Util]],0) -> 21.367565 | J103: =Tabela3[[#This Row],[Custo Total]]/Tabela3[[#This Row],[Realizado]] -> 59.572772 | K103: =IFERROR(Tabela3[[#This Row],[Qtde Cx Produzida]]/Tabela3[[#This Row],[Tempo]]/24,0) -> 8.4507042 | L103: =Tabela3[[#This Row],[Qtde Cx Produzida]]*Tabela3[[#This Row],[Qdt Peça Placa]] -> 20 | M103: =Tabela3[[#This Row],[Previsto]]-Tabela3[[#This Row],[Perda Pçs]] -> 20 | N103: =IFERROR(Tabela3[[#This Row],[Perda Pçs]]/Tabela3[[#This Row],[Previsto]],0) -> 0 | O103: =IFERROR(IF(Tabela3[[#This Row],[Qtde Cx Produzida]] <> 0, Tabela3[[#This Row],[Tempo]] / Tabela3[[#This Row],[Qtde Cx Produzida]], 0),0) -> 0.0049305556 | P103: =IFERROR(Tabela3[[#This Row],[Perda Pçs]]/Tabela3[[#This Row],[Qdt Peça Placa]],0) -> 0 | Q103: =IFERROR(Tabela3[[#This Row],[Realizado]]*Tabela3[[#This Row],[Peso Util/Pç]],0) -> 55.76 | R103: =IFERROR(Tabela3[[#This Row],[Peso Total Galho]]*Tabela3[[#This Row],[Qtde Cx Produzida]]*1.055,0) -> 77.015 | S103: =(Tabela3[[#This Row],[Aluminio Bruto]]-Tabela3[[#This Row],[Aluminio Util]])*0.9 -> 19.1295 | T103: =Tabela3[[#This Row],[Aluminio Bruto]]/OleoKGAluminio -> 32.400111 | U103: =IFERROR((VLOOKUP(Tabela3[[#This Row],[Moldador]],Tabela1[],5,)+(VLOOKUP(Tabela3[[#This Row],[Ajudante]],Tabela1[],5,))*3.5),0) -> 99.950346 | V103: =IFERROR(Tabela3[[#This Row],[Custo M.O. / H]]/((Tabela3[[#This Row],[Realizado]]/Tabela3[[#This Row],[Qdt Peça Placa]])/Tabela3[[#This Row],[Tempo]]/24),) -> 11.827458 | W103: =Tabela3[[#This Row],[Custo / Cx Moldada]]*Tabela3[[#This Row],[Qtde Cx Produzida]] -> 236.54915 | X103: =Tabela3[[#This Row],[Aluminio Util]]*Tabela3[[#This Row],[Custo/Kg]] -> 869.856 | Y103: =IFERROR(VLOOKUP(Tabela3[[#This Row],[Data]],Tabela461213[],2,1)*(Tabela3[[#This Row],[Qtde Cx Produzida]]*Tabela3[[#This Row],[Qde macho / CX]]*Tabela3[[#This Row],[Peso Macho]]),) -> 0 | Z103: =IFERROR(Tabela3[[#This Row],[Qtde Oleo]]*(VLOOKUP(Tabela3[[#This Row],[Data]],CompraOleo[],3,TRUE))*1.05,0) -> 85.050291 | AA103: =(Tabela3[[#This Row],[Custo Oleo]]+Tabela3[[#This Row],[Custo Aluminio]]+Tabela3[[#This Row],[Custo M.O. Total]]+Tabela3[[#This Row],[Custo Machos]]) -> 1191.4554 | AB103: =Tabela3[[#This Row],[Custo Total]]*Tabela3[[#This Row],[% Perda]] -> 0 | AC103: =IFERROR(VLOOKUP(Tabela3[[#This Row],[Produto]],Tabela2[],2,0),0) -> 1 | AD103: =IFERROR(VLOOKUP(Tabela3[[#This Row],[Produto]],Tabela2[],3,0),0) -> 2.788 | AE103: =IFERROR(VLOOKUP(Tabela3[[#This Row],[Produto]],Tabela2[],4,0),0) -> 3.65 | AF103: =IFERROR(VLOOKUP(Tabela3[[#This Row],[Produto]],Tabela2[],5,0),0) -> 0.7758 | AG103: =IFERROR(VLOOKUP(Tabela3[[#This Row],[Produto]],Tabela2[],6,0),0) -> 0 | AH103: =IFERROR(VLOOKUP(Tabela3[[#This Row],[Produto]],Tabela2[],7,0),0) -> 0 | AI103: =IFERROR(VLOOKUP(Tabela3[[#This Row],[Produto]],Tabela2[],8,0),0) -> 0 | AJ103: =IFERROR(VLOOKUP(Tabela3[[#This Row],[Produto]],Tabela2[],13,0),0) -> 15.6 | AK103: =IFERROR(VLOOKUP(Tabela3[[#This Row],[Produto]],Tabela2[],14,0),0) -> Jumil | AL103: =IFERROR(VLOOKUP(Tabela3[[#This Row],[Produto]],Tabela2[],15,0),0) -> 35 | AM103: =(Tabela3[[#This Row],[Custo Usinagem]]+Tabela3[[#This Row],[Custo / Pç]])*1.2 -> 113.48733 | AN103: =Tabela3[[#This Row],[Valor Mínimo Venda]]*1.15 -> 130.51043 | AO103: =Tabela3[[#This Row],[Tabela 1]]*1.08 -> 140.95126 | AP103: =Tabela3[[#This Row],[Tabela 2]]*1.15 -> 162.09395
A104: 45733 | B104: Ventilador Grande 45093000 Fundido | C104: 5891 | D104: Daniel Garcia | E104: Marcelo Santos | F104: 17 | G104: 0.075694444 | H104: 0 | I104: =IFERROR(Tabela3[[#This Row],[Custo Total]]/Tabela3[[#This Row],[Aluminio Util]],0) -> 24.989063 | J104: =Tabela3[[#This Row],[Custo Total]]/Tabela3[[#This Row],[Realizado]] -> 63.222329 | K104: =IFERROR(Tabela3[[#This Row],[Qtde Cx Produzida]]/Tabela3[[#This Row],[Tempo]]/24,0) -> 9.3577982 | L104: =Tabela3[[#This Row],[Qtde Cx Produzida]]*Tabela3[[#This Row],[Qdt Peça Placa]] -> 17 | M104: =Tabela3[[#This Row],[Previsto]]-Tabela3[[#This Row],[Perda Pçs]] -> 17 | N104: =IFERROR(Tabela3[[#This Row],[Perda Pçs]]/Tabela3[[#This Row],[Previsto]],0) -> 0 | O104: =IFERROR(IF(Tabela3[[#This Row],[Qtde Cx Produzida]] <> 0, Tabela3[[#This Row],[Tempo]] / Tabela3[[#This Row],[Qtde Cx Produzida]], 0),0) -> 0.0044526144 | P104: =IFERROR(Tabela3[[#This Row],[Perda Pçs]]/Tabela3[[#This Row],[Qdt Peça Placa]],0) -> 0 | Q104: =IFERROR(Tabela3[[#This Row],[Realizado]]*Tabela3[[#This Row],[Peso Util/Pç]],0) -> 43.01 | R104: =IFERROR(Tabela3[[#This Row],[Peso Total Galho]]*Tabela3[[#This Row],[Qtde Cx Produzida]]*1.055,0) -> 80.3488 | S104: =(Tabela3[[#This Row],[Aluminio Bruto]]-Tabela3[[#This Row],[Aluminio Util]])*0.9 -> 33.60492 | T104: =Tabela3[[#This Row],[Aluminio Bruto]]/OleoKGAluminio -> 33.802636 | U104: =IFERROR((VLOOKUP(Tabela3[[#This Row],[Moldador]],Tabela1[],5,)+(VLOOKUP(Tabela3[[#This Row],[Ajudante]],Tabela1[],5,))*3.5),0) -> 126.0945 | V104: =IFERROR(Tabela3[[#This Row],[Custo M.O. / H]]/((Tabela3[[#This Row],[Realizado]]/Tabela3[[#This Row],[Qdt Peça Placa]])/Tabela3[[#This Row],[Tempo]]/24),) -> 13.474804 | W104: =Tabela3[[#This Row],[Custo / Cx Moldada]]*Tabela3[[#This Row],[Qtde Cx Produzida]] -> 229.07167 | X104: =Tabela3[[#This Row],[Aluminio Util]]*Tabela3[[#This Row],[Custo/Kg]] -> 756.976 | Y104: =IFERROR(VLOOKUP(Tabela3[[#This Row],[Data]],Tabela461213[],2,1)*(Tabela3[[#This Row],[Qtde Cx Produzida]]*Tabela3[[#This Row],[Qde macho / CX]]*Tabela3[[#This Row],[Peso Macho]]),) -> 0 | Z104: =IFERROR(Tabela3[[#This Row],[Qtde Oleo]]*(VLOOKUP(Tabela3[[#This Row],[Data]],CompraOleo[],3,TRUE))*1.05,0) -> 88.73192 | AA104: =(Tabela3[[#This Row],[Custo Oleo]]+Tabela3[[#This Row],[Custo Aluminio]]+Tabela3[[#This Row],[Custo M.O. Total]]+Tabela3[[#This Row],[Custo Machos]]) -> 1074.7796 | AB104: =Tabela3[[#This Row],[Custo Total]]*Tabela3[[#This Row],[% Perda]] -> 0 | AC104: =IFERROR(VLOOKUP(Tabela3[[#This Row],[Produto]],Tabela2[],2,0),0) -> 1 | AD104: =IFERROR(VLOOKUP(Tabela3[[#This Row],[Produto]],Tabela2[],3,0),0) -> 2.53 | AE104: =IFERROR(VLOOKUP(Tabela3[[#This Row],[Produto]],Tabela2[],4,0),0) -> 4.48 | AF104: =IFERROR(VLOOKUP(Tabela3[[#This Row],[Produto]],Tabela2[],5,0),0) -> 1.755 | AG104: =IFERROR(VLOOKUP(Tabela3[[#This Row],[Produto]],Tabela2[],6,0),0) -> 0 | AH104: =IFERROR(VLOOKUP(Tabela3[[#This Row],[Produto]],Tabela2[],7,0),0) -> 0 | AI104: =IFERROR(VLOOKUP(Tabela3[[#This Row],[Produto]],Tabela2[],8,0),0) -> 0 | AJ104: =IFERROR(VLOOKUP(Tabela3[[#This Row],[Produto]],Tabela2[],13,0),0) -> 17.6 | AK104: =IFERROR(VLOOKUP(Tabela3[[#This Row],[Produto]],Tabela2[],14,0),0) -> Bambozzi | AL104: =IFERROR(VLOOKUP(Tabela3[[#This Row],[Produto]],Tabela2[],15,0),0) -> 15 | AM104: =(Tabela3[[#This Row],[Custo Usinagem]]+Tabela3[[#This Row],[Custo / Pç]])*1.2 -> 93.866795 | AN104: =Tabela3[[#This Row],[Valor Mínimo Venda]]*1.15 -> 107.94681 | AO104: =Tabela3[[#This Row],[Tabela 1]]*1.08 -> 116.58256 | AP104: =Tabela3[[#This Row],[Tabela 2]]*1.15 -> 134.06994
A105: 45733 | B105: VENTILADOR NOVO | C105: 5968 | D105: Daniel Garcia | E105: Marcelo Santos | F105: 15 | G105: 0.12847222 | H105: 0 | I105: =IFERROR(Tabela3[[#This Row],[Custo Total]]/Tabela3[[#This Row],[Aluminio Util]],0) -> 29.701084 | J105: =Tabela3[[#This Row],[Custo Total]]/Tabela3[[#This Row],[Realizado]] -> 72.767657 | K105: =IFERROR(Tabela3[[#This Row],[Qtde Cx Produzida]]/Tabela3[[#This Row],[Tempo]]/24,0) -> 4.8648649 | L105: =Tabela3[[#This Row],[Qtde Cx Produzida]]*Tabela3[[#This Row],[Qdt Peça Placa]] -> 15 | M105: =Tabela3[[#This Row],[Previsto]]-Tabela3[[#This Row],[Perda Pçs]] -> 15 | N105: =IFERROR(Tabela3[[#This Row],[Perda Pçs]]/Tabela3[[#This Row],[Previsto]],0) -> 0 | O105: =IFERROR(IF(Tabela3[[#This Row],[Qtde Cx Produzida]] <> 0, Tabela3[[#This Row],[Tempo]] / Tabela3[[#This Row],[Qtde Cx Produzida]], 0),0) -> 0.0085648148 | P105: =IFERROR(Tabela3[[#This Row],[Perda Pçs]]/Tabela3[[#This Row],[Qdt Peça Placa]],0) -> 0 | Q105: =IFERROR(Tabela3[[#This Row],[Realizado]]*Tabela3[[#This Row],[Peso Util/Pç]],0) -> 36.75 | R105: =IFERROR(Tabela3[[#This Row],[Peso Total Galho]]*Tabela3[[#This Row],[Qtde Cx Produzida]]*1.055,0) -> 50.64 | S105: =(Tabela3[[#This Row],[Aluminio Bruto]]-Tabela3[[#This Row],[Aluminio Util]])*0.9 -> 12.501 | T105: =Tabela3[[#This Row],[Aluminio Bruto]]/OleoKGAluminio -> 21.304183 | U105: =IFERROR((VLOOKUP(Tabela3[[#This Row],[Moldador]],Tabela1[],5,)+(VLOOKUP(Tabela3[[#This Row],[Ajudante]],Tabela1[],5,))*3.5),0) -> 126.0945 | V105: =IFERROR(Tabela3[[#This Row],[Custo M.O. / H]]/((Tabela3[[#This Row],[Realizado]]/Tabela3[[#This Row],[Qdt Peça Placa]])/Tabela3[[#This Row],[Tempo]]/24),) -> 25.919425 | W105: =Tabela3[[#This Row],[Custo / Cx Moldada]]*Tabela3[[#This Row],[Qtde Cx Produzida]] -> 388.79137 | X105: =Tabela3[[#This Row],[Aluminio Util]]*Tabela3[[#This Row],[Custo/Kg]] -> 646.8 | Y105: =IFERROR(VLOOKUP(Tabela3[[#This Row],[Data]],Tabela461213[],2,1)*(Tabela3[[#This Row],[Qtde Cx Produzida]]*Tabela3[[#This Row],[Qde macho / CX]]*Tabela3[[#This Row],[Peso Macho]]),) -> 0 | Z105: =IFERROR(Tabela3[[#This Row],[Qtde Oleo]]*(VLOOKUP(Tabela3[[#This Row],[Data]],CompraOleo[],3,TRUE))*1.05,0) -> 55.923479 | AA105: =(Tabela3[[#This Row],[Custo Oleo]]+Tabela3[[#This Row],[Custo Aluminio]]+Tabela3[[#This Row],[Custo M.O. Total]]+Tabela3[[#This Row],[Custo Machos]]) -> 1091.5149 | AB105: =Tabela3[[#This Row],[Custo Total]]*Tabela3[[#This Row],[% Perda]] -> 0 | AC105: =IFERROR(VLOOKUP(Tabela3[[#This Row],[Produto]],Tabela2[],2,0),0) -> 1 | AD105: =IFERROR(VLOOKUP(Tabela3[[#This Row],[Produto]],Tabela2[],3,0),0) -> 2.45 | AE105: =IFERROR(VLOOKUP(Tabela3[[#This Row],[Produto]],Tabela2[],4,0),0) -> 3.2 | AF105: =IFERROR(VLOOKUP(Tabela3[[#This Row],[Produto]],Tabela2[],5,0),0) -> 0.675 | AG105: =IFERROR(VLOOKUP(Tabela3[[#This Row],[Produto]],Tabela2[],6,0),0) -> 0 | AH105: =IFERROR(VLOOKUP(Tabela3[[#This Row],[Produto]],Tabela2[],7,0),0) -> 0 | AI105: =IFERROR(VLOOKUP(Tabela3[[#This Row],[Produto]],Tabela2[],8,0),0) -> 0 | AJ105: =IFERROR(VLOOKUP(Tabela3[[#This Row],[Produto]],Tabela2[],13,0),0) -> 17.6 | AK105: =IFERROR(VLOOKUP(Tabela3[[#This Row],[Produto]],Tabela2[],14,0),0) -> Bambozzi | AL105: =IFERROR(VLOOKUP(Tabela3[[#This Row],[Produto]],Tabela2[],15,0),0) -> 12 | AM105: =(Tabela3[[#This Row],[Custo Usinagem]]+Tabela3[[#This Row],[Custo / Pç]])*1.2 -> 101.72119 | AN105: =Tabela3[[#This Row],[Valor Mínimo Venda]]*1.15 -> 116.97937 | AO105: =Tabela3[[#This Row],[Tabela 1]]*1.08 -> 126.33772 | AP105: =Tabela3[[#This Row],[Tabela 2]]*1.15 -> 145.28837
A106: 45733 | B106: Prot. Interfone Coletivo Intelbras 4,8 e 12 Canais Fundido | C106: 5927 | D106: Daniel Garcia | E106: Marcelo Santos | F106: 26 | G106: 0.14236111 | H106: 5 | I106: =IFERROR(Tabela3[[#This Row],[Custo Total]]/Tabela3[[#This Row],[Aluminio Util]],0) -> 25.228937 | J106: =Tabela3[[#This Row],[Custo Total]]/Tabela3[[#This Row],[Realizado]] -> 15.465338 | K106: =IFERROR(Tabela3[[#This Row],[Qtde Cx Produzida]]/Tabela3[[#This Row],[Tempo]]/24,0) -> 7.6097561 | L106: =Tabela3[[#This Row],[Qtde Cx Produzida]]*Tabela3[[#This Row],[Qdt Peça Placa]] -> 104 | M106: =Tabela3[[#This Row],[Previsto]]-Tabela3[[#This Row],[Perda Pçs]] -> 99 | N106: =IFERROR(Tabela3[[#This Row],[Perda Pçs]]/Tabela3[[#This Row],[Previsto]],0) -> 0.048076923 | O106: =IFERROR(IF(Tabela3[[#This Row],[Qtde Cx Produzida]] <> 0, Tabela3[[#This Row],[Tempo]] / Tabela3[[#This Row],[Qtde Cx Produzida]], 0),0) -> 0.0054754274 | P106: =IFERROR(Tabela3[[#This Row],[Perda Pçs]]/Tabela3[[#This Row],[Qdt Peça Placa]],0) -> 1.25 | Q106: =IFERROR(Tabela3[[#This Row],[Realizado]]*Tabela3[[#This Row],[Peso Util/Pç]],0) -> 60.687 | R106: =IFERROR(Tabela3[[#This Row],[Peso Total Galho]]*Tabela3[[#This Row],[Qtde Cx Produzida]]*1.055,0) -> 119.3205 | S106: =(Tabela3[[#This Row],[Aluminio Bruto]]-Tabela3[[#This Row],[Aluminio Util]])*0.9 -> 52.77015 | T106: =Tabela3[[#This Row],[Aluminio Bruto]]/OleoKGAluminio -> 50.19798 | U106: =IFERROR((VLOOKUP(Tabela3[[#This Row],[Moldador]],Tabela1[],5,)+(VLOOKUP(Tabela3[[#This Row],[Ajudante]],Tabela1[],5,))*3.5),0) -> 126.0945 | V106: =IFERROR(Tabela3[[#This Row],[Custo M.O. / H]]/((Tabela3[[#This Row],[Realizado]]/Tabela3[[#This Row],[Qdt Peça Placa]])/Tabela3[[#This Row],[Tempo]]/24),) -> 17.406985 | W106: =Tabela3[[#This Row],[Custo / Cx Moldada]]*Tabela3[[#This Row],[Qtde Cx Produzida]] -> 452.58161 | X106: =Tabela3[[#This Row],[Aluminio Util]]*Tabela3[[#This Row],[Custo/Kg]] -> 946.7172 | Y106: =IFERROR(VLOOKUP(Tabela3[[#This Row],[Data]],Tabela461213[],2,1)*(Tabela3[[#This Row],[Qtde Cx Produzida]]*Tabela3[[#This Row],[Qde macho / CX]]*Tabela3[[#This Row],[Peso Macho]]),) -> 0 | Z106: =IFERROR(Tabela3[[#This Row],[Qtde Oleo]]*(VLOOKUP(Tabela3[[#This Row],[Data]],CompraOleo[],3,TRUE))*1.05,0) -> 131.7697 | AA106: =(Tabela3[[#This Row],[Custo Oleo]]+Tabela3[[#This Row],[Custo Aluminio]]+Tabela3[[#This Row],[Custo M.O. Total]]+Tabela3[[#This Row],[Custo Machos]]) -> 1531.0685 | AB106: =Tabela3[[#This Row],[Custo Total]]*Tabela3[[#This Row],[% Perda]] -> 73.609063 | AC106: =IFERROR(VLOOKUP(Tabela3[[#This Row],[Produto]],Tabela2[],2,0),0) -> 4 | AD106: =IFERROR(VLOOKUP(Tabela3[[#This Row],[Produto]],Tabela2[],3,0),0) -> 0.613 | AE106: =IFERROR(VLOOKUP(Tabela3[[#This Row],[Produto]],Tabela2[],4,0),0) -> 4.35 | AF106: =IFERROR(VLOOKUP(Tabela3[[#This Row],[Produto]],Tabela2[],5,0),0) -> 1.7082 | AG106: =IFERROR(VLOOKUP(Tabela3[[#This Row],[Produto]],Tabela2[],6,0),0) -> 0 | AH106: =IFERROR(VLOOKUP(Tabela3[[#This Row],[Produto]],Tabela2[],7,0),0) -> 0 | AI106: =IFERROR(VLOOKUP(Tabela3[[#This Row],[Produto]],Tabela2[],8,0),0) -> 0 | AJ106: =IFERROR(VLOOKUP(Tabela3[[#This Row],[Produto]],Tabela2[],13,0),0) -> 15.6 | AK106: =IFERROR(VLOOKUP(Tabela3[[#This Row],[Produto]],Tabela2[],14,0),0) -> Senun | AL106: =IFERROR(VLOOKUP(Tabela3[[#This Row],[Produto]],Tabela2[],15,0),0) -> 4 | AM106: =(Tabela3[[#This Row],[Custo Usinagem]]+Tabela3[[#This Row],[Custo / Pç]])*1.2 -> 23.358406 | AN106: =Tabela3[[#This Row],[Valor Mínimo Venda]]*1.15 -> 26.862167 | AO106: =Tabela3[[#This Row],[Tabela 1]]*1.08 -> 29.01114 | AP106: =Tabela3[[#This Row],[Tabela 2]]*1.15 -> 33.362811
A107: 45734 | B107: Prot. Interfone Coletivo Intelbras 4,8 e 12 Canais Fundido | C107: 5927 | D107: Daniel Garcia | E107: Victor Hugo | F107: 24 | G107: 0.13055556 | H107: 0 | I107: =IFERROR(Tabela3[[#This Row],[Custo Total]]/Tabela3[[#This Row],[Aluminio Util]],0) -> 22.988719 | J107: =Tabela3[[#This Row],[Custo Total]]/Tabela3[[#This Row],[Realizado]] -> 14.092085 | K107: =IFERROR(Tabela3[[#This Row],[Qtde Cx Produzida]]/Tabela3[[#This Row],[Tempo]]/24,0) -> 7.6595745 | L107: =Tabela3[[#This Row],[Qtde Cx Produzida]]*Tabela3[[#This Row],[Qdt Peça Placa]] -> 96 | M107: =Tabela3[[#This Row],[Previsto]]-Tabela3[[#This Row],[Perda Pçs]] -> 96 | N107: =IFERROR(Tabela3[[#This Row],[Perda Pçs]]/Tabela3[[#This Row],[Previsto]],0) -> 0 | O107: =IFERROR(IF(Tabela3[[#This Row],[Qtde Cx Produzida]] <> 0, Tabela3[[#This Row],[Tempo]] / Tabela3[[#This Row],[Qtde Cx Produzida]], 0),0) -> 0.0054398148 | P107: =IFERROR(Tabela3[[#This Row],[Perda Pçs]]/Tabela3[[#This Row],[Qdt Peça Placa]],0) -> 0 | Q107: =IFERROR(Tabela3[[#This Row],[Realizado]]*Tabela3[[#This Row],[Peso Util/Pç]],0) -> 58.848 | R107: =IFERROR(Tabela3[[#This Row],[Peso Total Galho]]*Tabela3[[#This Row],[Qtde Cx Produzida]]*1.055,0) -> 110.142 | S107: =(Tabela3[[#This Row],[Aluminio Bruto]]-Tabela3[[#This Row],[Aluminio Util]])*0.9 -> 46.1646 | T107: =Tabela3[[#This Row],[Aluminio Bruto]]/OleoKGAluminio -> 46.336597 | U107: =IFERROR((VLOOKUP(Tabela3[[#This Row],[Moldador]],Tabela1[],5,)+(VLOOKUP(Tabela3[[#This Row],[Ajudante]],Tabela1[],5,))*3.5),0) -> 99.950346 | V107: =IFERROR(Tabela3[[#This Row],[Custo M.O. / H]]/((Tabela3[[#This Row],[Realizado]]/Tabela3[[#This Row],[Qdt Peça Placa]])/Tabela3[[#This Row],[Tempo]]/24),) -> 13.049073 | W107: =Tabela3[[#This Row],[Custo / Cx Moldada]]*Tabela3[[#This Row],[Qtde Cx Produzida]] -> 313.17775 | X107: =Tabela3[[#This Row],[Aluminio Util]]*Tabela3[[#This Row],[Custo/Kg]] -> 918.0288 | Y107: =IFERROR(VLOOKUP(Tabela3[[#This Row],[Data]],Tabela461213[],2,1)*(Tabela3[[#This Row],[Qtde Cx Produzida]]*Tabela3[[#This Row],[Qde macho / CX]]*Tabela3[[#This Row],[Peso Macho]]),) -> 0 | Z107: =IFERROR(Tabela3[[#This Row],[Qtde Oleo]]*(VLOOKUP(Tabela3[[#This Row],[Data]],CompraOleo[],3,TRUE))*1.05,0) -> 121.63357 | AA107: =(Tabela3[[#This Row],[Custo Oleo]]+Tabela3[[#This Row],[Custo Aluminio]]+Tabela3[[#This Row],[Custo M.O. Total]]+Tabela3[[#This Row],[Custo Machos]]) -> 1352.8401 | AB107: =Tabela3[[#This Row],[Custo Total]]*Tabela3[[#This Row],[% Perda]] -> 0 | AC107: =IFERROR(VLOOKUP(Tabela3[[#This Row],[Produto]],Tabela2[],2,0),0) -> 4 | AD107: =IFERROR(VLOOKUP(Tabela3[[#This Row],[Produto]],Tabela2[],3,0),0) -> 0.613 | AE107: =IFERROR(VLOOKUP(Tabela3[[#This Row],[Produto]],Tabela2[],4,0),0) -> 4.35 | AF107: =IFERROR(VLOOKUP(Tabela3[[#This Row],[Produto]],Tabela2[],5,0),0) -> 1.7082 | AG107: =IFERROR(VLOOKUP(Tabela3[[#This Row],[Produto]],Tabela2[],6,0),0) -> 0 | AH107: =IFERROR(VLOOKUP(Tabela3[[#This Row],[Produto]],Tabela2[],7,0),0) -> 0 | AI107: =IFERROR(VLOOKUP(Tabela3[[#This Row],[Produto]],Tabela2[],8,0),0) -> 0 | AJ107: =IFERROR(VLOOKUP(Tabela3[[#This Row],[Produto]],Tabela2[],13,0),0) -> 15.6 | AK107: =IFERROR(VLOOKUP(Tabela3[[#This Row],[Produto]],Tabela2[],14,0),0) -> Senun | AL107: =IFERROR(VLOOKUP(Tabela3[[#This Row],[Produto]],Tabela2[],15,0),0) -> 4 | AM107: =(Tabela3[[#This Row],[Custo Usinagem]]+Tabela3[[#This Row],[Custo / Pç]])*1.2 -> 21.710501 | AN107: =Tabela3[[#This Row],[Valor Mínimo Venda]]*1.15 -> 24.967077 | AO107: =Tabela3[[#This Row],[Tabela 1]]*1.08 -> 26.964443 | AP107: =Tabela3[[#This Row],[Tabela 2]]*1.15 -> 31.009109
A108: 45734 | B108: Prot. Interfone Xpe 1001/1013 Plus Id Intelbras Fundido | C108: 5926 | D108: Daniel Garcia | E108: Victor Hugo | F108: 41 | G108: 0.22291667 | H108: 23 | I108: =IFERROR(Tabela3[[#This Row],[Custo Total]]/Tabela3[[#This Row],[Aluminio Util]],0) -> 30.097937 | J108: =Tabela3[[#This Row],[Custo Total]]/Tabela3[[#This Row],[Realizado]] -> 10.775061 | K108: =IFERROR(Tabela3[[#This Row],[Qtde Cx Produzida]]/Tabela3[[#This Row],[Tempo]]/24,0) -> 7.6635514 | L108: =Tabela3[[#This Row],[Qtde Cx Produzida]]*Tabela3[[#This Row],[Qdt Peça Placa]] -> 164 | M108: =Tabela3[[#This Row],[Previsto]]-Tabela3[[#This Row],[Perda Pçs]] -> 141 | N108: =IFERROR(Tabela3[[#This Row],[Perda Pçs]]/Tabela3[[#This Row],[Previsto]],0) -> 0.1402439 | O108: =IFERROR(IF(Tabela3[[#This Row],[Qtde Cx Produzida]] <> 0, Tabela3[[#This Row],[Tempo]] / Tabela3[[#This Row],[Qtde Cx Produzida]], 0),0) -> 0.0054369919 | P108: =IFERROR(Tabela3[[#This Row],[Perda Pçs]]/Tabela3[[#This Row],[Qdt Peça Placa]],0) -> 5.75 | Q108: =IFERROR(Tabela3[[#This Row],[Realizado]]*Tabela3[[#This Row],[Peso Util/Pç]],0) -> 50.478 | R108: =IFERROR(Tabela3[[#This Row],[Peso Total Galho]]*Tabela3[[#This Row],[Qtde Cx Produzida]]*1.055,0) -> 99.4865 | S108: =(Tabela3[[#This Row],[Aluminio Bruto]]-Tabela3[[#This Row],[Aluminio Util]])*0.9 -> 44.10765 | T108: =Tabela3[[#This Row],[Aluminio Bruto]]/OleoKGAluminio -> 41.853842 | U108: =IFERROR((VLOOKUP(Tabela3[[#This Row],[Moldador]],Tabela1[],5,)+(VLOOKUP(Tabela3[[#This Row],[Ajudante]],Tabela1[],5,))*3.5),0) -> 99.950346 | V108: =IFERROR(Tabela3[[#This Row],[Custo M.O. / H]]/((Tabela3[[#This Row],[Realizado]]/Tabela3[[#This Row],[Qdt Peça Placa]])/Tabela3[[#This Row],[Tempo]]/24),) -> 15.169769 | W108: =Tabela3[[#This Row],[Custo / Cx Moldada]]*Tabela3[[#This Row],[Qtde Cx Produzida]] -> 621.96052 | X108: =Tabela3[[#This Row],[Aluminio Util]]*Tabela3[[#This Row],[Custo/Kg]] -> 787.4568 | Y108: =IFERROR(VLOOKUP(Tabela3[[#This Row],[Data]],Tabela461213[],2,1)*(Tabela3[[#This Row],[Qtde Cx Produzida]]*Tabela3[[#This Row],[Qde macho / CX]]*Tabela3[[#This Row],[Peso Macho]]),) -> 0 | Z108: =IFERROR(Tabela3[[#This Row],[Qtde Oleo]]*(VLOOKUP(Tabela3[[#This Row],[Data]],CompraOleo[],3,TRUE))*1.05,0) -> 109.86634 | AA108: =(Tabela3[[#This Row],[Custo Oleo]]+Tabela3[[#This Row],[Custo Aluminio]]+Tabela3[[#This Row],[Custo M.O. Total]]+Tabela3[[#This Row],[Custo Machos]]) -> 1519.2837 | AB108: =Tabela3[[#This Row],[Custo Total]]*Tabela3[[#This Row],[% Perda]] -> 213.07027 | AC108: =IFERROR(VLOOKUP(Tabela3[[#This Row],[Produto]],Tabela2[],2,0),0) -> 4 | AD108: =IFERROR(VLOOKUP(Tabela3[[#This Row],[Produto]],Tabela2[],3,0),0) -> 0.358 | AE108: =IFERROR(VLOOKUP(Tabela3[[#This Row],[Produto]],Tabela2[],4,0),0) -> 2.3 | AF108: =IFERROR(VLOOKUP(Tabela3[[#This Row],[Produto]],Tabela2[],5,0),0) -> 0.7812 | AG108: =IFERROR(VLOOKUP(Tabela3[[#This Row],[Produto]],Tabela2[],6,0),0) -> 0 | AH108: =IFERROR(VLOOKUP(Tabela3[[#This Row],[Produto]],Tabela2[],7,0),0) -> 0 | AI108: =IFERROR(VLOOKUP(Tabela3[[#This Row],[Produto]],Tabela2[],8,0),0) -> 0 | AJ108: =IFERROR(VLOOKUP(Tabela3[[#This Row],[Produto]],Tabela2[],13,0),0) -> 15.6 | AK108: =IFERROR(VLOOKUP(Tabela3[[#This Row],[Produto]],Tabela2[],14,0),0) -> Senun | AL108: =IFERROR(VLOOKUP(Tabela3[[#This Row],[Produto]],Tabela2[],15,0),0) -> 4 | AM108: =(Tabela3[[#This Row],[Custo Usinagem]]+Tabela3[[#This Row],[Custo / Pç]])*1.2 -> 17.730074 | AN108: =Tabela3[[#This Row],[Valor Mínimo Venda]]*1.15 -> 20.389585 | AO108: =Tabela3[[#This Row],[Tabela 1]]*1.08 -> 22.020751 | AP108: =Tabela3[[#This Row],[Tabela 2]]*1.15 -> 25.323864
A109: 45734 | B109: Prot. Interfone Intelbras 7010 Fundido | C109: 5944 | D109: Marcelo Santos | E109: Claudio Henrique | F109: 48 | G109: 0.22083333 | H109: 25 | I109: =IFERROR(Tabela3[[#This Row],[Custo Total]]/Tabela3[[#This Row],[Aluminio Util]],0) -> 28.904645 | J109: =Tabela3[[#This Row],[Custo Total]]/Tabela3[[#This Row],[Realizado]] -> 9.5963423 | K109: =IFERROR(Tabela3[[#This Row],[Qtde Cx Produzida]]/Tabela3[[#This Row],[Tempo]]/24,0) -> 9.0566038 | L109: =Tabela3[[#This Row],[Qtde Cx Produzida]]*Tabela3[[#This Row],[Qdt Peça Placa]] -> 192 | M109: =Tabela3[[#This Row],[Previsto]]-Tabela3[[#This Row],[Perda Pçs]] -> 167 | N109: =IFERROR(Tabela3[[#This Row],[Perda Pçs]]/Tabela3[[#This Row],[Previsto]],0) -> 0.13020833 | O109: =IFERROR(IF(Tabela3[[#This Row],[Qtde Cx Produzida]] <> 0, Tabela3[[#This Row],[Tempo]] / Tabela3[[#This Row],[Qtde Cx Produzida]], 0),0) -> 0.0046006944 | P109: =IFERROR(Tabela3[[#This Row],[Perda Pçs]]/Tabela3[[#This Row],[Qdt Peça Placa]],0) -> 6.25 | Q109: =IFERROR(Tabela3[[#This Row],[Realizado]]*Tabela3[[#This Row],[Peso Util/Pç]],0) -> 55.444 | R109: =IFERROR(Tabela3[[#This Row],[Peso Total Galho]]*Tabela3[[#This Row],[Qtde Cx Produzida]]*1.055,0) -> 116.472 | S109: =(Tabela3[[#This Row],[Aluminio Bruto]]-Tabela3[[#This Row],[Aluminio Util]])*0.9 -> 54.9252 | T109: =Tabela3[[#This Row],[Aluminio Bruto]]/OleoKGAluminio -> 48.99962 | U109: =IFERROR((VLOOKUP(Tabela3[[#This Row],[Moldador]],Tabela1[],5,)+(VLOOKUP(Tabela3[[#This Row],[Ajudante]],Tabela1[],5,))*3.5),0) -> 99.950346 | V109: =IFERROR(Tabela3[[#This Row],[Custo M.O. / H]]/((Tabela3[[#This Row],[Realizado]]/Tabela3[[#This Row],[Qdt Peça Placa]])/Tabela3[[#This Row],[Tempo]]/24),) -> 12.688307 | W109: =Tabela3[[#This Row],[Custo / Cx Moldada]]*Tabela3[[#This Row],[Qtde Cx Produzida]] -> 609.03875 | X109: =Tabela3[[#This Row],[Aluminio Util]]*Tabela3[[#This Row],[Custo/Kg]] -> 864.9264 | Y109: =IFERROR(VLOOKUP(Tabela3[[#This Row],[Data]],Tabela461213[],2,1)*(Tabela3[[#This Row],[Qtde Cx Produzida]]*Tabela3[[#This Row],[Qde macho / CX]]*Tabela3[[#This Row],[Peso Macho]]),) -> 0 | Z109: =IFERROR(Tabela3[[#This Row],[Qtde Oleo]]*(VLOOKUP(Tabela3[[#This Row],[Data]],CompraOleo[],3,TRUE))*1.05,0) -> 128.624 | AA109: =(Tabela3[[#This Row],[Custo Oleo]]+Tabela3[[#This Row],[Custo Aluminio]]+Tabela3[[#This Row],[Custo M.O. Total]]+Tabela3[[#This Row],[Custo Machos]]) -> 1602.5892 | AB109: =Tabela3[[#This Row],[Custo Total]]*Tabela3[[#This Row],[% Perda]] -> 208.67046 | AC109: =IFERROR(VLOOKUP(Tabela3[[#This Row],[Produto]],Tabela2[],2,0),0) -> 4 | AD109: =IFERROR(VLOOKUP(Tabela3[[#This Row],[Produto]],Tabela2[],3,0),0) -> 0.332 | AE109: =IFERROR(VLOOKUP(Tabela3[[#This Row],[Produto]],Tabela2[],4,0),0) -> 2.3 | AF109: =IFERROR(VLOOKUP(Tabela3[[#This Row],[Produto]],Tabela2[],5,0),0) -> 0.8748 | AG109: =IFERROR(VLOOKUP(Tabela3[[#This Row],[Produto]],Tabela2[],6,0),0) -> 0 | AH109: =IFERROR(VLOOKUP(Tabela3[[#This Row],[Produto]],Tabela2[],7,0),0) -> 0 | AI109: =IFERROR(VLOOKUP(Tabela3[[#This Row],[Produto]],Tabela2[],8,0),0) -> 0 | AJ109: =IFERROR(VLOOKUP(Tabela3[[#This Row],[Produto]],Tabela2[],13,0),0) -> 15.6 | AK109: =IFERROR(VLOOKUP(Tabela3[[#This Row],[Produto]],Tabela2[],14,0),0) -> Senun | AL109: =IFERROR(VLOOKUP(Tabela3[[#This Row],[Produto]],Tabela2[],15,0),0) -> 3.5 | AM109: =(Tabela3[[#This Row],[Custo Usinagem]]+Tabela3[[#This Row],[Custo / Pç]])*1.2 -> 15.715611 | AN109: =Tabela3[[#This Row],[Valor Mínimo Venda]]*1.15 -> 18.072952 | AO109: =Tabela3[[#This Row],[Tabela 1]]*1.08 -> 19.518788 | AP109: =Tabela3[[#This Row],[Tabela 2]]*1.15 -> 22.446607
A110: 45734 | B110: PLACA FBO Fundido- OSCAR | C110: 5711 | D110: Marcelo Santos | E110: Claudio Henrique | F110: 7 | G110: 0.11180556 | H110: 0 | I110: =IFERROR(Tabela3[[#This Row],[Custo Total]]/Tabela3[[#This Row],[Aluminio Util]],0) -> 20.270422 | J110: =Tabela3[[#This Row],[Custo Total]]/Tabela3[[#This Row],[Realizado]] -> 547.3014 | K110: =IFERROR(Tabela3[[#This Row],[Qtde Cx Produzida]]/Tabela3[[#This Row],[Tempo]]/24,0) -> 2.6086957 | L110: =Tabela3[[#This Row],[Qtde Cx Produzida]]*Tabela3[[#This Row],[Qdt Peça Placa]] -> 7 | M110: =Tabela3[[#This Row],[Previsto]]-Tabela3[[#This Row],[Perda Pçs]] -> 7 | N110: =IFERROR(Tabela3[[#This Row],[Perda Pçs]]/Tabela3[[#This Row],[Previsto]],0) -> 0 | O110: =IFERROR(IF(Tabela3[[#This Row],[Qtde Cx Produzida]] <> 0, Tabela3[[#This Row],[Tempo]] / Tabela3[[#This Row],[Qtde Cx Produzida]], 0),0) -> 0.015972222 | P110: =IFERROR(Tabela3[[#This Row],[Perda Pçs]]/Tabela3[[#This Row],[Qdt Peça Placa]],0) -> 0 | Q110: =IFERROR(Tabela3[[#This Row],[Realizado]]*Tabela3[[#This Row],[Peso Util/Pç]],0) -> 189 | R110: =IFERROR(Tabela3[[#This Row],[Peso Total Galho]]*Tabela3[[#This Row],[Qtde Cx Produzida]]*1.055,0) -> 214.165 | S110: =(Tabela3[[#This Row],[Aluminio Bruto]]-Tabela3[[#This Row],[Aluminio Util]])*0.9 -> 22.6485 | T110: =Tabela3[[#This Row],[Aluminio Bruto]]/OleoKGAluminio -> 90.098939 | U110: =IFERROR((VLOOKUP(Tabela3[[#This Row],[Moldador]],Tabela1[],5,)+(VLOOKUP(Tabela3[[#This Row],[Ajudante]],Tabela1[],5,))*3.5),0) -> 99.950346 | V110: =IFERROR(Tabela3[[#This Row],[Custo M.O. / H]]/((Tabela3[[#This Row],[Realizado]]/Tabela3[[#This Row],[Qdt Peça Placa]])/Tabela3[[#This Row],[Tempo]]/24),) -> 38.314299 | W110: =Tabela3[[#This Row],[Custo / Cx Moldada]]*Tabela3[[#This Row],[Qtde Cx Produzida]] -> 268.20009 | X110: =Tabela3[[#This Row],[Aluminio Util]]*Tabela3[[#This Row],[Custo/Kg]] -> 3326.4 | Y110: =IFERROR(VLOOKUP(Tabela3[[#This Row],[Data]],Tabela461213[],2,1)*(Tabela3[[#This Row],[Qtde Cx Produzida]]*Tabela3[[#This Row],[Qde macho / CX]]*Tabela3[[#This Row],[Peso Macho]]),) -> 0 | Z110: =IFERROR(Tabela3[[#This Row],[Qtde Oleo]]*(VLOOKUP(Tabela3[[#This Row],[Data]],CompraOleo[],3,TRUE))*1.05,0) -> 236.50971 | AA110: =(Tabela3[[#This Row],[Custo Oleo]]+Tabela3[[#This Row],[Custo Aluminio]]+Tabela3[[#This Row],[Custo M.O. Total]]+Tabela3[[#This Row],[Custo Machos]]) -> 3831.1098 | AB110: =Tabela3[[#This Row],[Custo Total]]*Tabela3[[#This Row],[% Perda]] -> 0 | AC110: =IFERROR(VLOOKUP(Tabela3[[#This Row],[Produto]],Tabela2[],2,0),0) -> 1 | AD110: =IFERROR(VLOOKUP(Tabela3[[#This Row],[Produto]],Tabela2[],3,0),0) -> 27 | AE110: =IFERROR(VLOOKUP(Tabela3[[#This Row],[Produto]],Tabela2[],4,0),0) -> 29 | AF110: =IFERROR(VLOOKUP(Tabela3[[#This Row],[Produto]],Tabela2[],5,0),0) -> 1.8 | AG110: =IFERROR(VLOOKUP(Tabela3[[#This Row],[Produto]],Tabela2[],6,0),0) -> 0 | AH110: =IFERROR(VLOOKUP(Tabela3[[#This Row],[Produto]],Tabela2[],7,0),0) -> 0 | AI110: =IFERROR(VLOOKUP(Tabela3[[#This Row],[Produto]],Tabela2[],8,0),0) -> 0 | AJ110: =IFERROR(VLOOKUP(Tabela3[[#This Row],[Produto]],Tabela2[],13,0),0) -> 17.6 | AK110: =IFERROR(VLOOKUP(Tabela3[[#This Row],[Produto]],Tabela2[],14,0),0) -> Oscar | AL110: =IFERROR(VLOOKUP(Tabela3[[#This Row],[Produto]],Tabela2[],15,0),0) -> 0 | AM110: =(Tabela3[[#This Row],[Custo Usinagem]]+Tabela3[[#This Row],[Custo / Pç]])*1.2 -> 656.76168 | AN110: =Tabela3[[#This Row],[Valor Mínimo Venda]]*1.15 -> 755.27593 | AO110: =Tabela3[[#This Row],[Tabela 1]]*1.08 -> 815.69801 | AP110: =Tabela3[[#This Row],[Tabela 2]]*1.15 -> 938.05271
A111: 45734 | B111: MODELO SOLTO - OSCAR | C111: 6045 | D111: Marcelo Santos | E111: Claudio Henrique | F111: 2 | G111: 0.013888889 | H111: 0 | I111: =IFERROR(Tabela3[[#This Row],[Custo Total]]/Tabela3[[#This Row],[Aluminio Util]],0) -> 19.399053 | J111: =Tabela3[[#This Row],[Custo Total]]/Tabela3[[#This Row],[Realizado]] -> 570.33215 | K111: =IFERROR(Tabela3[[#This Row],[Qtde Cx Produzida]]/Tabela3[[#This Row],[Tempo]]/24,0) -> 6 | L111: =Tabela3[[#This Row],[Qtde Cx Produzida]]*Tabela3[[#This Row],[Qdt Peça Placa]] -> 2 | M111: =Tabela3[[#This Row],[Previsto]]-Tabela3[[#This Row],[Perda Pçs]] -> 2 | N111: =IFERROR(Tabela3[[#This Row],[Perda Pçs]]/Tabela3[[#This Row],[Previsto]],0) -> 0 | O111: =IFERROR(IF(Tabela3[[#This Row],[Qtde Cx Produzida]] <> 0, Tabela3[[#This Row],[Tempo]] / Tabela3[[#This Row],[Qtde Cx Produzida]], 0),0) -> 0.0069444444 | P111: =IFERROR(Tabela3[[#This Row],[Perda Pçs]]/Tabela3[[#This Row],[Qdt Peça Placa]],0) -> 0 | Q111: =IFERROR(Tabela3[[#This Row],[Realizado]]*Tabela3[[#This Row],[Peso Util/Pç]],0) -> 58.8 | R111: =IFERROR(Tabela3[[#This Row],[Peso Total Galho]]*Tabela3[[#This Row],[Qtde Cx Produzida]]*1.055,0) -> 65.621 | S111: =(Tabela3[[#This Row],[Aluminio Bruto]]-Tabela3[[#This Row],[Aluminio Util]])*0.9 -> 6.1389 | T111: =Tabela3[[#This Row],[Aluminio Bruto]]/OleoKGAluminio -> 27.60667 | U111: =IFERROR((VLOOKUP(Tabela3[[#This Row],[Moldador]],Tabela1[],5,)+(VLOOKUP(Tabela3[[#This Row],[Ajudante]],Tabela1[],5,))*3.5),0) -> 99.950346 | V111: =IFERROR(Tabela3[[#This Row],[Custo M.O. / H]]/((Tabela3[[#This Row],[Realizado]]/Tabela3[[#This Row],[Qdt Peça Placa]])/Tabela3[[#This Row],[Tempo]]/24),) -> 16.658391 | W111: =Tabela3[[#This Row],[Custo / Cx Moldada]]*Tabela3[[#This Row],[Qtde Cx Produzida]] -> 33.316782 | X111: =Tabela3[[#This Row],[Aluminio Util]]*Tabela3[[#This Row],[Custo/Kg]] -> 1034.88 | Y111: =IFERROR(VLOOKUP(Tabela3[[#This Row],[Data]],Tabela461213[],2,1)*(Tabela3[[#This Row],[Qtde Cx Produzida]]*Tabela3[[#This Row],[Qde macho / CX]]*Tabela3[[#This Row],[Peso Macho]]),) -> 0 | Z111: =IFERROR(Tabela3[[#This Row],[Qtde Oleo]]*(VLOOKUP(Tabela3[[#This Row],[Data]],CompraOleo[],3,TRUE))*1.05,0) -> 72.467508 | AA111: =(Tabela3[[#This Row],[Custo Oleo]]+Tabela3[[#This Row],[Custo Aluminio]]+Tabela3[[#This Row],[Custo M.O. Total]]+Tabela3[[#This Row],[Custo Machos]]) -> 1140.6643 | AB111: =Tabela3[[#This Row],[Custo Total]]*Tabela3[[#This Row],[% Perda]] -> 0 | AC111: =IFERROR(VLOOKUP(Tabela3[[#This Row],[Produto]],Tabela2[],2,0),0) -> 1 | AD111: =IFERROR(VLOOKUP(Tabela3[[#This Row],[Produto]],Tabela2[],3,0),0) -> 29.4 | AE111: =IFERROR(VLOOKUP(Tabela3[[#This Row],[Produto]],Tabela2[],4,0),0) -> 31.1 | AF111: =IFERROR(VLOOKUP(Tabela3[[#This Row],[Produto]],Tabela2[],5,0),0) -> 1.53 | AG111: =IFERROR(VLOOKUP(Tabela3[[#This Row],[Produto]],Tabela2[],6,0),0) -> 0 | AH111: =IFERROR(VLOOKUP(Tabela3[[#This Row],[Produto]],Tabela2[],7,0),0) -> 0 | AI111: =IFERROR(VLOOKUP(Tabela3[[#This Row],[Produto]],Tabela2[],8,0),0) -> 0 | AJ111: =IFERROR(VLOOKUP(Tabela3[[#This Row],[Produto]],Tabela2[],13,0),0) -> 17.6 | AK111: =IFERROR(VLOOKUP(Tabela3[[#This Row],[Produto]],Tabela2[],14,0),0) -> Oscar | AL111: =IFERROR(VLOOKUP(Tabela3[[#This Row],[Produto]],Tabela2[],15,0),0) -> 4 | AM111: =(Tabela3[[#This Row],[Custo Usinagem]]+Tabela3[[#This Row],[Custo / Pç]])*1.2 -> 689.19857 | AN111: =Tabela3[[#This Row],[Valor Mínimo Venda]]*1.15 -> 792.57836 | AO111: =Tabela3[[#This Row],[Tabela 1]]*1.08 -> 855.98463 | AP111: =Tabela3[[#This Row],[Tabela 2]]*1.15 -> 984.38232
A112: 45735 | B112: Prot. Interfone Xpe 1001/1013 Plus Id Intelbras Fundido | C112: 5926 | D112: Daniel Garcia | E112: Victor Hugo | F112: 9 | G112: 0.052083333 | H112: 5 | I112: =IFERROR(Tabela3[[#This Row],[Custo Total]]/Tabela3[[#This Row],[Aluminio Util]],0) -> 30.84655 | J112: =Tabela3[[#This Row],[Custo Total]]/Tabela3[[#This Row],[Realizado]] -> 11.043065 | K112: =IFERROR(Tabela3[[#This Row],[Qtde Cx Produzida]]/Tabela3[[#This Row],[Tempo]]/24,0) -> 7.2 | L112: =Tabela3[[#This Row],[Qtde Cx Produzida]]*Tabela3[[#This Row],[Qdt Peça Placa]] -> 36 | M112: =Tabela3[[#This Row],[Previsto]]-Tabela3[[#This Row],[Perda Pçs]] -> 31 | N112: =IFERROR(Tabela3[[#This Row],[Perda Pçs]]/Tabela3[[#This Row],[Previsto]],0) -> 0.13888889 | O112: =IFERROR(IF(Tabela3[[#This Row],[Qtde Cx Produzida]] <> 0, Tabela3[[#This Row],[Tempo]] / Tabela3[[#This Row],[Qtde Cx Produzida]], 0),0) -> 0.005787037 | P112: =IFERROR(Tabela3[[#This Row],[Perda Pçs]]/Tabela3[[#This Row],[Qdt Peça Placa]],0) -> 1.25 | Q112: =IFERROR(Tabela3[[#This Row],[Realizado]]*Tabela3[[#This Row],[Peso Util/Pç]],0) -> 11.098 | R112: =IFERROR(Tabela3[[#This Row],[Peso Total Galho]]*Tabela3[[#This Row],[Qtde Cx Produzida]]*1.055,0) -> 21.8385 | S112: =(Tabela3[[#This Row],[Aluminio Bruto]]-Tabela3[[#This Row],[Aluminio Util]])*0.9 -> 9.66645 | T112: =Tabela3[[#This Row],[Aluminio Bruto]]/OleoKGAluminio -> 9.1874287 | U112: =IFERROR((VLOOKUP(Tabela3[[#This Row],[Moldador]],Tabela1[],5,)+(VLOOKUP(Tabela3[[#This Row],[Ajudante]],Tabela1[],5,))*3.5),0) -> 99.950346 | V112: =IFERROR(Tabela3[[#This Row],[Custo M.O. / H]]/((Tabela3[[#This Row],[Realizado]]/Tabela3[[#This Row],[Qdt Peça Placa]])/Tabela3[[#This Row],[Tempo]]/24),) -> 16.121024 | W112: =Tabela3[[#This Row],[Custo / Cx Moldada]]*Tabela3[[#This Row],[Qtde Cx Produzida]] -> 145.08921 | X112: =Tabela3[[#This Row],[Aluminio Util]]*Tabela3[[#This Row],[Custo/Kg]] -> 173.1288 | Y112: =IFERROR(VLOOKUP(Tabela3[[#This Row],[Data]],Tabela461213[],2,1)*(Tabela3[[#This Row],[Qtde Cx Produzida]]*Tabela3[[#This Row],[Qde macho / CX]]*Tabela3[[#This Row],[Peso Macho]]),) -> 0 | Z112: =IFERROR(Tabela3[[#This Row],[Qtde Oleo]]*(VLOOKUP(Tabela3[[#This Row],[Data]],CompraOleo[],3,TRUE))*1.05,0) -> 24.117 | AA112: =(Tabela3[[#This Row],[Custo Oleo]]+Tabela3[[#This Row],[Custo Aluminio]]+Tabela3[[#This Row],[Custo M.O. Total]]+Tabela3[[#This Row],[Custo Machos]]) -> 342.33501 | AB112: =Tabela3[[#This Row],[Custo Total]]*Tabela3[[#This Row],[% Perda]] -> 47.546529 | AC112: =IFERROR(VLOOKUP(Tabela3[[#This Row],[Produto]],Tabela2[],2,0),0) -> 4 | AD112: =IFERROR(VLOOKUP(Tabela3[[#This Row],[Produto]],Tabela2[],3,0),0) -> 0.358 | AE112: =IFERROR(VLOOKUP(Tabela3[[#This Row],[Produto]],Tabela2[],4,0),0) -> 2.3 | AF112: =IFERROR(VLOOKUP(Tabela3[[#This Row],[Produto]],Tabela2[],5,0),0) -> 0.7812 | AG112: =IFERROR(VLOOKUP(Tabela3[[#This Row],[Produto]],Tabela2[],6,0),0) -> 0 | AH112: =IFERROR(VLOOKUP(Tabela3[[#This Row],[Produto]],Tabela2[],7,0),0) -> 0 | AI112: =IFERROR(VLOOKUP(Tabela3[[#This Row],[Produto]],Tabela2[],8,0),0) -> 0 | AJ112: =IFERROR(VLOOKUP(Tabela3[[#This Row],[Produto]],Tabela2[],13,0),0) -> 15.6 | AK112: =IFERROR(VLOOKUP(Tabela3[[#This Row],[Produto]],Tabela2[],14,0),0) -> Senun | AL112: =IFERROR(VLOOKUP(Tabela3[[#This Row],[Produto]],Tabela2[],15,0),0) -> 4 | AM112: =(Tabela3[[#This Row],[Custo Usinagem]]+Tabela3[[#This Row],[Custo / Pç]])*1.2 -> 18.051678 | AN112: =Tabela3[[#This Row],[Valor Mínimo Venda]]*1.15 -> 20.75943 | AO112: =Tabela3[[#This Row],[Tabela 1]]*1.08 -> 22.420184 | AP112: =Tabela3[[#This Row],[Tabela 2]]*1.15 -> 25.783212
... A121: 45737 | B121: TARUGO DE 35mm | C121: 6051 | D121: Marcelo Santos | E121: Claudio Henrique | F121: 20 | G121: 0.083333333 | H121: 0 | I121: =IFERROR(Tabela3[[#This Row],[Custo Total]]/Tabela3[[#This Row],[Aluminio Util]],0) -> 23.879097 | J121: =Tabela3[[#This Row],[Custo Total]]/Tabela3[[#This Row],[Realizado]] -> 47.758194 | K121: =IFERROR(Tabela3[[#This Row],[Qtde Cx Produzida]]/Tabela3[[#This Row],[Tempo]]/24,0) -> 10 | L121: =Tabela3[[#This Row],[Qtde Cx Produzida]]*Tabela3[[#This Row],[Qdt Peça Placa]] -> 20 | M121: =Tabela3[[#This Row],[Previsto]]-Tabela3[[#This Row],[Perda Pçs]] -> 20 | N121: =IFERROR(Tabela3[[#This Row],[Perda Pçs]]/Tabela3[[#This Row],[Previsto]],0) -> 0 | O121: =IFERROR(IF(Tabela3[[#This Row],[Qtde Cx Produzida]] <> 0, Tabela3[[#This Row],[Tempo]] / Tabela3[[#This Row],[Qtde Cx Produzida]], 0),0) -> 0.0041666667 | P121: =IFERROR(Tabela3[[#This Row],[Perda Pçs]]/Tabela3[[#This Row],[Qdt Peça Placa]],0) -> 0 | Q121: =IFERROR(Tabela3[[#This Row],[Realizado]]*Tabela3[[#This Row],[Peso Util/Pç]],0) -> 40 | R121: =IFERROR(Tabela3[[#This Row],[Peso Total Galho]]*Tabela3[[#This Row],[Qtde Cx Produzida]]*1.055,0) -> 46.42 | S121: =(Tabela3[[#This Row],[Aluminio Bruto]]-Tabela3[[#This Row],[Aluminio Util]])*0.9 -> 5.778 | T121: =Tabela3[[#This Row],[Aluminio Bruto]]/OleoKGAluminio -> 19.528834 | U121: =IFERROR((VLOOKUP(Tabela3[[#This Row],[Moldador]],Tabela1[],5,)+(VLOOKUP(Tabela3[[#This Row],[Ajudante]],Tabela1[],5,))*3.5),0) -> 99.950346 | V121: =IFERROR(Tabela3[[#This Row],[Custo M.O. / H]]/((Tabela3[[#This Row],[Realizado]]/Tabela3[[#This Row],[Qdt Peça Placa]])/Tabela3[[#This Row],[Tempo]]/24),) -> 9.9950346 | W121: =Tabela3[[#This Row],[Custo / Cx Moldada]]*Tabela3[[#This Row],[Qtde Cx Produzida]] -> 199.90069 | X121: =Tabela3[[#This Row],[Aluminio Util]]*Tabela3[[#This Row],[Custo/Kg]] -> 704 | Y121: =IFERROR(VLOOKUP(Tabela3[[#This Row],[Data]],Tabela461213[],2,1)*(Tabela3[[#This Row],[Qtde Cx Produzida]]*Tabela3[[#This Row],[Qde macho / CX]]*Tabela3[[#This Row],[Peso Macho]]),) -> 0 | Z121: =IFERROR(Tabela3[[#This Row],[Qtde Oleo]]*(VLOOKUP(Tabela3[[#This Row],[Data]],CompraOleo[],3,TRUE))*1.05,0) -> 51.263189 | AA121: =(Tabela3[[#This Row],[Custo Oleo]]+Tabela3[[#This Row],[Custo Aluminio]]+Tabela3[[#This Row],[Custo M.O. Total]]+Tabela3[[#This Row],[Custo Machos]]) -> 955.16388 | AB121: =Tabela3[[#This Row],[Custo Total]]*Tabela3[[#This Row],[% Perda]] -> 0 | AC121: =IFERROR(VLOOKUP(Tabela3[[#This Row],[Produto]],Tabela2[],2,0),0) -> 1 | AD121: =IFERROR(VLOOKUP(Tabela3[[#This Row],[Produto]],Tabela2[],3,0),0) -> 2 | AE121: =IFERROR(VLOOKUP(Tabela3[[#This Row],[Produto]],Tabela2[],4,0),0) -> 2.2 | AF121: =IFERROR(VLOOKUP(Tabela3[[#This Row],[Produto]],Tabela2[],5,0),0) -> 0.18 | AG121: =IFERROR(VLOOKUP(Tabela3[[#This Row],[Produto]],Tabela2[],6,0),0) -> 0 | AH121: =IFERROR(VLOOKUP(Tabela3[[#This Row],[Produto]],Tabela2[],7,0),0) -> 0 | AI121: =IFERROR(VLOOKUP(Tabela3[[#This Row],[Produto]],Tabela2[],8,0),0) -> 0 | AJ121: =IFERROR(VLOOKUP(Tabela3[[#This Row],[Produto]],Tabela2[],13,0),0) -> 17.6 | AK121: =IFERROR(VLOOKUP(Tabela3[[#This Row],[Produto]],Tabela2[],14,0),0) -> Oscar | AL121: =IFERROR(VLOOKUP(Tabela3[[#This Row],[Produto]],Tabela2[],15,0),0) -> 0 | AM121: =(Tabela3[[#This Row],[Custo Usinagem]]+Tabela3[[#This Row],[Custo / Pç]])*1.2 -> 57.309833 | AN121: =Tabela3[[#This Row],[Valor Mínimo Venda]]*1.15 -> 65.906308 | AO121: =Tabela3[[#This Row],[Tabela 1]]*1.08 -> 71.178812 | AP121: =Tabela3[[#This Row],[Tabela 2]]*1.15 -> 81.855634
A122: 45737 | B122: ESTRADO PARA HUNTER 10 | C122: 6054 | D122: Daniel Garcia | E122: Victor Hugo | F122: 51 | G122: 0.26597222 | I122: =IFERROR(Tabela3[[#This Row],[Custo Total]]/Tabela3[[#This Row],[Aluminio Util]],0) -> 19.369958 | J122: =Tabela3[[#This Row],[Custo Total]]/Tabela3[[#This Row],[Realizado]] -> 96.07499 | K122: =IFERROR(Tabela3[[#This Row],[Qtde Cx Produzida]]/Tabela3[[#This Row],[Tempo]]/24,0) -> 7.9895561 | L122: =Tabela3[[#This Row],[Qtde Cx Produzida]]*Tabela3[[#This Row],[Qdt Peça Placa]] -> 51 | M122: =Tabela3[[#This Row],[Previsto]]-Tabela3[[#This Row],[Perda Pçs]] -> 51 | N122: =IFERROR(Tabela3[[#This Row],[Perda Pçs]]/Tabela3[[#This Row],[Previsto]],0) -> 0 | O122: =IFERROR(IF(Tabela3[[#This Row],[Qtde Cx Produzida]] <> 0, Tabela3[[#This Row],[Tempo]] / Tabela3[[#This Row],[Qtde Cx Produzida]], 0),0) -> 0.0052151416 | P122: =IFERROR(Tabela3[[#This Row],[Perda Pçs]]/Tabela3[[#This Row],[Qdt Peça Placa]],0) -> 0 | Q122: =IFERROR(Tabela3[[#This Row],[Realizado]]*Tabela3[[#This Row],[Peso Util/Pç]],0) -> 252.96 | R122: =IFERROR(Tabela3[[#This Row],[Peso Total Galho]]*Tabela3[[#This Row],[Qtde Cx Produzida]]*1.055,0) -> 285.81216 | S122: =(Tabela3[[#This Row],[Aluminio Bruto]]-Tabela3[[#This Row],[Aluminio Util]])*0.9 -> 29.566944 | T122: =Tabela3[[#This Row],[Aluminio Bruto]]/OleoKGAluminio -> 120.24081 | U122: =IFERROR((VLOOKUP(Tabela3[[#This Row],[Moldador]],Tabela1[],5,)+(VLOOKUP(Tabela3[[#This Row],[Ajudante]],Tabela1[],5,))*3.5),0) -> 99.950346 | V122: =IFERROR(Tabela3[[#This Row],[Custo M.O. / H]]/((Tabela3[[#This Row],[Realizado]]/Tabela3[[#This Row],[Qdt Peça Placa]])/Tabela3[[#This Row],[Tempo]]/24),) -> 12.510125 | W122: =Tabela3[[#This Row],[Custo / Cx Moldada]]*Tabela3[[#This Row],[Qtde Cx Produzida]] -> 638.01637 | X122: =Tabela3[[#This Row],[Aluminio Util]]*Tabela3[[#This Row],[Custo/Kg]] -> 3946.176 | Y122: =IFERROR(VLOOKUP(Tabela3[[#This Row],[Data]],Tabela461213[],2,1)*(Tabela3[[#This Row],[Qtde Cx Produzida]]*Tabela3[[#This Row],[Qde macho / CX]]*Tabela3[[#This Row],[Peso Macho]]),) -> 0 | Z122: =IFERROR(Tabela3[[#This Row],[Qtde Oleo]]*(VLOOKUP(Tabela3[[#This Row],[Data]],CompraOleo[],3,TRUE))*1.05,0) -> 315.63212 | AA122: =(Tabela3[[#This Row],[Custo Oleo]]+Tabela3[[#This Row],[Custo Aluminio]]+Tabela3[[#This Row],[Custo M.O. Total]]+Tabela3[[#This Row],[Custo Machos]]) -> 4899.8245 | AB122: =Tabela3[[#This Row],[Custo Total]]*Tabela3[[#This Row],[% Perda]] -> 0 | AC122: =IFERROR(VLOOKUP(Tabela3[[#This Row],[Produto]],Tabela2[],2,0),0) -> 1 | AD122: =IFERROR(VLOOKUP(Tabela3[[#This Row],[Produto]],Tabela2[],3,0),0) -> 4.96 | AE122: =IFERROR(VLOOKUP(Tabela3[[#This Row],[Produto]],Tabela2[],4,0),0) -> 5.312 | AF122: =IFERROR(VLOOKUP(Tabela3[[#This Row],[Produto]],Tabela2[],5,0),0) -> 0.3168 | AG122: =IFERROR(VLOOKUP(Tabela3[[#This Row],[Produto]],Tabela2[],6,0),0) -> 0 | AH122: =IFERROR(VLOOKUP(Tabela3[[#This Row],[Produto]],Tabela2[],7,0),0) -> 0 | AI122: =IFERROR(VLOOKUP(Tabela3[[#This Row],[Produto]],Tabela2[],8,0),0) -> 0 | AJ122: =IFERROR(VLOOKUP(Tabela3[[#This Row],[Produto]],Tabela2[],13,0),0) -> 15.6 | AK122: =IFERROR(VLOOKUP(Tabela3[[#This Row],[Produto]],Tabela2[],14,0),0) -> Jumil | AL122: =IFERROR(VLOOKUP(Tabela3[[#This Row],[Produto]],Tabela2[],15,0),0) -> 1 | AM122: =(Tabela3[[#This Row],[Custo Usinagem]]+Tabela3[[#This Row],[Custo / Pç]])*1.2 -> 116.48999 | AN122: =Tabela3[[#This Row],[Valor Mínimo Venda]]*1.15 -> 133.96349 | AO122: =Tabela3[[#This Row],[Tabela 1]]*1.08 -> 144.68057 | AP122: =Tabela3[[#This Row],[Tabela 2]]*1.15 -> 166.38265
A123: 45740 | B123: Centro da Banda (3224429P) - Fundido | C123: 6013 | D123: Daniel Garcia | E123: Victor Hugo | F123: 90 | G123: 0.35694444 | H123: 0 | I123: =IFERROR(Tabela3[[#This Row],[Custo Total]]/Tabela3[[#This Row],[Aluminio Util]],0) -> 23.290745 | J123: =Tabela3[[#This Row],[Custo Total]]/Tabela3[[#This Row],[Realizado]] -> 39.361359 | K123: =IFERROR(Tabela3[[#This Row],[Qtde Cx Produzida]]/Tabela3[[#This Row],[Tempo]]/24,0) -> 10.505837 | L123: =Tabela3[[#This Row],[Qtde Cx Produzida]]*Tabela3[[#This Row],[Qdt Peça Placa]] -> 90 | M123: =Tabela3[[#This Row],[Previsto]]-Tabela3[[#This Row],[Perda Pçs]] -> 90 | N123: =IFERROR(Tabela3[[#This Row],[Perda Pçs]]/Tabela3[[#This Row],[Previsto]],0) -> 0 | O123: =IFERROR(IF(Tabela3[[#This Row],[Qtde Cx Produzida]] <> 0, Tabela3[[#This Row],[Tempo]] / Tabela3[[#This Row],[Qtde Cx Produzida]], 0),0) -> 0.0039660494 | P123: =IFERROR(Tabela3[[#This Row],[Perda Pçs]]/Tabela3[[#This Row],[Qdt Peça Placa]],0) -> 0 | Q123: =IFERROR(Tabela3[[#This Row],[Realizado]]*Tabela3[[#This Row],[Peso Util/Pç]],0) -> 152.1 | R123: =IFERROR(Tabela3[[#This Row],[Peso Total Galho]]*Tabela3[[#This Row],[Qtde Cx Produzida]]*1.055,0) -> 283.9005 | S123: =(Tabela3[[#This Row],[Aluminio Bruto]]-Tabela3[[#This Row],[Aluminio Util]])*0.9 -> 118.62045 | T123: =Tabela3[[#This Row],[Aluminio Bruto]]/OleoKGAluminio -> 119.43657 | U123: =IFERROR((VLOOKUP(Tabela3[[#This Row],[Moldador]],Tabela1[],5,)+(VLOOKUP(Tabela3[[#This Row],[Ajudante]],Tabela1[],5,))*3.5),0) -> 99.950346 | V123: =IFERROR(Tabela3[[#This Row],[Custo M.O. / H]]/((Tabela3[[#This Row],[Realizado]]/Tabela3[[#This Row],[Qdt Peça Placa]])/Tabela3[[#This Row],[Tempo]]/24),) -> 9.5137922 | W123: =Tabela3[[#This Row],[Custo / Cx Moldada]]*Tabela3[[#This Row],[Qtde Cx Produzida]] -> 856.2413 | X123: =Tabela3[[#This Row],[Aluminio Util]]*Tabela3[[#This Row],[Custo/Kg]] -> 2372.76 | Y123: =IFERROR(VLOOKUP(Tabela3[[#This Row],[Data]],Tabela461213[],2,1)*(Tabela3[[#This Row],[Qtde Cx Produzida]]*Tabela3[[#This Row],[Qde macho / CX]]*Tabela3[[#This Row],[Peso Macho]]),) -> 0 | Z123: =IFERROR(Tabela3[[#This Row],[Qtde Oleo]]*(VLOOKUP(Tabela3[[#This Row],[Data]],CompraOleo[],3,TRUE))*1.05,0) -> 313.521 | AA123: =(Tabela3[[#This Row],[Custo Oleo]]+Tabela3[[#This Row],[Custo Aluminio]]+Tabela3[[#This Row],[Custo M.O. Total]]+Tabela3[[#This Row],[Custo Machos]]) -> 3542.5223 | AB123: =Tabela3[[#This Row],[Custo Total]]*Tabela3[[#This Row],[% Perda]] -> 0 | AC123: =IFERROR(VLOOKUP(Tabela3[[#This Row],[Produto]],Tabela2[],2,0),0) -> 1 | AD123: =IFERROR(VLOOKUP(Tabela3[[#This Row],[Produto]],Tabela2[],3,0),0) -> 1.69 | AE123: =IFERROR(VLOOKUP(Tabela3[[#This Row],[Produto]],Tabela2[],4,0),0) -> 2.99 | AF123: =IFERROR(VLOOKUP(Tabela3[[#This Row],[Produto]],Tabela2[],5,0),0) -> 1.17 | AG123: =IFERROR(VLOOKUP(Tabela3[[#This Row],[Produto]],Tabela2[],6,0),0) -> 0 | AH123: =IFERROR(VLOOKUP(Tabela3[[#This Row],[Produto]],Tabela2[],7,0),0) -> 0 | AI123: =IFERROR(VLOOKUP(Tabela3[[#This Row],[Produto]],Tabela2[],8,0),0) -> 0 | AJ123: =IFERROR(VLOOKUP(Tabela3[[#This Row],[Produto]],Tabela2[],13,0),0) -> 15.6 | AK123: =IFERROR(VLOOKUP(Tabela3[[#This Row],[Produto]],Tabela2[],14,0),0) -> Jumil | AL123: =IFERROR(VLOOKUP(Tabela3[[#This Row],[Produto]],Tabela2[],15,0),0) -> 8 | AM123: =(Tabela3[[#This Row],[Custo Usinagem]]+Tabela3[[#This Row],[Custo / Pç]])*1.2 -> 56.833631 | AN123: =Tabela3[[#This Row],[Valor Mínimo Venda]]*1.15 -> 65.358675 | AO123: =Tabela3[[#This Row],[Tabela 1]]*1.08 -> 70.587369 | AP123: =Tabela3[[#This Row],[Tabela 2]]*1.15 -> 81.175475
A124: 45740 | B124: Prot Câm Dome C Acopl - SENUN METAL | C124: 6060 | D124: Marcelo Santos | E124: Claudio Henrique | F124: 61 | G124: 0.33819444 | H124: 0 | I124: =IFERROR(Tabela3[[#This Row],[Custo Total]]/Tabela3[[#This Row],[Aluminio Util]],0) -> 24.323311 | J124: =Tabela3[[#This Row],[Custo Total]]/Tabela3[[#This Row],[Realizado]] -> 7.34564 | K124: =IFERROR(Tabela3[[#This Row],[Qtde Cx Produzida]]/Tabela3[[#This Row],[Tempo]]/24,0) -> 7.5154004 | L124: =Tabela3[[#This Row],[Qtde Cx Produzida]]*Tabela3[[#This Row],[Qdt Peça Placa]] -> 366 | M124: =Tabela3[[#This Row],[Previsto]]-Tabela3[[#This Row],[Perda Pçs]] -> 366 | N124: =IFERROR(Tabela3[[#This Row],[Perda Pçs]]/Tabela3[[#This Row],[Previsto]],0) -> 0 | O124: =IFERROR(IF(Tabela3[[#This Row],[Qtde Cx Produzida]] <> 0, Tabela3[[#This Row],[Tempo]] / Tabela3[[#This Row],[Qtde Cx Produzida]], 0),0) -> 0.0055441712 | P124: =IFERROR(Tabela3[[#This Row],[Perda Pçs]]/Tabela3[[#This Row],[Qdt Peça Placa]],0) -> 0 | Q124: =IFERROR(Tabela3[[#This Row],[Realizado]]*Tabela3[[#This Row],[Peso Util/Pç]],0) -> 110.532 | R124: =IFERROR(Tabela3[[#This Row],[Peso Total Galho]]*Tabela3[[#This Row],[Qtde Cx Produzida]]*1.055,0) -> 138.49196 | S124: =(Tabela3[[#This Row],[Aluminio Bruto]]-Tabela3[[#This Row],[Aluminio Util]])*0.9 -> 25.163964 | T124: =Tabela3[[#This Row],[Aluminio Bruto]]/OleoKGAluminio -> 58.263389 | U124: =IFERROR((VLOOKUP(Tabela3[[#This Row],[Moldador]],Tabela1[],5,)+(VLOOKUP(Tabela3[[#This Row],[Ajudante]],Tabela1[],5,))*3.5),0) -> 99.950346 | V124: =IFERROR(Tabela3[[#This Row],[Custo M.O. / H]]/((Tabela3[[#This Row],[Realizado]]/Tabela3[[#This Row],[Qdt Peça Placa]])/Tabela3[[#This Row],[Tempo]]/24),) -> 13.299404 | W124: =Tabela3[[#This Row],[Custo / Cx Moldada]]*Tabela3[[#This Row],[Qtde Cx Produzida]] -> 811.26364 | X124: =Tabela3[[#This Row],[Aluminio Util]]*Tabela3[[#This Row],[Custo/Kg]] -> 1724.2992 | Y124: =IFERROR(VLOOKUP(Tabela3[[#This Row],[Data]],Tabela461213[],2,1)*(Tabela3[[#This Row],[Qtde Cx Produzida]]*Tabela3[[#This Row],[Qde macho / CX]]*Tabela3[[#This Row],[Peso Macho]]),) -> 0 | Z124: =IFERROR(Tabela3[[#This Row],[Qtde Oleo]]*(VLOOKUP(Tabela3[[#This Row],[Data]],CompraOleo[],3,TRUE))*1.05,0) -> 152.94139 | AA124: =(Tabela3[[#This Row],[Custo Oleo]]+Tabela3[[#This Row],[Custo Aluminio]]+Tabela3[[#This Row],[Custo M.O. Total]]+Tabela3[[#This Row],[Custo Machos]]) -> 2688.5042 | AB124: =Tabela3[[#This Row],[Custo Total]]*Tabela3[[#This Row],[% Perda]] -> 0 | AC124: =IFERROR(VLOOKUP(Tabela3[[#This Row],[Produto]],Tabela2[],2,0),0) -> 6 | AD124: =IFERROR(VLOOKUP(Tabela3[[#This Row],[Produto]],Tabela2[],3,0),0) -> 0.302 | AE124: =IFERROR(VLOOKUP(Tabela3[[#This Row],[Produto]],Tabela2[],4,0),0) -> 2.152 | AF124: =IFERROR(VLOOKUP(Tabela3[[#This Row],[Produto]],Tabela2[],5,0),0) -> 0.306 | AG124: =IFERROR(VLOOKUP(Tabela3[[#This Row],[Produto]],Tabela2[],6,0),0) -> 0 | AH124: =IFERROR(VLOOKUP(Tabela3[[#This Row],[Produto]],Tabela2[],7,0),0) -> 0 | AI124: =IFERROR(VLOOKUP(Tabela3[[#This Row],[Produto]],Tabela2[],8,0),0) -> 0 | AJ124: =IFERROR(VLOOKUP(Tabela3[[#This Row],[Produto]],Tabela2[],13,0),0) -> 15.6 | AK124: =IFERROR(VLOOKUP(Tabela3[[#This Row],[Produto]],Tabela2[],14,0),0) -> Senun | AL124: =IFERROR(VLOOKUP(Tabela3[[#This Row],[Produto]],Tabela2[],15,0),0) -> 4 | AM124: =(Tabela3[[#This Row],[Custo Usinagem]]+Tabela3[[#This Row],[Custo / Pç]])*1.2 -> 13.614768 | AN124: =Tabela3[[#This Row],[Valor Mínimo Venda]]*1.15 -> 15.656983 | AO124: =Tabela3[[#This Row],[Tabela 1]]*1.08 -> 16.909542 | AP124: =Tabela3[[#This Row],[Tabela 2]]*1.15 -> 19.445973
A125: 45741 | B125: Prot Câm Dome C Acopl - SENUN METAL | C125: 6060 | D125: Marcelo Santos | E125: Claudio Henrique | F125: 39 | G125: 0.24097222 | H125: 0 | I125: =IFERROR(Tabela3[[#This Row],[Custo Total]]/Tabela3[[#This Row],[Aluminio Util]],0) -> 25.163429 | J125: =Tabela3[[#This Row],[Custo Total]]/Tabela3[[#This Row],[Realizado]] -> 7.5993554 | K125: =IFERROR(Tabela3[[#This Row],[Qtde Cx Produzida]]/Tabela3[[#This Row],[Tempo]]/24,0) -> 6.7435159 | L125: =Tabela3[[#This Row],[Qtde Cx Produzida]]*Tabela3[[#This Row],[Qdt Peça Placa]] -> 234 | M125: =Tabela3[[#This Row],[Previsto]]-Tabela3[[#This Row],[Perda Pçs]] -> 234 | N125: =IFERROR(Tabela3[[#This Row],[Perda Pçs]]/Tabela3[[#This Row],[Previsto]],0) -> 0 | O125: =IFERROR(IF(Tabela3[[#This Row],[Qtde Cx Produzida]] <> 0, Tabela3[[#This Row],[Tempo]] / Tabela3[[#This Row],[Qtde Cx Produzida]], 0),0) -> 0.0061787749 | P125: =IFERROR(Tabela3[[#This Row],[Perda Pçs]]/Tabela3[[#This Row],[Qdt Peça Placa]],0) -> 0 | Q125: =IFERROR(Tabela3[[#This Row],[Realizado]]*Tabela3[[#This Row],[Peso Util/Pç]],0) -> 70.668 | R125: =IFERROR(Tabela3[[#This Row],[Peso Total Galho]]*Tabela3[[#This Row],[Qtde Cx Produzida]]*1.055,0) -> 88.54404 | S125: =(Tabela3[[#This Row],[Aluminio Bruto]]-Tabela3[[#This Row],[Aluminio Util]])*0.9 -> 16.088436 | T125: =Tabela3[[#This Row],[Aluminio Bruto]]/OleoKGAluminio -> 37.250363 | U125: =IFERROR((VLOOKUP(Tabela3[[#This Row],[Moldador]],Tabela1[],5,)+(VLOOKUP(Tabela3[[#This Row],[Ajudante]],Tabela1[],5,))*3.5),0) -> 99.950346 | V125: =IFERROR(Tabela3[[#This Row],[Custo M.O. / H]]/((Tabela3[[#This Row],[Realizado]]/Tabela3[[#This Row],[Qdt Peça Placa]])/Tabela3[[#This Row],[Tempo]]/24),) -> 14.821697 | W125: =Tabela3[[#This Row],[Custo / Cx Moldada]]*Tabela3[[#This Row],[Qtde Cx Produzida]] -> 578.04617 | X125: =Tabela3[[#This Row],[Aluminio Util]]*Tabela3[[#This Row],[Custo/Kg]] -> 1102.4208 | Y125: =IFERROR(VLOOKUP(Tabela3[[#This Row],[Data]],Tabela461213[],2,1)*(Tabela3[[#This Row],[Qtde Cx Produzida]]*Tabela3[[#This Row],[Qde macho / CX]]*Tabela3[[#This Row],[Peso Macho]]),) -> 0 | Z125: =IFERROR(Tabela3[[#This Row],[Qtde Oleo]]*(VLOOKUP(Tabela3[[#This Row],[Data]],CompraOleo[],3,TRUE))*1.05,0) -> 97.782203 | AA125: =(Tabela3[[#This Row],[Custo Oleo]]+Tabela3[[#This Row],[Custo Aluminio]]+Tabela3[[#This Row],[Custo M.O. Total]]+Tabela3[[#This Row],[Custo Machos]]) -> 1778.2492 | AB125: =Tabela3[[#This Row],[Custo Total]]*Tabela3[[#This Row],[% Perda]] -> 0 | AC125: =IFERROR(VLOOKUP(Tabela3[[#This Row],[Produto]],Tabela2[],2,0),0) -> 6 | AD125: =IFERROR(VLOOKUP(Tabela3[[#This Row],[Produto]],Tabela2[],3,0),0) -> 0.302 | AE125: =IFERROR(VLOOKUP(Tabela3[[#This Row],[Produto]],Tabela2[],4,0),0) -> 2.152 | AF125: =IFERROR(VLOOKUP(Tabela3[[#This Row],[Produto]],Tabela2[],5,0),0) -> 0.306 | AG125: =IFERROR(VLOOKUP(Tabela3[[#This Row],[Produto]],Tabela2[],6,0),0) -> 0 | AH125: =IFERROR(VLOOKUP(Tabela3[[#This Row],[Produto]],Tabela2[],7,0),0) -> 0 | AI125: =IFERROR(VLOOKUP(Tabela3[[#This Row],[Produto]],Tabela2[],8,0),0) -> 0 | AJ125: =IFERROR(VLOOKUP(Tabela3[[#This Row],[Produto]],Tabela2[],13,0),0) -> 15.6 | AK125: =IFERROR(VLOOKUP(Tabela3[[#This Row],[Produto]],Tabela2[],14,0),0) -> Senun | AL125: =IFERROR(VLOOKUP(Tabela3[[#This Row],[Produto]],Tabela2[],15,0),0) -> 4 | AM125: =(Tabela3[[#This Row],[Custo Usinagem]]+Tabela3[[#This Row],[Custo / Pç]])*1.2 -> 13.919227 | AN125: =Tabela3[[#This Row],[Valor Mínimo Venda]]*1.15 -> 16.00711 | AO125: =Tabela3[[#This Row],[Tabela 1]]*1.08 -> 17.287679 | AP125: =Tabela3[[#This Row],[Tabela 2]]*1.15 -> 19.880831
A126: 45741 | B126: BRACINHO ARTICULADOR | C126: 6064 | D126: Marcelo Santos | E126: Claudio Henrique | F126: 10 | G126: 0.052777778 | H126: 0 | I126: =IFERROR(Tabela3[[#This Row],[Custo Total]]/Tabela3[[#This Row],[Aluminio Util]],0) -> 25.794305 | J126: =Tabela3[[#This Row],[Custo Total]]/Tabela3[[#This Row],[Realizado]] -> 12.897152 | K126: =IFERROR(Tabela3[[#This Row],[Qtde Cx Produzida]]/Tabela3[[#This Row],[Tempo]]/24,0) -> 7.8947368 | L126: =Tabela3[[#This Row],[Qtde Cx Produzida]]*Tabela3[[#This Row],[Qdt Peça Placa]] -> 40 | M126: =Tabela3[[#This Row],[Previsto]]-Tabela3[[#This Row],[Perda Pçs]] -> 40 | N126: =IFERROR(Tabela3[[#This Row],[Perda Pçs]]/Tabela3[[#This Row],[Previsto]],0) -> 0 | O126: =IFERROR(IF(Tabela3[[#This Row],[Qtde Cx Produzida]] <> 0, Tabela3[[#This Row],[Tempo]] / Tabela3[[#This Row],[Qtde Cx Produzida]], 0),0) -> 0.0052777778 | P126: =IFERROR(Tabela3[[#This Row],[Perda Pçs]]/Tabela3[[#This Row],[Qdt Peça Placa]],0) -> 0 | Q126: =IFERROR(Tabela3[[#This Row],[Realizado]]*Tabela3[[#This Row],[Peso Util/Pç]],0) -> 20 | R126: =IFERROR(Tabela3[[#This Row],[Peso Total Galho]]*Tabela3[[#This Row],[Qtde Cx Produzida]]*1.055,0) -> 33.76 | S126: =(Tabela3[[#This Row],[Aluminio Bruto]]-Tabela3[[#This Row],[Aluminio Util]])*0.9 -> 12.384 | T126: =Tabela3[[#This Row],[Aluminio Bruto]]/OleoKGAluminio -> 14.202788 | U126: =IFERROR((VLOOKUP(Tabela3[[#This Row],[Moldador]],Tabela1[],5,)+(VLOOKUP(Tabela3[[#This Row],[Ajudante]],Tabela1[],5,))*3.5),0) -> 99.950346 | V126: =IFERROR(Tabela3[[#This Row],[Custo M.O. / H]]/((Tabela3[[#This Row],[Realizado]]/Tabela3[[#This Row],[Qdt Peça Placa]])/Tabela3[[#This Row],[Tempo]]/24),) -> 12.660377 | W126: =Tabela3[[#This Row],[Custo / Cx Moldada]]*Tabela3[[#This Row],[Qtde Cx Produzida]] -> 126.60377 | X126: =Tabela3[[#This Row],[Aluminio Util]]*Tabela3[[#This Row],[Custo/Kg]] -> 352 | Y126: =IFERROR(VLOOKUP(Tabela3[[#This Row],[Data]],Tabela461213[],2,1)*(Tabela3[[#This Row],[Qtde Cx Produzida]]*Tabela3[[#This Row],[Qde macho / CX]]*Tabela3[[#This Row],[Peso Macho]]),) -> 0 | Z126: =IFERROR(Tabela3[[#This Row],[Qtde Oleo]]*(VLOOKUP(Tabela3[[#This Row],[Data]],CompraOleo[],3,TRUE))*1.05,0) -> 37.282319 | AA126: =(Tabela3[[#This Row],[Custo Oleo]]+Tabela3[[#This Row],[Custo Aluminio]]+Tabela3[[#This Row],[Custo M.O. Total]]+Tabela3[[#This Row],[Custo Machos]]) -> 515.88609 | AB126: =Tabela3[[#This Row],[Custo Total]]*Tabela3[[#This Row],[% Perda]] -> 0 | AC126: =IFERROR(VLOOKUP(Tabela3[[#This Row],[Produto]],Tabela2[],2,0),0) -> 4 | AD126: =IFERROR(VLOOKUP(Tabela3[[#This Row],[Produto]],Tabela2[],3,0),0) -> 0.5 | AE126: =IFERROR(VLOOKUP(Tabela3[[#This Row],[Produto]],Tabela2[],4,0),0) -> 3.2 | AF126: =IFERROR(VLOOKUP(Tabela3[[#This Row],[Produto]],Tabela2[],5,0),0) -> 1.08 | AG126: =IFERROR(VLOOKUP(Tabela3[[#This Row],[Produto]],Tabela2[],6,0),0) -> 0 | AH126: =IFERROR(VLOOKUP(Tabela3[[#This Row],[Produto]],Tabela2[],7,0),0) -> 0 | AI126: =IFERROR(VLOOKUP(Tabela3[[#This Row],[Produto]],Tabela2[],8,0),0) -> 0 | AJ126: =IFERROR(VLOOKUP(Tabela3[[#This Row],[Produto]],Tabela2[],13,0),0) -> 17.6 | AK126: =IFERROR(VLOOKUP(Tabela3[[#This Row],[Produto]],Tabela2[],14,0),0) -> Marcelo | AL126: =IFERROR(VLOOKUP(Tabela3[[#This Row],[Produto]],Tabela2[],15,0),0) -> 0 | AM126: =(Tabela3[[#This Row],[Custo Usinagem]]+Tabela3[[#This Row],[Custo / Pç]])*1.2 -> 15.476583 | AN126: =Tabela3[[#This Row],[Valor Mínimo Venda]]*1.15 -> 17.79807 | AO126: =Tabela3[[#This Row],[Tabela 1]]*1.08 -> 19.221916 | AP126: =Tabela3[[#This Row],[Tabela 2]]*1.15 -> 22.105203
A127: 45741 | B127: Lateral Churrasqueira 1 Fogareiro - Fundido | C127: 6073 | D127: Marcelo Santos | E127: Claudio Henrique | F127: 2 | G127: 0.0055555556 | H127: 0 | I127: =IFERROR(Tabela3[[#This Row],[Custo Total]]/Tabela3[[#This Row],[Aluminio Util]],0) -> 24.068356 | J127: =Tabela3[[#This Row],[Custo Total]]/Tabela3[[#This Row],[Realizado]] -> 6.2577724 | K127: =IFERROR(Tabela3[[#This Row],[Qtde Cx Produzida]]/Tabela3[[#This Row],[Tempo]]/24,0) -> 15 | L127: =Tabela3[[#This Row],[Qtde Cx Produzida]]*Tabela3[[#This Row],[Qdt Peça Placa]] -> 8 | M127: =Tabela3[[#This Row],[Previsto]]-Tabela3[[#This Row],[Perda Pçs]] -> 8 | N127: =IFERROR(Tabela3[[#This Row],[Perda Pçs]]/Tabela3[[#This Row],[Previsto]],0) -> 0 | O127: =IFERROR(IF(Tabela3[[#This Row],[Qtde Cx Produzida]] <> 0, Tabela3[[#This Row],[Tempo]] / Tabela3[[#This Row],[Qtde Cx Produzida]], 0),0) -> 0.0027777778 | P127: =IFERROR(Tabela3[[#This Row],[Perda Pçs]]/Tabela3[[#This Row],[Qdt Peça Placa]],0) -> 0 | Q127: =IFERROR(Tabela3[[#This Row],[Realizado]]*Tabela3[[#This Row],[Peso Util/Pç]],0) -> 2.08 | R127: =IFERROR(Tabela3[[#This Row],[Peso Total Galho]]*Tabela3[[#This Row],[Qtde Cx Produzida]]*1.055,0) -> 3.8824 | S127: =(Tabela3[[#This Row],[Aluminio Bruto]]-Tabela3[[#This Row],[Aluminio Util]])*0.9 -> 1.62216 | T127: =Tabela3[[#This Row],[Aluminio Bruto]]/OleoKGAluminio -> 1.6333207 | U127: =IFERROR((VLOOKUP(Tabela3[[#This Row],[Moldador]],Tabela1[],5,)+(VLOOKUP(Tabela3[[#This Row],[Ajudante]],Tabela1[],5,))*3.5),0) -> 99.950346 | V127: =IFERROR(Tabela3[[#This Row],[Custo M.O. / H]]/((Tabela3[[#This Row],[Realizado]]/Tabela3[[#This Row],[Qdt Peça Placa]])/Tabela3[[#This Row],[Tempo]]/24),) -> 6.6633564 | W127: =Tabela3[[#This Row],[Custo / Cx Moldada]]*Tabela3[[#This Row],[Qtde Cx Produzida]] -> 13.326713 | X127: =Tabela3[[#This Row],[Aluminio Util]]*Tabela3[[#This Row],[Custo/Kg]] -> 32.448 | Y127: =IFERROR(VLOOKUP(Tabela3[[#This Row],[Data]],Tabela461213[],2,1)*(Tabela3[[#This Row],[Qtde Cx Produzida]]*Tabela3[[#This Row],[Qde macho / CX]]*Tabela3[[#This Row],[Peso Macho]]),) -> 0 | Z127: =IFERROR(Tabela3[[#This Row],[Qtde Oleo]]*(VLOOKUP(Tabela3[[#This Row],[Data]],CompraOleo[],3,TRUE))*1.05,0) -> 4.2874667 | AA127: =(Tabela3[[#This Row],[Custo Oleo]]+Tabela3[[#This Row],[Custo Aluminio]]+Tabela3[[#This Row],[Custo M.O. Total]]+Tabela3[[#This Row],[Custo Machos]]) -> 50.06218 | AB127: =Tabela3[[#This Row],[Custo Total]]*Tabela3[[#This Row],[% Perda]] -> 0 | AC127: =IFERROR(VLOOKUP(Tabela3[[#This Row],[Produto]],Tabela2[],2,0),0) -> 4 | AD127: =IFERROR(VLOOKUP(Tabela3[[#This Row],[Produto]],Tabela2[],3,0),0) -> 0.26 | AE127: =IFERROR(VLOOKUP(Tabela3[[#This Row],[Produto]],Tabela2[],4,0),0) -> 1.84 | AF127: =IFERROR(VLOOKUP(Tabela3[[#This Row],[Produto]],Tabela2[],5,0),0) -> 0.72 | AG127: =IFERROR(VLOOKUP(Tabela3[[#This Row],[Produto]],Tabela2[],6,0),0) -> 0 | AH127: =IFERROR(VLOOKUP(Tabela3[[#This Row],[Produto]],Tabela2[],7,0),0) -> 0 | AI127: =IFERROR(VLOOKUP(Tabela3[[#This Row],[Produto]],Tabela2[],8,0),0) -> 0 | AJ127: =IFERROR(VLOOKUP(Tabela3[[#This Row],[Produto]],Tabela2[],13,0),0) -> 15.6 | AK127: =IFERROR(VLOOKUP(Tabela3[[#This Row],[Produto]],Tabela2[],14,0),0) -> Senun | AL127: =IFERROR(VLOOKUP(Tabela3[[#This Row],[Produto]],Tabela2[],15,0),0) -> 0 | AM127: =(Tabela3[[#This Row],[Custo Usinagem]]+Tabela3[[#This Row],[Custo / Pç]])*1.2 -> 7.5093269 | AN127: =Tabela3[[#This Row],[Valor Mínimo Venda]]*1.15 -> 8.635726 | AO127: =Tabela3[[#This Row],[Tabela 1]]*1.08 -> 9.326584 | AP127: =Tabela3[[#This Row],[Tabela 2]]*1.15 -> 10.725572
A128: 45741 | B128: Pé Churrasqueira 1 Fogareiro - Fundido | C128: 6074 | D128: Marcelo Santos | E128: Claudio Henrique | F128: 2 | G128: 0.011111111 | H128: 0 | I128: =IFERROR(Tabela3[[#This Row],[Custo Total]]/Tabela3[[#This Row],[Aluminio Util]],0) -> 32.147229 | J128: =Tabela3[[#This Row],[Custo Total]]/Tabela3[[#This Row],[Realizado]] -> 7.3938627 | K128: =IFERROR(Tabela3[[#This Row],[Qtde Cx Produzida]]/Tabela3[[#This Row],[Tempo]]/24,0) -> 7.5 | L128: =Tabela3[[#This Row],[Qtde Cx Produzida]]*Tabela3[[#This Row],[Qdt Peça Placa]] -> 8 | M128: =Tabela3[[#This Row],[Previsto]]-Tabela3[[#This Row],[Perda Pçs]] -> 8 | N128: =IFERROR(Tabela3[[#This Row],[Perda Pçs]]/Tabela3[[#This Row],[Previsto]],0) -> 0 | O128: =IFERROR(IF(Tabela3[[#This Row],[Qtde Cx Produzida]] <> 0, Tabela3[[#This Row],[Tempo]] / Tabela3[[#This Row],[Qtde Cx Produzida]], 0),0) -> 0.0055555556 | P128: =IFERROR(Tabela3[[#This Row],[Perda Pçs]]/Tabela3[[#This Row],[Qdt Peça Placa]],0) -> 0 | Q128: =IFERROR(Tabela3[[#This Row],[Realizado]]*Tabela3[[#This Row],[Peso Util/Pç]],0) -> 1.84 | R128: =IFERROR(Tabela3[[#This Row],[Peso Total Galho]]*Tabela3[[#This Row],[Qtde Cx Produzida]]*1.055,0) -> 3.43508 | S128: =(Tabela3[[#This Row],[Aluminio Bruto]]-Tabela3[[#This Row],[Aluminio Util]])*0.9 -> 1.435572 | T128: =Tabela3[[#This Row],[Aluminio Bruto]]/OleoKGAluminio -> 1.4451337 | U128: =IFERROR((VLOOKUP(Tabela3[[#This Row],[Moldador]],Tabela1[],5,)+(VLOOKUP(Tabela3[[#This Row],[Ajudante]],Tabela1[],5,))*3.5),0) -> 99.950346 | V128: =IFERROR(Tabela3[[#This Row],[Custo M.O. / H]]/((Tabela3[[#This Row],[Realizado]]/Tabela3[[#This Row],[Qdt Peça Placa]])/Tabela3[[#This Row],[Tempo]]/24),) -> 13.326713 | W128: =Tabela3[[#This Row],[Custo / Cx Moldada]]*Tabela3[[#This Row],[Qtde Cx Produzida]] -> 26.653426 | X128: =Tabela3[[#This Row],[Aluminio Util]]*Tabela3[[#This Row],[Custo/Kg]] -> 28.704 | Y128: =IFERROR(VLOOKUP(Tabela3[[#This Row],[Data]],Tabela461213[],2,1)*(Tabela3[[#This Row],[Qtde Cx Produzida]]*Tabela3[[#This Row],[Qde macho / CX]]*Tabela3[[#This Row],[Peso Macho]]),) -> 0 | Z128: =IFERROR(Tabela3[[#This Row],[Qtde Oleo]]*(VLOOKUP(Tabela3[[#This Row],[Data]],CompraOleo[],3,TRUE))*1.05,0) -> 3.793476 | AA128: =(Tabela3[[#This Row],[Custo Oleo]]+Tabela3[[#This Row],[Custo Aluminio]]+Tabela3[[#This Row],[Custo M.O. Total]]+Tabela3[[#This Row],[Custo Machos]]) -> 59.150902 | AB128: =Tabela3[[#This Row],[Custo Total]]*Tabela3[[#This Row],[% Perda]] -> 0 | AC128: =IFERROR(VLOOKUP(Tabela3[[#This Row],[Produto]],Tabela2[],2,0),0) -> 4 | AD128: =IFERROR(VLOOKUP(Tabela3[[#This Row],[Produto]],Tabela2[],3,0),0) -> 0.23 | AE128: =IFERROR(VLOOKUP(Tabela3[[#This Row],[Produto]],Tabela2[],4,0),0) -> 1.628 | AF128: =IFERROR(VLOOKUP(Tabela3[[#This Row],[Produto]],Tabela2[],5,0),0) -> 0.6372 | AG128: =IFERROR(VLOOKUP(Tabela3[[#This Row],[Produto]],Tabela2[],6,0),0) -> 0 | AH128: =IFERROR(VLOOKUP(Tabela3[[#This Row],[Produto]],Tabela2[],7,0),0) -> 0 | AI128: =IFERROR(VLOOKUP(Tabela3[[#This Row],[Produto]],Tabela2[],8,0),0) -> 0 | AJ128: =IFERROR(VLOOKUP(Tabela3[[#This Row],[Produto]],Tabela2[],13,0),0) -> 15.6 | AK128: =IFERROR(VLOOKUP(Tabela3[[#This Row],[Produto]],Tabela2[],14,0),0) -> Senun | AL128: =IFERROR(VLOOKUP(Tabela3[[#This Row],[Produto]],Tabela2[],15,0),0) -> 4 | AM128: =(Tabela3[[#This Row],[Custo Usinagem]]+Tabela3[[#This Row],[Custo / Pç]])*1.2 -> 13.672635 | AN128: =Tabela3[[#This Row],[Valor Mínimo Venda]]*1.15 -> 15.723531 | AO128: =Tabela3[[#This Row],[Tabela 1]]*1.08 -> 16.981413 | AP128: =Tabela3[[#This Row],[Tabela 2]]*1.15 -> 19.528625
A129: 45741 | B129: Tampa Rechaud Churrasqueira 1 Fogareiro - Fundido | C129: 6075 | D129: Marcelo Santos | E129: Claudio Henrique | F129: 2 | G129: 0.0097222222 | H129: 0 | I129: =IFERROR(Tabela3[[#This Row],[Custo Total]]/Tabela3[[#This Row],[Aluminio Util]],0) -> 31.545835 | J129: =Tabela3[[#This Row],[Custo Total]]/Tabela3[[#This Row],[Realizado]] -> 4.4164169 | K129: =IFERROR(Tabela3[[#This Row],[Qtde Cx Produzida]]/Tabela3[[#This Row],[Tempo]]/24,0) -> 8.5714286 | L129: =Tabela3[[#This Row],[Qtde Cx Produzida]]*Tabela3[[#This Row],[Qdt Peça Placa]] -> 12 | M129: =Tabela3[[#This Row],[Previsto]]-Tabela3[[#This Row],[Perda Pçs]] -> 12 | N129: =IFERROR(Tabela3[[#This Row],[Perda Pçs]]/Tabela3[[#This Row],[Previsto]],0) -> 0 | O129: =IFERROR(IF(Tabela3[[#This Row],[Qtde Cx Produzida]] <> 0, Tabela3[[#This Row],[Tempo]] / Tabela3[[#This Row],[Qtde Cx Produzida]], 0),0) -> 0.0048611111 | P129: =IFERROR(Tabela3[[#This Row],[Perda Pçs]]/Tabela3[[#This Row],[Qdt Peça Placa]],0) -> 0 | Q129: =IFERROR(Tabela3[[#This Row],[Realizado]]*Tabela3[[#This Row],[Peso Util/Pç]],0) -> 1.68 | R129: =IFERROR(Tabela3[[#This Row],[Peso Total Galho]]*Tabela3[[#This Row],[Qtde Cx Produzida]]*1.055,0) -> 3.13968 | S129: =(Tabela3[[#This Row],[Aluminio Bruto]]-Tabela3[[#This Row],[Aluminio Util]])*0.9 -> 1.313712 | T129: =Tabela3[[#This Row],[Aluminio Bruto]]/OleoKGAluminio -> 1.3208593 | U129: =IFERROR((VLOOKUP(Tabela3[[#This Row],[Moldador]],Tabela1[],5,)+(VLOOKUP(Tabela3[[#This Row],[Ajudante]],Tabela1[],5,))*3.5),0) -> 99.950346 | V129: =IFERROR(Tabela3[[#This Row],[Custo M.O. / H]]/((Tabela3[[#This Row],[Realizado]]/Tabela3[[#This Row],[Qdt Peça Placa]])/Tabela3[[#This Row],[Tempo]]/24),) -> 11.660874 | W129: =Tabela3[[#This Row],[Custo / Cx Moldada]]*Tabela3[[#This Row],[Qtde Cx Produzida]] -> 23.321747 | X129: =Tabela3[[#This Row],[Aluminio Util]]*Tabela3[[#This Row],[Custo/Kg]] -> 26.208 | Y129: =IFERROR(VLOOKUP(Tabela3[[#This Row],[Data]],Tabela461213[],2,1)*(Tabela3[[#This Row],[Qtde Cx Produzida]]*Tabela3[[#This Row],[Qde macho / CX]]*Tabela3[[#This Row],[Peso Macho]]),) -> 0 | Z129: =IFERROR(Tabela3[[#This Row],[Qtde Oleo]]*(VLOOKUP(Tabela3[[#This Row],[Data]],CompraOleo[],3,TRUE))*1.05,0) -> 3.4672557 | AA129: =(Tabela3[[#This Row],[Custo Oleo]]+Tabela3[[#This Row],[Custo Aluminio]]+Tabela3[[#This Row],[Custo M.O. Total]]+Tabela3[[#This Row],[Custo Machos]]) -> 52.997003 | AB129: =Tabela3[[#This Row],[Custo Total]]*Tabela3[[#This Row],[% Perda]] -> 0 | AC129: =IFERROR(VLOOKUP(Tabela3[[#This Row],[Produto]],Tabela2[],2,0),0) -> 6 | AD129: =IFERROR(VLOOKUP(Tabela3[[#This Row],[Produto]],Tabela2[],3,0),0) -> 0.14 | AE129: =IFERROR(VLOOKUP(Tabela3[[#This Row],[Produto]],Tabela2[],4,0),0) -> 1.488 | AF129: =IFERROR(VLOOKUP(Tabela3[[#This Row],[Produto]],Tabela2[],5,0),0) -> 0.5832 | AG129: =IFERROR(VLOOKUP(Tabela3[[#This Row],[Produto]],Tabela2[],6,0),0) -> 0 | AH129: =IFERROR(VLOOKUP(Tabela3[[#This Row],[Produto]],Tabela2[],7,0),0) -> 0 | AI129: =IFERROR(VLOOKUP(Tabela3[[#This Row],[Produto]],Tabela2[],8,0),0) -> 0 | AJ129: =IFERROR(VLOOKUP(Tabela3[[#This Row],[Produto]],Tabela2[],13,0),0) -> 15.6 | AK129: =IFERROR(VLOOKUP(Tabela3[[#This Row],[Produto]],Tabela2[],14,0),0) -> Senun | AL129: =IFERROR(VLOOKUP(Tabela3[[#This Row],[Produto]],Tabela2[],15,0),0) -> 0 | AM129: =(Tabela3[[#This Row],[Custo Usinagem]]+Tabela3[[#This Row],[Custo / Pç]])*1.2 -> 5.2997003 | AN129: =Tabela3[[#This Row],[Valor Mínimo Venda]]*1.15 -> 6.0946554 | AO129: =Tabela3[[#This Row],[Tabela 1]]*1.08 -> 6.5822278 | AP129: =Tabela3[[#This Row],[Tabela 2]]*1.15 -> 7.5695619
A130: 45741 | B130: Reservatório Churrasqueira 1 Fogareiro - Fundido | C130: 6094 | D130: Marcelo Santos | E130: Claudio Henrique | F130: 2 | G130: 0.0083333333 | H130: 0 | I130: =IFERROR(Tabela3[[#This Row],[Custo Total]]/Tabela3[[#This Row],[Aluminio Util]],0) -> 24.725907 | J130: =Tabela3[[#This Row],[Custo Total]]/Tabela3[[#This Row],[Realizado]] -> 11.744806 | K130: =IFERROR(Tabela3[[#This Row],[Qtde Cx Produzida]]/Tabela3[[#This Row],[Tempo]]/24,0) -> 10 | L130: =Tabela3[[#This Row],[Qtde Cx Produzida]]*Tabela3[[#This Row],[Qdt Peça Placa]] -> 6 | M130: =Tabela3[[#This Row],[Previsto]]-Tabela3[[#This Row],[Perda Pçs]] -> 6 | N130: =IFERROR(Tabela3[[#This Row],[Perda Pçs]]/Tabela3[[#This Row],[Previsto]],0) -> 0 | O130: =IFERROR(IF(Tabela3[[#This Row],[Qtde Cx Produzida]] <> 0, Tabela3[[#This Row],[Tempo]] / Tabela3[[#This Row],[Qtde Cx Produzida]], 0),0) -> 0.0041666667 | P130: =IFERROR(Tabela3[[#This Row],[Perda Pçs]]/Tabela3[[#This Row],[Qdt Peça Placa]],0) -> 0 | Q130: =IFERROR(Tabela3[[#This Row],[Realizado]]*Tabela3[[#This Row],[Peso Util/Pç]],0) -> 2.85 | R130: =IFERROR(Tabela3[[#This Row],[Peso Total Galho]]*Tabela3[[#This Row],[Qtde Cx Produzida]]*1.055,0) -> 5.45013 | S130: =(Tabela3[[#This Row],[Aluminio Bruto]]-Tabela3[[#This Row],[Aluminio Util]])*0.9 -> 2.340117 | T130: =Tabela3[[#This Row],[Aluminio Bruto]]/OleoKGAluminio -> 2.2928626 | U130: =IFERROR((VLOOKUP(Tabela3[[#This Row],[Moldador]],Tabela1[],5,)+(VLOOKUP(Tabela3[[#This Row],[Ajudante]],Tabela1[],5,))*3.5),0) -> 99.950346 | V130: =IFERROR(Tabela3[[#This Row],[Custo M.O. / H]]/((Tabela3[[#This Row],[Realizado]]/Tabela3[[#This Row],[Qdt Peça Placa]])/Tabela3[[#This Row],[Tempo]]/24),) -> 9.9950346 | W130: =Tabela3[[#This Row],[Custo / Cx Moldada]]*Tabela3[[#This Row],[Qtde Cx Produzida]] -> 19.990069 | X130: =Tabela3[[#This Row],[Aluminio Util]]*Tabela3[[#This Row],[Custo/Kg]] -> 44.46 | Y130: =IFERROR(VLOOKUP(Tabela3[[#This Row],[Data]],Tabela461213[],2,1)*(Tabela3[[#This Row],[Qtde Cx Produzida]]*Tabela3[[#This Row],[Qde macho / CX]]*Tabela3[[#This Row],[Peso Macho]]),) -> 0 | Z130: =IFERROR(Tabela3[[#This Row],[Qtde Oleo]]*(VLOOKUP(Tabela3[[#This Row],[Data]],CompraOleo[],3,TRUE))*1.05,0) -> 6.0187644 | AA130: =(Tabela3[[#This Row],[Custo Oleo]]+Tabela3[[#This Row],[Custo Aluminio]]+Tabela3[[#This Row],[Custo M.O. Total]]+Tabela3[[#This Row],[Custo Machos]]) -> 70.468834 | AB130: =Tabela3[[#This Row],[Custo Total]]*Tabela3[[#This Row],[% Perda]] -> 0 | AC130: =IFERROR(VLOOKUP(Tabela3[[#This Row],[Produto]],Tabela2[],2,0),0) -> 3 | AD130: =IFERROR(VLOOKUP(Tabela3[[#This Row],[Produto]],Tabela2[],3,0),0) -> 0.475 | AE130: =IFERROR(VLOOKUP(Tabela3[[#This Row],[Produto]],Tabela2[],4,0),0) -> 2.583 | AF130: =IFERROR(VLOOKUP(Tabela3[[#This Row],[Produto]],Tabela2[],5,0),0) -> 1.0422 | AG130: =IFERROR(VLOOKUP(Tabela3[[#This Row],[Produto]],Tabela2[],6,0),0) -> 0 | AH130: =IFERROR(VLOOKUP(Tabela3[[#This Row],[Produto]],Tabela2[],7,0),0) -> 0 | AI130: =IFERROR(VLOOKUP(Tabela3[[#This Row],[Produto]],Tabela2[],8,0),0) -> 0 | AJ130: =IFERROR(VLOOKUP(Tabela3[[#This Row],[Produto]],Tabela2[],13,0),0) -> 15.6 | AK130: =IFERROR(VLOOKUP(Tabela3[[#This Row],[Produto]],Tabela2[],14,0),0) -> Senun | AL130: =IFERROR(VLOOKUP(Tabela3[[#This Row],[Produto]],Tabela2[],15,0),0) -> 6 | AM130: =(Tabela3[[#This Row],[Custo Usinagem]]+Tabela3[[#This Row],[Custo / Pç]])*1.2 -> 21.293767 | AN130: =Tabela3[[#This Row],[Valor Mínimo Venda]]*1.15 -> 24.487832 | AO130: =Tabela3[[#This Row],[Tabela 1]]*1.08 -> 26.446858 | AP130: =Tabela3[[#This Row],[Tabela 2]]*1.15 -> 30.413887
A131: 45741 | B131: Centro da Banda (3224429P) - Fundido | C131: 6013 | D131: Daniel Garcia | E131: Victor Hugo | F131: 5 | G131: 0.016666667 | I131: =IFERROR(Tabela3[[#This Row],[Custo Total]]/Tabela3[[#This Row],[Aluminio Util]],0) -> 22.392659 | J131: =Tabela3[[#This Row],[Custo Total]]/Tabela3[[#This Row],[Realizado]] -> 37.843594 | K131: =IFERROR(Tabela3[[#This Row],[Qtde Cx Produzida]]/Tabela3[[#This Row],[Tempo]]/24,0) -> 12.5 | L131: =Tabela3[[#This Row],[Qtde Cx Produzida]]*Tabela3[[#This Row],[Qdt Peça Placa]] -> 5 | M131: =Tabela3[[#This Row],[Previsto]]-Tabela3[[#This Row],[Perda Pçs]] -> 5 | N131: =IFERROR(Tabela3[[#This Row],[Perda Pçs]]/Tabela3[[#This Row],[Previsto]],0) -> 0 | O131: =IFERROR(IF(Tabela3[[#This Row],[Qtde Cx Produzida]] <> 0, Tabela3[[#This Row],[Tempo]] / Tabela3[[#This Row],[Qtde Cx Produzida]], 0),0) -> 0.0033333333 | P131: =IFERROR(Tabela3[[#This Row],[Perda Pçs]]/Tabela3[[#This Row],[Qdt Peça Placa]],0) -> 0 | Q131: =IFERROR(Tabela3[[#This Row],[Realizado]]*Tabela3[[#This Row],[Peso Util/Pç]],0) -> 8.45 | R131: =IFERROR(Tabela3[[#This Row],[Peso Total Galho]]*Tabela3[[#This Row],[Qtde Cx Produzida]]*1.055,0) -> 15.77225 | S131: =(Tabela3[[#This Row],[Aluminio Bruto]]-Tabela3[[#This Row],[Aluminio Util]])*0.9 -> 6.590025 | T131: =Tabela3[[#This Row],[Aluminio Bruto]]/OleoKGAluminio -> 6.6353652 | U131: =IFERROR((VLOOKUP(Tabela3[[#This Row],[Moldador]],Tabela1[],5,)+(VLOOKUP(Tabela3[[#This Row],[Ajudante]],Tabela1[],5,))*3.5),0) -> 99.950346 | V131: =IFERROR(Tabela3[[#This Row],[Custo M.O. / H]]/((Tabela3[[#This Row],[Realizado]]/Tabela3[[#This Row],[Qdt Peça Placa]])/Tabela3[[#This Row],[Tempo]]/24),) -> 7.9960277 | W131: =Tabela3[[#This Row],[Custo / Cx Moldada]]*Tabela3[[#This Row],[Qtde Cx Produzida]] -> 39.980138 | X131: =Tabela3[[#This Row],[Aluminio Util]]*Tabela3[[#This Row],[Custo/Kg]] -> 131.82 | Y131: =IFERROR(VLOOKUP(Tabela3[[#This Row],[Data]],Tabela461213[],2,1)*(Tabela3[[#This Row],[Qtde Cx Produzida]]*Tabela3[[#This Row],[Qde macho / CX]]*Tabela3[[#This Row],[Peso Macho]]),) -> 0 | Z131: =IFERROR(Tabela3[[#This Row],[Qtde Oleo]]*(VLOOKUP(Tabela3[[#This Row],[Data]],CompraOleo[],3,TRUE))*1.05,0) -> 17.417834 | AA131: =(Tabela3[[#This Row],[Custo Oleo]]+Tabela3[[#This Row],[Custo Aluminio]]+Tabela3[[#This Row],[Custo M.O. Total]]+Tabela3[[#This Row],[Custo Machos]]) -> 189.21797 | AB131: =Tabela3[[#This Row],[Custo Total]]*Tabela3[[#This Row],[% Perda]] -> 0 | AC131: =IFERROR(VLOOKUP(Tabela3[[#This Row],[Produto]],Tabela2[],2,0),0) -> 1 | AD131: =IFERROR(VLOOKUP(Tabela3[[#This Row],[Produto]],Tabela2[],3,0),0) -> 1.69 | AE131: =IFERROR(VLOOKUP(Tabela3[[#This Row],[Produto]],Tabela2[],4,0),0) -> 2.99 | AF131: =IFERROR(VLOOKUP(Tabela3[[#This Row],[Produto]],Tabela2[],5,0),0) -> 1.17 | AG131: =IFERROR(VLOOKUP(Tabela3[[#This Row],[Produto]],Tabela2[],6,0),0) -> 0 | AH131: =IFERROR(VLOOKUP(Tabela3[[#This Row],[Produto]],Tabela2[],7,0),0) -> 0 | AI131: =IFERROR(VLOOKUP(Tabela3[[#This Row],[Produto]],Tabela2[],8,0),0) -> 0 | AJ131: =IFERROR(VLOOKUP(Tabela3[[#This Row],[Produto]],Tabela2[],13,0),0) -> 15.6 | AK131: =IFERROR(VLOOKUP(Tabela3[[#This Row],[Produto]],Tabela2[],14,0),0) -> Jumil | AL131: =IFERROR(VLOOKUP(Tabela3[[#This Row],[Produto]],Tabela2[],15,0),0) -> 8 | AM131: =(Tabela3[[#This Row],[Custo Usinagem]]+Tabela3[[#This Row],[Custo / Pç]])*1.2 -> 55.012313 | AN131: =Tabela3[[#This Row],[Valor Mínimo Venda]]*1.15 -> 63.26416 | AO131: =Tabela3[[#This Row],[Tabela 1]]*1.08 -> 68.325293 | AP131: =Tabela3[[#This Row],[Tabela 2]]*1.15 -> 78.574087
A132: 45741 | B132: Prot. Interfone Intelbras 7010 Fundido | C132: 6061 | D132: Daniel Garcia | E132: Victor Hugo | F132: 76 | G132: 0.34097222 | H132: 23 | I132: =IFERROR(Tabela3[[#This Row],[Custo Total]]/Tabela3[[#This Row],[Aluminio Util]],0) -> 27.267983 | J132: =Tabela3[[#This Row],[Custo Total]]/Tabela3[[#This Row],[Realizado]] -> 9.0529702 | K132: =IFERROR(Tabela3[[#This Row],[Qtde Cx Produzida]]/Tabela3[[#This Row],[Tempo]]/24,0) -> 9.287169 | L132: =Tabela3[[#This Row],[Qtde Cx Produzida]]*Tabela3[[#This Row],[Qdt Peça Placa]] -> 304 | M132: =Tabela3[[#This Row],[Previsto]]-Tabela3[[#This Row],[Perda Pçs]] -> 281 | N132: =IFERROR(Tabela3[[#This Row],[Perda Pçs]]/Tabela3[[#This Row],[Previsto]],0) -> 0.075657895 | O132: =IFERROR(IF(Tabela3[[#This Row],[Qtde Cx Produzida]] <> 0, Tabela3[[#This Row],[Tempo]] / Tabela3[[#This Row],[Qtde Cx Produzida]], 0),0) -> 0.0044864766 | P132: =IFERROR(Tabela3[[#This Row],[Perda Pçs]]/Tabela3[[#This Row],[Qdt Peça Placa]],0) -> 5.75 | Q132: =IFERROR(Tabela3[[#This Row],[Realizado]]*Tabela3[[#This Row],[Peso Util/Pç]],0) -> 93.292 | R132: =IFERROR(Tabela3[[#This Row],[Peso Total Galho]]*Tabela3[[#This Row],[Qtde Cx Produzida]]*1.055,0) -> 184.414 | S132: =(Tabela3[[#This Row],[Aluminio Bruto]]-Tabela3[[#This Row],[Aluminio Util]])*0.9 -> 82.0098 | T132: =Tabela3[[#This Row],[Aluminio Bruto]]/OleoKGAluminio -> 77.582731 | U132: =IFERROR((VLOOKUP(Tabela3[[#This Row],[Moldador]],Tabela1[],5,)+(VLOOKUP(Tabela3[[#This Row],[Ajudante]],Tabela1[],5,))*3.5),0) -> 99.950346 | V132: =IFERROR(Tabela3[[#This Row],[Custo M.O. / H]]/((Tabela3[[#This Row],[Realizado]]/Tabela3[[#This Row],[Qdt Peça Placa]])/Tabela3[[#This Row],[Tempo]]/24),) -> 11.643089 | W132: =Tabela3[[#This Row],[Custo / Cx Moldada]]*Tabela3[[#This Row],[Qtde Cx Produzida]] -> 884.87476 | X132: =Tabela3[[#This Row],[Aluminio Util]]*Tabela3[[#This Row],[Custo/Kg]] -> 1455.3552 | Y132: =IFERROR(VLOOKUP(Tabela3[[#This Row],[Data]],Tabela461213[],2,1)*(Tabela3[[#This Row],[Qtde Cx Produzida]]*Tabela3[[#This Row],[Qde macho / CX]]*Tabela3[[#This Row],[Peso Macho]]),) -> 0 | Z132: =IFERROR(Tabela3[[#This Row],[Qtde Oleo]]*(VLOOKUP(Tabela3[[#This Row],[Data]],CompraOleo[],3,TRUE))*1.05,0) -> 203.65467 | AA132: =(Tabela3[[#This Row],[Custo Oleo]]+Tabela3[[#This Row],[Custo Aluminio]]+Tabela3[[#This Row],[Custo M.O. Total]]+Tabela3[[#This Row],[Custo Machos]]) -> 2543.8846 | AB132: =Tabela3[[#This Row],[Custo Total]]*Tabela3[[#This Row],[% Perda]] -> 192.46496 | AC132: =IFERROR(VLOOKUP(Tabela3[[#This Row],[Produto]],Tabela2[],2,0),0) -> 4 | AD132: =IFERROR(VLOOKUP(Tabela3[[#This Row],[Produto]],Tabela2[],3,0),0) -> 0.332 | AE132: =IFERROR(VLOOKUP(Tabela3[[#This Row],[Produto]],Tabela2[],4,0),0) -> 2.3 | AF132: =IFERROR(VLOOKUP(Tabela3[[#This Row],[Produto]],Tabela2[],5,0),0) -> 0.8748 | AG132: =IFERROR(VLOOKUP(Tabela3[[#This Row],[Produto]],Tabela2[],6,0),0) -> 0 | AH132: =IFERROR(VLOOKUP(Tabela3[[#This Row],[Produto]],Tabela2[],7,0),0) -> 0 | AI132: =IFERROR(VLOOKUP(Tabela3[[#This Row],[Produto]],Tabela2[],8,0),0) -> 0 | AJ132: =IFERROR(VLOOKUP(Tabela3[[#This Row],[Produto]],Tabela2[],13,0),0) -> 15.6 | AK132: =IFERROR(VLOOKUP(Tabela3[[#This Row],[Produto]],Tabela2[],14,0),0) -> Senun | AL132: =IFERROR(VLOOKUP(Tabela3[[#This Row],[Produto]],Tabela2[],15,0),0) -> 3.5 | AM132: =(Tabela3[[#This Row],[Custo Usinagem]]+Tabela3[[#This Row],[Custo / Pç]])*1.2 -> 15.063564 | AN132: =Tabela3[[#This Row],[Valor Mínimo Venda]]*1.15 -> 17.323099 | AO132: =Tabela3[[#This Row],[Tabela 1]]*1.08 -> 18.708947 | AP132: =Tabela3[[#This Row],[Tabela 2]]*1.15 -> 21.515289
A133: 45742 | B133: Lateral Churrasqueira 2 Fogareiro Fundido | C133: 6059 | D133: Daniel Garcia | E133: Victor Hugo | F133: 7 | G133: 0.035416667 | H133: 0 | I133: =IFERROR(Tabela3[[#This Row],[Custo Total]]/Tabela3[[#This Row],[Aluminio Util]],0) -> 29.199042 | J133: =Tabela3[[#This Row],[Custo Total]]/Tabela3[[#This Row],[Realizado]] -> 15.358696 | K133: =IFERROR(Tabela3[[#This Row],[Qtde Cx Produzida]]/Tabela3[[#This Row],[Tempo]]/24,0) -> 8.2352941 | L133: =Tabela3[[#This Row],[Qtde Cx Produzida]]*Tabela3[[#This Row],[Qdt Peça Placa]] -> 14 | M133: =Tabela3[[#This Row],[Previsto]]-Tabela3[[#This Row],[Perda Pçs]] -> 14 | N133: =IFERROR(Tabela3[[#This Row],[Perda Pçs]]/Tabela3[[#This Row],[Previsto]],0) -> 0 | O133: =IFERROR(IF(Tabela3[[#This Row],[Qtde Cx Produzida]] <> 0, Tabela3[[#This Row],[Tempo]] / Tabela3[[#This Row],[Qtde Cx Produzida]], 0),0) -> 0.0050595238 | P133: =IFERROR(Tabela3[[#This Row],[Perda Pçs]]/Tabela3[[#This Row],[Qdt Peça Placa]],0) -> 0 | Q133: =IFERROR(Tabela3[[#This Row],[Realizado]]*Tabela3[[#This Row],[Peso Util/Pç]],0) -> 7.364 | R133: =IFERROR(Tabela3[[#This Row],[Peso Total Galho]]*Tabela3[[#This Row],[Qtde Cx Produzida]]*1.055,0) -> 13.75087 | S133: =(Tabela3[[#This Row],[Aluminio Bruto]]-Tabela3[[#This Row],[Aluminio Util]])*0.9 -> 5.748183 | T133: =Tabela3[[#This Row],[Aluminio Bruto]]/OleoKGAluminio -> 5.7849732 | U133: =IFERROR((VLOOKUP(Tabela3[[#This Row],[Moldador]],Tabela1[],5,)+(VLOOKUP(Tabela3[[#This Row],[Ajudante]],Tabela1[],5,))*3.5),0) -> 99.950346 | V133: =IFERROR(Tabela3[[#This Row],[Custo M.O. / H]]/((Tabela3[[#This Row],[Realizado]]/Tabela3[[#This Row],[Qdt Peça Placa]])/Tabela3[[#This Row],[Tempo]]/24),) -> 12.136828 | W133: =Tabela3[[#This Row],[Custo / Cx Moldada]]*Tabela3[[#This Row],[Qtde Cx Produzida]] -> 84.957794 | X133: =Tabela3[[#This Row],[Aluminio Util]]*Tabela3[[#This Row],[Custo/Kg]] -> 114.8784 | Y133: =IFERROR(VLOOKUP(Tabela3[[#This Row],[Data]],Tabela461213[],2,1)*(Tabela3[[#This Row],[Qtde Cx Produzida]]*Tabela3[[#This Row],[Qde macho / CX]]*Tabela3[[#This Row],[Peso Macho]]),) -> 0 | Z133: =IFERROR(Tabela3[[#This Row],[Qtde Oleo]]*(VLOOKUP(Tabela3[[#This Row],[Data]],CompraOleo[],3,TRUE))*1.05,0) -> 15.185555 | AA133: =(Tabela3[[#This Row],[Custo Oleo]]+Tabela3[[#This Row],[Custo Aluminio]]+Tabela3[[#This Row],[Custo M.O. Total]]+Tabela3[[#This Row],[Custo Machos]]) -> 215.02175 | AB133: =Tabela3[[#This Row],[Custo Total]]*Tabela3[[#This Row],[% Perda]] -> 0 | AC133: =IFERROR(VLOOKUP(Tabela3[[#This Row],[Produto]],Tabela2[],2,0),0) -> 2 | AD133: =IFERROR(VLOOKUP(Tabela3[[#This Row],[Produto]],Tabela2[],3,0),0) -> 0.526 | AE133: =IFERROR(VLOOKUP(Tabela3[[#This Row],[Produto]],Tabela2[],4,0),0) -> 1.862 | AF133: =IFERROR(VLOOKUP(Tabela3[[#This Row],[Produto]],Tabela2[],5,0),0) -> 0.729 | AG133: =IFERROR(VLOOKUP(Tabela3[[#This Row],[Produto]],Tabela2[],6,0),0) -> 0 | AH133: =IFERROR(VLOOKUP(Tabela3[[#This Row],[Produto]],Tabela2[],7,0),0) -> 0 | AI133: =IFERROR(VLOOKUP(Tabela3[[#This Row],[Produto]],Tabela2[],8,0),0) -> 0 | AJ133: =IFERROR(VLOOKUP(Tabela3[[#This Row],[Produto]],Tabela2[],13,0),0) -> 15.6 | AK133: =IFERROR(VLOOKUP(Tabela3[[#This Row],[Produto]],Tabela2[],14,0),0) -> Senun | AL133: =IFERROR(VLOOKUP(Tabela3[[#This Row],[Produto]],Tabela2[],15,0),0) -> 0 | AM133: =(Tabela3[[#This Row],[Custo Usinagem]]+Tabela3[[#This Row],[Custo / Pç]])*1.2 -> 18.430436 | AN133: =Tabela3[[#This Row],[Valor Mínimo Venda]]*1.15 -> 21.195001 | AO133: =Tabela3[[#This Row],[Tabela 1]]*1.08 -> 22.890601 | AP133: =Tabela3[[#This Row],[Tabela 2]]*1.15 -> 26.324191
A134: 45742 | B134: Chapa Churrasqueira 2 Fogareiros Fundido | C134: 6058 | D134: Daniel Garcia | E134: Victor Hugo | F134: 60 | G134: 0.3125 | H134: 3 | I134: =IFERROR(Tabela3[[#This Row],[Custo Total]]/Tabela3[[#This Row],[Aluminio Util]],0) -> 22.175764 | J134: =Tabela3[[#This Row],[Custo Total]]/Tabela3[[#This Row],[Realizado]] -> 69.676252 | K134: =IFERROR(Tabela3[[#This Row],[Qtde Cx Produzida]]/Tabela3[[#This Row],[Tempo]]/24,0) -> 8 | L134: =Tabela3[[#This Row],[Qtde Cx Produzida]]*Tabela3[[#This Row],[Qdt Peça Placa]] -> 60 | M134: =Tabela3[[#This Row],[Previsto]]-Tabela3[[#This Row],[Perda Pçs]] -> 57 | N134: =IFERROR(Tabela3[[#This Row],[Perda Pçs]]/Tabela3[[#This Row],[Previsto]],0) -> 0.05 | O134: =IFERROR(IF(Tabela3[[#This Row],[Qtde Cx Produzida]] <> 0, Tabela3[[#This Row],[Tempo]] / Tabela3[[#This Row],[Qtde Cx Produzida]], 0),0) -> 0.0052083333 | P134: =IFERROR(Tabela3[[#This Row],[Perda Pçs]]/Tabela3[[#This Row],[Qdt Peça Placa]],0) -> 3 | Q134: =IFERROR(Tabela3[[#This Row],[Realizado]]*Tabela3[[#This Row],[Peso Util/Pç]],0) -> 179.094 | R134: =IFERROR(Tabela3[[#This Row],[Peso Total Galho]]*Tabela3[[#This Row],[Qtde Cx Produzida]]*1.055,0) -> 351.8847 | S134: =(Tabela3[[#This Row],[Aluminio Bruto]]-Tabela3[[#This Row],[Aluminio Util]])*0.9 -> 155.51163 | T134: =Tabela3[[#This Row],[Aluminio Bruto]]/OleoKGAluminio -> 148.03744 | U134: =IFERROR((VLOOKUP(Tabela3[[#This Row],[Moldador]],Tabela1[],5,)+(VLOOKUP(Tabela3[[#This Row],[Ajudante]],Tabela1[],5,))*3.5),0) -> 99.950346 | V134: =IFERROR(Tabela3[[#This Row],[Custo M.O. / H]]/((Tabela3[[#This Row],[Realizado]]/Tabela3[[#This Row],[Qdt Peça Placa]])/Tabela3[[#This Row],[Tempo]]/24),) -> 13.151361 | W134: =Tabela3[[#This Row],[Custo / Cx Moldada]]*Tabela3[[#This Row],[Qtde Cx Produzida]] -> 789.08168 | X134: =Tabela3[[#This Row],[Aluminio Util]]*Tabela3[[#This Row],[Custo/Kg]] -> 2793.8664 | Y134: =IFERROR(VLOOKUP(Tabela3[[#This Row],[Data]],Tabela461213[],2,1)*(Tabela3[[#This Row],[Qtde Cx Produzida]]*Tabela3[[#This Row],[Qde macho / CX]]*Tabela3[[#This Row],[Peso Macho]]),) -> 0 | Z134: =IFERROR(Tabela3[[#This Row],[Qtde Oleo]]*(VLOOKUP(Tabela3[[#This Row],[Data]],CompraOleo[],3,TRUE))*1.05,0) -> 388.59828 | AA134: =(Tabela3[[#This Row],[Custo Oleo]]+Tabela3[[#This Row],[Custo Aluminio]]+Tabela3[[#This Row],[Custo M.O. Total]]+Tabela3[[#This Row],[Custo Machos]]) -> 3971.5464 | AB134: =Tabela3[[#This Row],[Custo Total]]*Tabela3[[#This Row],[% Perda]] -> 198.57732 | AC134: =IFERROR(VLOOKUP(Tabela3[[#This Row],[Produto]],Tabela2[],2,0),0) -> 1 | AD134: =IFERROR(VLOOKUP(Tabela3[[#This Row],[Produto]],Tabela2[],3,0),0) -> 3.142 | AE134: =IFERROR(VLOOKUP(Tabela3[[#This Row],[Produto]],Tabela2[],4,0),0) -> 5.559 | AF134: =IFERROR(VLOOKUP(Tabela3[[#This Row],[Produto]],Tabela2[],5,0),0) -> 2.1753 | AG134: =IFERROR(VLOOKUP(Tabela3[[#This Row],[Produto]],Tabela2[],6,0),0) -> 0 | AH134: =IFERROR(VLOOKUP(Tabela3[[#This Row],[Produto]],Tabela2[],7,0),0) -> 0 | AI134: =IFERROR(VLOOKUP(Tabela3[[#This Row],[Produto]],Tabela2[],8,0),0) -> 0 | AJ134: =IFERROR(VLOOKUP(Tabela3[[#This Row],[Produto]],Tabela2[],13,0),0) -> 15.6 | AK134: =IFERROR(VLOOKUP(Tabela3[[#This Row],[Produto]],Tabela2[],14,0),0) -> Senun | AL134: =IFERROR(VLOOKUP(Tabela3[[#This Row],[Produto]],Tabela2[],15,0),0) -> 6.5 | AM134: =(Tabela3[[#This Row],[Custo Usinagem]]+Tabela3[[#This Row],[Custo / Pç]])*1.2 -> 91.411502 | AN134: =Tabela3[[#This Row],[Valor Mínimo Venda]]*1.15 -> 105.12323 | AO134: =Tabela3[[#This Row],[Tabela 1]]*1.08 -> 113.53309 | AP134: =Tabela3[[#This Row],[Tabela 2]]*1.15 -> 130.56305
A135: 45742 | B135: BRACINHO ARTICULADOR | C135: 6064 | D135: Marcelo Santos | E135: Claudio Henrique | F135: 27 | G135: 0.17083333 | H135: 0 | I135: =IFERROR(Tabela3[[#This Row],[Custo Total]]/Tabela3[[#This Row],[Aluminio Util]],0) -> 27.052939 | J135: =Tabela3[[#This Row],[Custo Total]]/Tabela3[[#This Row],[Realizado]] -> 13.526469 | K135: =IFERROR(Tabela3[[#This Row],[Qtde Cx Produzida]]/Tabela3[[#This Row],[Tempo]]/24,0) -> 6.5853659 | L135: =Tabela3[[#This Row],[Qtde Cx Produzida]]*Tabela3[[#This Row],[Qdt Peça Placa]] -> 108 | M135: =Tabela3[[#This Row],[Previsto]]-Tabela3[[#This Row],[Perda Pçs]] -> 108 | N135: =IFERROR(Tabela3[[#This Row],[Perda Pçs]]/Tabela3[[#This Row],[Previsto]],0) -> 0 | O135: =IFERROR(IF(Tabela3[[#This Row],[Qtde Cx Produzida]] <> 0, Tabela3[[#This Row],[Tempo]] / Tabela3[[#This Row],[Qtde Cx Produzida]], 0),0) -> 0.0063271605 | P135: =IFERROR(Tabela3[[#This Row],[Perda Pçs]]/Tabela3[[#This Row],[Qdt Peça Placa]],0) -> 0 | Q135: =IFERROR(Tabela3[[#This Row],[Realizado]]*Tabela3[[#This Row],[Peso Util/Pç]],0) -> 54 | R135: =IFERROR(Tabela3[[#This Row],[Peso Total Galho]]*Tabela3[[#This Row],[Qtde Cx Produzida]]*1.055,0) -> 91.152 | S135: =(Tabela3[[#This Row],[Aluminio Bruto]]-Tabela3[[#This Row],[Aluminio Util]])*0.9 -> 33.4368 | T135: =Tabela3[[#This Row],[Aluminio Bruto]]/OleoKGAluminio -> 38.347529 | U135: =IFERROR((VLOOKUP(Tabela3[[#This Row],[Moldador]],Tabela1[],5,)+(VLOOKUP(Tabela3[[#This Row],[Ajudante]],Tabela1[],5,))*3.5),0) -> 99.950346 | V135: =IFERROR(Tabela3[[#This Row],[Custo M.O. / H]]/((Tabela3[[#This Row],[Realizado]]/Tabela3[[#This Row],[Qdt Peça Placa]])/Tabela3[[#This Row],[Tempo]]/24),) -> 15.177645 | W135: =Tabela3[[#This Row],[Custo / Cx Moldada]]*Tabela3[[#This Row],[Qtde Cx Produzida]] -> 409.79642 | X135: =Tabela3[[#This Row],[Aluminio Util]]*Tabela3[[#This Row],[Custo/Kg]] -> 950.4 | Y135: =IFERROR(VLOOKUP(Tabela3[[#This Row],[Data]],Tabela461213[],2,1)*(Tabela3[[#This Row],[Qtde Cx Produzida]]*Tabela3[[#This Row],[Qde macho / CX]]*Tabela3[[#This Row],[Peso Macho]]),) -> 0 | Z135: =IFERROR(Tabela3[[#This Row],[Qtde Oleo]]*(VLOOKUP(Tabela3[[#This Row],[Data]],CompraOleo[],3,TRUE))*1.05,0) -> 100.66226 | AA135: =(Tabela3[[#This Row],[Custo Oleo]]+Tabela3[[#This Row],[Custo Aluminio]]+Tabela3[[#This Row],[Custo M.O. Total]]+Tabela3[[#This Row],[Custo Machos]]) -> 1460.8587 | AB135: =Tabela3[[#This Row],[Custo Total]]*Tabela3[[#This Row],[% Perda]] -> 0 | AC135: =IFERROR(VLOOKUP(Tabela3[[#This Row],[Produto]],Tabela2[],2,0),0) -> 4 | AD135: =IFERROR(VLOOKUP(Tabela3[[#This Row],[Produto]],Tabela2[],3,0),0) -> 0.5 | AE135: =IFERROR(VLOOKUP(Tabela3[[#This Row],[Produto]],Tabela2[],4,0),0) -> 3.2 | AF135: =IFERROR(VLOOKUP(Tabela3[[#This Row],[Produto]],Tabela2[],5,0),0) -> 1.08 | AG135: =IFERROR(VLOOKUP(Tabela3[[#This Row],[Produto]],Tabela2[],6,0),0) -> 0 | AH135: =IFERROR(VLOOKUP(Tabela3[[#This Row],[Produto]],Tabela2[],7,0),0) -> 0 | AI135: =IFERROR(VLOOKUP(Tabela3[[#This Row],[Produto]],Tabela2[],8,0),0) -> 0 | AJ135: =IFERROR(VLOOKUP(Tabela3[[#This Row],[Produto]],Tabela2[],13,0),0) -> 17.6 | AK135: =IFERROR(VLOOKUP(Tabela3[[#This Row],[Produto]],Tabela2[],14,0),0) -> Marcelo | AL135: =IFERROR(VLOOKUP(Tabela3[[#This Row],[Produto]],Tabela2[],15,0),0) -> 0 | AM135: =(Tabela3[[#This Row],[Custo Usinagem]]+Tabela3[[#This Row],[Custo / Pç]])*1.2 -> 16.231763 | AN135: =Tabela3[[#This Row],[Valor Mínimo Venda]]*1.15 -> 18.666528 | AO135: =Tabela3[[#This Row],[Tabela 1]]*1.08 -> 20.15985 | AP135: =Tabela3[[#This Row],[Tabela 2]]*1.15 -> 23.183827
A136: 45742 | B136: Chapa Churrasqueira 1 Fogareiro - Fundido | C136: 6076 | D136: Marcelo Santos | E136: Claudio Henrique | F136: 39 | G136: 0.17638889 | H136: 0 | I136: =IFERROR(Tabela3[[#This Row],[Custo Total]]/Tabela3[[#This Row],[Aluminio Util]],0) -> 24.958918 | J136: =Tabela3[[#This Row],[Custo Total]]/Tabela3[[#This Row],[Realizado]] -> 34.992402 | K136: =IFERROR(Tabela3[[#This Row],[Qtde Cx Produzida]]/Tabela3[[#This Row],[Tempo]]/24,0) -> 9.2125984 | L136: =Tabela3[[#This Row],[Qtde Cx Produzida]]*Tabela3[[#This Row],[Qdt Peça Placa]] -> 39 | M136: =Tabela3[[#This Row],[Previsto]]-Tabela3[[#This Row],[Perda Pçs]] -> 39 | N136: =IFERROR(Tabela3[[#This Row],[Perda Pçs]]/Tabela3[[#This Row],[Previsto]],0) -> 0 | O136: =IFERROR(IF(Tabela3[[#This Row],[Qtde Cx Produzida]] <> 0, Tabela3[[#This Row],[Tempo]] / Tabela3[[#This Row],[Qtde Cx Produzida]], 0),0) -> 0.004522792 | P136: =IFERROR(Tabela3[[#This Row],[Perda Pçs]]/Tabela3[[#This Row],[Qdt Peça Placa]],0) -> 0 | Q136: =IFERROR(Tabela3[[#This Row],[Realizado]]*Tabela3[[#This Row],[Peso Util/Pç]],0) -> 54.678 | R136: =IFERROR(Tabela3[[#This Row],[Peso Total Galho]]*Tabela3[[#This Row],[Qtde Cx Produzida]]*1.055,0) -> 80.23275 | S136: =(Tabela3[[#This Row],[Aluminio Bruto]]-Tabela3[[#This Row],[Aluminio Util]])*0.9 -> 22.999275 | T136: =Tabela3[[#This Row],[Aluminio Bruto]]/OleoKGAluminio -> 33.753814 | U136: =IFERROR((VLOOKUP(Tabela3[[#This Row],[Moldador]],Tabela1[],5,)+(VLOOKUP(Tabela3[[#This Row],[Ajudante]],Tabela1[],5,))*3.5),0) -> 99.950346 | V136: =IFERROR(Tabela3[[#This Row],[Custo M.O. / H]]/((Tabela3[[#This Row],[Realizado]]/Tabela3[[#This Row],[Qdt Peça Placa]])/Tabela3[[#This Row],[Tempo]]/24),) -> 10.849311 | W136: =Tabela3[[#This Row],[Custo / Cx Moldada]]*Tabela3[[#This Row],[Qtde Cx Produzida]] -> 423.12313 | X136: =Tabela3[[#This Row],[Aluminio Util]]*Tabela3[[#This Row],[Custo/Kg]] -> 852.9768 | Y136: =IFERROR(VLOOKUP(Tabela3[[#This Row],[Data]],Tabela461213[],2,1)*(Tabela3[[#This Row],[Qtde Cx Produzida]]*Tabela3[[#This Row],[Qde macho / CX]]*Tabela3[[#This Row],[Peso Macho]]),) -> 0 | Z136: =IFERROR(Tabela3[[#This Row],[Qtde Oleo]]*(VLOOKUP(Tabela3[[#This Row],[Data]],CompraOleo[],3,TRUE))*1.05,0) -> 88.603762 | AA136: =(Tabela3[[#This Row],[Custo Oleo]]+Tabela3[[#This Row],[Custo Aluminio]]+Tabela3[[#This Row],[Custo M.O. Total]]+Tabela3[[#This Row],[Custo Machos]]) -> 1364.7037 | AB136: =Tabela3[[#This Row],[Custo Total]]*Tabela3[[#This Row],[% Perda]] -> 0 | AC136: =IFERROR(VLOOKUP(Tabela3[[#This Row],[Produto]],Tabela2[],2,0),0) -> 1 | AD136: =IFERROR(VLOOKUP(Tabela3[[#This Row],[Produto]],Tabela2[],3,0),0) -> 1.402 | AE136: =IFERROR(VLOOKUP(Tabela3[[#This Row],[Produto]],Tabela2[],4,0),0) -> 1.95 | AF136: =IFERROR(VLOOKUP(Tabela3[[#This Row],[Produto]],Tabela2[],5,0),0) -> 0.4932 | AG136: =IFERROR(VLOOKUP(Tabela3[[#This Row],[Produto]],Tabela2[],6,0),0) -> 0 | AH136: =IFERROR(VLOOKUP(Tabela3[[#This Row],[Produto]],Tabela2[],7,0),0) -> 0 | AI136: =IFERROR(VLOOKUP(Tabela3[[#This Row],[Produto]],Tabela2[],8,0),0) -> 0 | AJ136: =IFERROR(VLOOKUP(Tabela3[[#This Row],[Produto]],Tabela2[],13,0),0) -> 15.6 | AK136: =IFERROR(VLOOKUP(Tabela3[[#This Row],[Produto]],Tabela2[],14,0),0) -> Senun | AL136: =IFERROR(VLOOKUP(Tabela3[[#This Row],[Produto]],Tabela2[],15,0),0) -> 6 | AM136: =(Tabela3[[#This Row],[Custo Usinagem]]+Tabela3[[#This Row],[Custo / Pç]])*1.2 -> 49.190883 | AN136: =Tabela3[[#This Row],[Valor Mínimo Venda]]*1.15 -> 56.569515 | AO136: =Tabela3[[#This Row],[Tabela 1]]*1.08 -> 61.095077 | AP136: =Tabela3[[#This Row],[Tabela 2]]*1.15 -> 70.259338
A137: 45743 | B137: Chapa Churrasqueira 1 Fogareiro - Fundido | C137: 6076 | D137: Marcelo Santos | E137: Claudio Henrique | F137: 16 | G137: 0.068055556 | H137: 0 | I137: =IFERROR(Tabela3[[#This Row],[Custo Total]]/Tabela3[[#This Row],[Aluminio Util]],0) -> 24.498114 | J137: =Tabela3[[#This Row],[Custo Total]]/Tabela3[[#This Row],[Realizado]] -> 34.346356 | K137: =IFERROR(Tabela3[[#This Row],[Qtde Cx Produzida]]/Tabela3[[#This Row],[Tempo]]/24,0) -> 9.7959184 | L137: =Tabela3[[#This Row],[Qtde Cx Produzida]]*Tabela3[[#This Row],[Qdt Peça Placa]] -> 16 | M137: =Tabela3[[#This Row],[Previsto]]-Tabela3[[#This Row],[Perda Pçs]] -> 16 | N137: =IFERROR(Tabela3[[#This Row],[Perda Pçs]]/Tabela3[[#This Row],[Previsto]],0) -> 0 | O137: =IFERROR(IF(Tabela3[[#This Row],[Qtde Cx Produzida]] <> 0, Tabela3[[#This Row],[Tempo]] / Tabela3[[#This Row],[Qtde Cx Produzida]], 0),0) -> 0.0042534722 | P137: =IFERROR(Tabela3[[#This Row],[Perda Pçs]]/Tabela3[[#This Row],[Qdt Peça Placa]],0) -> 0 | Q137: =IFERROR(Tabela3[[#This Row],[Realizado]]*Tabela3[[#This Row],[Peso Util/Pç]],0) -> 22.432 | R137: =IFERROR(Tabela3[[#This Row],[Peso Total Galho]]*Tabela3[[#This Row],[Qtde Cx Produzida]]*1.055,0) -> 32.916 | S137: =(Tabela3[[#This Row],[Aluminio Bruto]]-Tabela3[[#This Row],[Aluminio Util]])*0.9 -> 9.4356 | T137: =Tabela3[[#This Row],[Aluminio Bruto]]/OleoKGAluminio -> 13.847719 | U137: =IFERROR((VLOOKUP(Tabela3[[#This Row],[Moldador]],Tabela1[],5,)+(VLOOKUP(Tabela3[[#This Row],[Ajudante]],Tabela1[],5,))*3.5),0) -> 99.950346 | V137: =IFERROR(Tabela3[[#This Row],[Custo M.O. / H]]/((Tabela3[[#This Row],[Realizado]]/Tabela3[[#This Row],[Qdt Peça Placa]])/Tabela3[[#This Row],[Tempo]]/24),) -> 10.203264 | W137: =Tabela3[[#This Row],[Custo / Cx Moldada]]*Tabela3[[#This Row],[Qtde Cx Produzida]] -> 163.25223 | X137: =Tabela3[[#This Row],[Aluminio Util]]*Tabela3[[#This Row],[Custo/Kg]] -> 349.9392 | Y137: =IFERROR(VLOOKUP(Tabela3[[#This Row],[Data]],Tabela461213[],2,1)*(Tabela3[[#This Row],[Qtde Cx Produzida]]*Tabela3[[#This Row],[Qde macho / CX]]*Tabela3[[#This Row],[Peso Macho]]),) -> 0 | Z137: =IFERROR(Tabela3[[#This Row],[Qtde Oleo]]*(VLOOKUP(Tabela3[[#This Row],[Data]],CompraOleo[],3,TRUE))*1.05,0) -> 36.350261 | AA137: =(Tabela3[[#This Row],[Custo Oleo]]+Tabela3[[#This Row],[Custo Aluminio]]+Tabela3[[#This Row],[Custo M.O. Total]]+Tabela3[[#This Row],[Custo Machos]]) -> 549.54169 | AB137: =Tabela3[[#This Row],[Custo Total]]*Tabela3[[#This Row],[% Perda]] -> 0 | AC137: =IFERROR(VLOOKUP(Tabela3[[#This Row],[Produto]],Tabela2[],2,0),0) -> 1 | AD137: =IFERROR(VLOOKUP(Tabela3[[#This Row],[Produto]],Tabela2[],3,0),0) -> 1.402 | AE137: =IFERROR(VLOOKUP(Tabela3[[#This Row],[Produto]],Tabela2[],4,0),0) -> 1.95 | AF137: =IFERROR(VLOOKUP(Tabela3[[#This Row],[Produto]],Tabela2[],5,0),0) -> 0.4932 | AG137: =IFERROR(VLOOKUP(Tabela3[[#This Row],[Produto]],Tabela2[],6,0),0) -> 0 | AH137: =IFERROR(VLOOKUP(Tabela3[[#This Row],[Produto]],Tabela2[],7,0),0) -> 0 | AI137: =IFERROR(VLOOKUP(Tabela3[[#This Row],[Produto]],Tabela2[],8,0),0) -> 0 | AJ137: =IFERROR(VLOOKUP(Tabela3[[#This Row],[Produto]],Tabela2[],13,0),0) -> 15.6 | AK137: =IFERROR(VLOOKUP(Tabela3[[#This Row],[Produto]],Tabela2[],14,0),0) -> Senun | AL137: =IFERROR(VLOOKUP(Tabela3[[#This Row],[Produto]],Tabela2[],15,0),0) -> 6 | AM137: =(Tabela3[[#This Row],[Custo Usinagem]]+Tabela3[[#This Row],[Custo / Pç]])*1.2 -> 48.415627 | AN137: =Tabela3[[#This Row],[Valor Mínimo Venda]]*1.15 -> 55.677971 | AO137: =Tabela3[[#This Row],[Tabela 1]]*1.08 -> 60.132209 | AP137: =Tabela3[[#This Row],[Tabela 2]]*1.15 -> 69.15204
